Workbook

Sheet Matriz de riesgo SD
A1: Codigo | B1: Responsables | C1: Proceso | D1: AreasTrabajo | E1: AvancePlanificado | F1: AvanceReal | G1: Descripcion | H1: FechaInicio | I1: FechaVencimiento
A2: SD 2187 | B2: Lizama Donoso Andrés A. (AALIZAMA@collahuasi.cl);Melo Miranda Fernando A. (FMELO@collahuasi.cl);Meriño Martinez Máximo E. (MEMERINO@collahuasi.cl) | C2: Puerto | D2: Planta Filtros | E2: 0 | F2: 0 | G2: Mantención Sementral 310FL002 | H2: =Tareas!$H$2 -> 43992 | I2: 44034

Sheet Tareas
A1: Nombre de tarea | B1: Ponderacion | C1: Asignado a | D1: Actividad | E1: AvancePlanificado | F1: AvanceReal | G1: Descripción | H1: Fecha de inicio | I1: Fecha de vencimiento | J1: Activo | K1: Validada | L1: Comentarios | M1: ID | N1: FREC | O1: DURACIÓN
A2: 01 Creacion y difusion Matriz de riesgo SD Mantención | B2: =IF(Tareas[[#This Row],[ID]]=1,100/SUM($M$2:$M$24),0) -> 4.7619048 | C2: Meriño Martinez Máximo E. (MEMERINO@collahuasi.cl) | D2: A. PLANIFICACION DEL MANTENIMIENTO | E2: =(IF(I2<=TODAY(),1,0))*B2 -> 4.7619048 | F2: 4.8 | H2: =I2-O2 -> 43992 | I2: ='Matriz de riesgo SD'!$I$2-N2 -> 43994 | J2: Sí | K2: 0 | M2: =IF(Tareas[[#This Row],[Activo]]="sí",1,0) -> 1 | N2: 40 | O2: 2
A3: 02 Revision Aprendizajes (caja 6) mantención anterior | B3: =IF(Tareas[[#This Row],[ID]]=1,100/SUM($M$2:$M$24),0) -> 4.7619048 | C3: Meriño Martinez Máximo E. (MEMERINO@collahuasi.cl) | D3: A. PLANIFICACION DEL MANTENIMIENTO | E3: =(IF(I3<=TODAY(),1,0))*B3 -> 4.7619048 | F3: 4.8 | H3: =I3-O3 -> 43992 | I3: ='Matriz de riesgo SD'!$I$2-N3 -> 43994 | J3: Sí | K3: 0 | M3: =IF(Tareas[[#This Row],[Activo]]="sí",1,0) -> 1 | N3: 40 | O3: 2
A4: 03 Generacion de carta gantt base para mantencion | B4: =IF(Tareas[[#This Row],[ID]]=1,100/SUM($M$2:$M$24),0) -> 4.7619048 | C4: Meriño Martinez Máximo E. (MEMERINO@collahuasi.cl) | D4: A. PLANIFICACION DEL MANTENIMIENTO | E4: =(IF(I4<=TODAY(),1,0))*B4 -> 4.7619048 | F4: 4.8 | H4: =I4-O4 -> 43990 | I4: ='Matriz de riesgo SD'!$I$2-N4 -> 43994 | J4: Sí | K4: 0 | L4: CARTA TIPO | M4: =IF(Tareas[[#This Row],[Activo]]="sí",1,0) -> 1 | N4: 40 | O4: 4
A5: 04 Revision de WR para mantencion | B5: =IF(Tareas[[#This Row],[ID]]=1,100/SUM($M$2:$M$24),0) -> 4.7619048 | C5: Meriño Martinez Máximo E. (MEMERINO@collahuasi.cl) | D5: A. PLANIFICACION DEL MANTENIMIENTO | E5: =(IF(I5<=TODAY(),1,0))*B5 -> 4.7619048 | F5: 4.8 | H5: =I5-O5 -> 44001 | I5: ='Matriz de riesgo SD'!$I$2-N5 -> 44004 | J5: Sí | K5: 0 | M5: =IF(Tareas[[#This Row],[Activo]]="sí",1,0) -> 1 | N5: 30 | O5: 3
A6: 05 Revision de MST para la mantención | B6: =IF(Tareas[[#This Row],[ID]]=1,100/SUM($M$2:$M$24),0) -> 4.7619048 | C6: Meriño Martinez Máximo E. (MEMERINO@collahuasi.cl) | D6: A. PLANIFICACION DEL MANTENIMIENTO | E6: =(IF(I6<=TODAY(),1,0))*B6 -> 4.7619048 | F6: 4.8 | H6: =I6-O6 -> 44001 | I6: ='Matriz de riesgo SD'!$I$2-N6 -> 44004 | J6: Sí | K6: 0 | M6: =IF(Tareas[[#This Row],[Activo]]="sí",1,0) -> 1 | N6: 30 | O6: 3
A7: 06 Revision de Backlog (Ots derivadas del corto plazo para Mantenciones SD) | B7: =IF(Tareas[[#This Row],[ID]]=1,100/SUM($M$2:$M$24),0) -> 0 | C7: Meriño Martinez Máximo E. (MEMERINO@collahuasi.cl) | D7: A. PLANIFICACION DEL MANTENIMIENTO | E7: =(IF(I7<=TODAY(),1,0))*B7 -> 0 | F7: 0 | H7: =I7-O7 -> 44001 | I7: ='Matriz de riesgo SD'!$I$2-N7 -> 44004 | J7: No | K7: 0 | M7: =IF(Tareas[[#This Row],[Activo]]="sí",1,0) -> 0 | N7: 30 | O7: 3
A8: 07 Recepcion actividades Proyectos (Formulario autorizado) | B8: =IF(Tareas[[#This Row],[ID]]=1,100/SUM($M$2:$M$24),0) -> 0 | C8: Meriño Martinez Máximo E. (MEMERINO@collahuasi.cl) | D8: A. PLANIFICACION DEL MANTENIMIENTO | E8: =(IF(I8<=TODAY(),1,0))*B8 -> 0 | F8: 0 | H8: =I8-O8 -> 44001 | I8: ='Matriz de riesgo SD'!$I$2-N8 -> 44004 | J8: No | K8: 0 | M8: =IF(Tareas[[#This Row],[Activo]]="sí",1,0) -> 0 | N8: 30 | O8: 3
A9: 08 Recepcion actividades desde WR (Formulario autorizado) | B9: =IF(Tareas[[#This Row],[ID]]=1,100/SUM($M$2:$M$24),0) -> 4.7619048 | C9: Meriño Martinez Máximo E. (MEMERINO@collahuasi.cl) | D9: A. PLANIFICACION DEL MANTENIMIENTO | E9: =(IF(I9<=TODAY(),1,0))*B9 -> 4.7619048 | F9: 4.8 | H9: =I9-O9 -> 44002 | I9: ='Matriz de riesgo SD'!$I$2-N9 -> 44004 | J9: Sí | K9: 0 | M9: =IF(Tareas[[#This Row],[Activo]]="sí",1,0) -> 1 | N9: 30 | O9: 2
A10: 09 Creacion de Ots Padres por equipos | B10: =IF(Tareas[[#This Row],[ID]]=1,100/SUM($M$2:$M$24),0) -> 4.7619048 | C10: Meriño Martinez Máximo E. (MEMERINO@collahuasi.cl) | D10: A. PLANIFICACION DEL MANTENIMIENTO | E10: =(IF(I10<=TODAY(),1,0))*B10 -> 4.7619048 | F10: 4.8 | H10: =I10-O10 -> 44003 | I10: ='Matriz de riesgo SD'!$I$2-N10 -> 44004 | J10: Sí | K10: 0 | M10: =IF(Tareas[[#This Row],[Activo]]="sí",1,0) -> 1 | N10: 30 | O10: 1
A11: 10 Creacion de Ordenes de trabajo y compromiso en ellipse para los Grupos | B11: =IF(Tareas[[#This Row],[ID]]=1,100/SUM($M$2:$M$24),0) -> 4.7619048 | C11: Meriño Martinez Máximo E. (MEMERINO@collahuasi.cl) | D11: A. PLANIFICACION DEL MANTENIMIENTO | E11: =(IF(I11<=TODAY(),1,0))*B11 -> 4.7619048 | F11: 4.8 | H11: =I11-O11 -> 44022 | I11: ='Matriz de riesgo SD'!$I$2-N11 -> 44023 | J11: Sí | K11: 0 | M11: =IF(Tareas[[#This Row],[Activo]]="sí",1,0) -> 1 | N11: 11 | O11: 1
A12: 11 Generar calendario de Hitos Planificacion Mantenimiento | B12: =IF(Tareas[[#This Row],[ID]]=1,100/SUM($M$2:$M$24),0) -> 4.7619048 | C12: Meriño Martinez Máximo E. (MEMERINO@collahuasi.cl) | D12: A. PLANIFICACION DEL MANTENIMIENTO | E12: =(IF(I12<=TODAY(),1,0))*B12 -> 4.7619048 | F12: 4.8 | H12: =I12-O12 -> 44003 | I12: ='Matriz de riesgo SD'!$I$2-N12 -> 44004 | J12: Sí | K12: 0 | M12: =IF(Tareas[[#This Row],[Activo]]="sí",1,0) -> 1 | N12: 30 | O12: 1
A13: 12 Preparacion de reportabilidad avances y curva "S" | B13: =IF(Tareas[[#This Row],[ID]]=1,100/SUM($M$2:$M$24),0) -> 4.7619048 | C13: Meriño Martinez Máximo E. (MEMERINO@collahuasi.cl) | D13: A. PLANIFICACION DEL MANTENIMIENTO | E13: =(IF(I13<=TODAY(),1,0))*B13 -> 4.7619048 | F13: 0 | H13: =I13-O13 -> 44023 | I13: ='Matriz de riesgo SD'!$I$2-N13 -> 44028 | J13: Sí | K13: 0 | M13: =IF(Tareas[[#This Row],[Activo]]="sí",1,0) -> 1 | N13: 6 | O13: 5
A14: 13 Generar y controlar "Mapa Requerimientos". | B14: =IF(Tareas[[#This Row],[ID]]=1,100/SUM($M$2:$M$24),0) -> 4.7619048 | C14: Meriño Martinez Máximo E. (MEMERINO@collahuasi.cl) | D14: A. PLANIFICACION DEL MANTENIMIENTO | E14: =(IF(I14<=TODAY(),1,0))*B14 -> 4.7619048 | F14: 4.8 | H14: =I14-O14 -> 44005 | I14: ='Matriz de riesgo SD'!$I$2-N14 -> 44006 | J14: Sí | K14: 0 | M14: =IF(Tareas[[#This Row],[Activo]]="sí",1,0) -> 1 | N14: 28 | O14: 1
A15: 14 Reunion: Definicion de Actividades de mantencion con involucrados por equipos | B15: =IF(Tareas[[#This Row],[ID]]=1,100/SUM($M$2:$M$24),0) -> 4.7619048 | C15: Meriño Martinez Máximo E. (MEMERINO@collahuasi.cl) | D15: A. PLANIFICACION DEL MANTENIMIENTO | E15: =(IF(I15<=TODAY(),1,0))*B15 -> 4.7619048 | F15: 4.8 | H15: =I15-O15 -> 44002 | I15: ='Matriz de riesgo SD'!$I$2-N15 -> 44004 | J15: Sí | K15: 0 | M15: =IF(Tareas[[#This Row],[Activo]]="sí",1,0) -> 1 | N15: 30 | O15: 2
A16: 15 Envio carta gantt en revision preliminar - Rev. A-B-C | B16: =IF(Tareas[[#This Row],[ID]]=1,100/SUM($M$2:$M$24),0) -> 4.7619048 | C16: Meriño Martinez Máximo E. (MEMERINO@collahuasi.cl) | D16: A. PLANIFICACION DEL MANTENIMIENTO | E16: =(IF(I16<=TODAY(),1,0))*B16 -> 4.7619048 | F16: 4.8 | H16: =I16-O16 -> 44005 | I16: ='Matriz de riesgo SD'!$I$2-N16 -> 44006 | J16: Sí | K16: 0 | M16: =IF(Tareas[[#This Row],[Activo]]="sí",1,0) -> 1 | N16: 28 | O16: 1
... A24: 23 Retiro de Ots del programa por parte de CMDIC y ESED ejecutantes | B24: =IF(Tareas[[#This Row],[ID]]=1,100/SUM($M$2:$M$24),0) -> 4.7619048 | C24: Hurtado Olcay Marcelo S (MSHURTADO@collahuasi.cl) | D24: A. PLANIFICACION DEL MANTENIMIENTO | E24: =(IF(I24<=TODAY(),1,0))*B24 -> 4.7619048 | F24: 0 | H24: =I24-O24 -> 44021 | I24: ='Matriz de riesgo SD'!$I$2-N24 -> 44022 | J24: Sí | K24: 0 | M24: =IF(Tareas[[#This Row],[Activo]]="sí",1,0) -> 1 | N24: 12 | O24: 1
A25: 01 Revision y confirmacion de actividades programadas - ELECTRICOS | B25: =IF(Tareas[[#This Row],[ID]]=1,100/SUM($M$25:$M$32),0) -> 25 | C25: Hurtado Olcay Marcelo S (MSHURTADO@collahuasi.cl) | D25: B. REVISION Y VALIDACION ACTIVIDADES PROGRAMADAS | E25: =(IF(I25<=TODAY(),1,0))*B25 -> 25 | F25: 25 | H25: =I25-O25 -> 44001 | I25: ='Matriz de riesgo SD'!$I$2-N25 -> 44004 | J25: Sí | K25: 0 | M25: =IF(Tareas[[#This Row],[Activo]]="sí",1,0) -> 1 | N25: 30 | O25: 3
A26: 02 Revision y confirmacion de actividades programadas - DCS | B26: =IF(Tareas[[#This Row],[ID]]=1,100/SUM($M$25:$M$32),0) -> 0 | C26: Hurtado Olcay Marcelo S (MSHURTADO@collahuasi.cl) | D26: B. REVISION Y VALIDACION ACTIVIDADES PROGRAMADAS | E26: =(IF(I26<=TODAY(),1,0))*B26 -> 0 | F26: 0 | H26: =I26-O26 -> 44001 | I26: ='Matriz de riesgo SD'!$I$2-N26 -> 44004 | J26: No | K26: 0 | M26: =IF(Tareas[[#This Row],[Activo]]="sí",1,0) -> 0 | N26: 30 | O26: 3
A27: 03 Revision y confirmacion de actividades programadas - INSTRUMENTACION | B27: =IF(Tareas[[#This Row],[ID]]=1,100/SUM($M$25:$M$32),0) -> 25 | C27: Hurtado Olcay Marcelo S (MSHURTADO@collahuasi.cl) | D27: B. REVISION Y VALIDACION ACTIVIDADES PROGRAMADAS | E27: =(IF(I27<=TODAY(),1,0))*B27 -> 25 | F27: 25 | H27: =I27-O27 -> 44001 | I27: ='Matriz de riesgo SD'!$I$2-N27 -> 44004 | J27: Sí | K27: 0 | M27: =IF(Tareas[[#This Row],[Activo]]="sí",1,0) -> 1 | N27: 30 | O27: 3
A28: 04 Revision y confirmacion de actividades programadas - MECANICOS | B28: =IF(Tareas[[#This Row],[ID]]=1,100/SUM($M$25:$M$32),0) -> 25 | C28: Hurtado Olcay Marcelo S (MSHURTADO@collahuasi.cl) | D28: B. REVISION Y VALIDACION ACTIVIDADES PROGRAMADAS | E28: =(IF(I28<=TODAY(),1,0))*B28 -> 25 | F28: 25 | H28: =I28-O28 -> 44001 | I28: ='Matriz de riesgo SD'!$I$2-N28 -> 44004 | J28: Sí | K28: 0 | M28: =IF(Tareas[[#This Row],[Activo]]="sí",1,0) -> 1 | N28: 30 | O28: 3
A29: 05 Revision y confirmacion de actividades programadas - LUBRICACION | B29: =IF(Tareas[[#This Row],[ID]]=1,100/SUM($M$25:$M$32),0) -> 25 | C29: Hurtado Olcay Marcelo S (MSHURTADO@collahuasi.cl) | D29: B. REVISION Y VALIDACION ACTIVIDADES PROGRAMADAS | E29: =(IF(I29<=TODAY(),1,0))*B29 -> 25 | F29: 25 | H29: =I29-O29 -> 44001 | I29: ='Matriz de riesgo SD'!$I$2-N29 -> 44004 | J29: Sí | K29: 0 | M29: =IF(Tareas[[#This Row],[Activo]]="sí",1,0) -> 1 | N29: 30 | O29: 3
A30: 06 Revision y confirmacion de actividades programadas - PREDICTIVO / CONFIABILIDAD | B30: =IF(Tareas[[#This Row],[ID]]=1,100/SUM($M$25:$M$32),0) -> 0 | C30: Meriño Martinez Máximo E. (MEMERINO@collahuasi.cl) | D30: B. REVISION Y VALIDACION ACTIVIDADES PROGRAMADAS | E30: =(IF(I30<=TODAY(),1,0))*B30 -> 0 | F30: 0 | H30: =I30-O30 -> 44001 | I30: ='Matriz de riesgo SD'!$I$2-N30 -> 44004 | J30: No | K30: 0 | M30: =IF(Tareas[[#This Row],[Activo]]="sí",1,0) -> 0 | N30: 30 | O30: 3
A31: 07 Revision y confirmacion de actividades programadas - METALURGIA | B31: =IF(Tareas[[#This Row],[ID]]=1,100/SUM($M$25:$M$32),0) -> 0 | C31: Meriño Martinez Máximo E. (MEMERINO@collahuasi.cl) | D31: B. REVISION Y VALIDACION ACTIVIDADES PROGRAMADAS | E31: =(IF(I31<=TODAY(),1,0))*B31 -> 0 | F31: 0 | H31: =I31-O31 -> 44001 | I31: ='Matriz de riesgo SD'!$I$2-N31 -> 44004 | J31: No | K31: 0 | M31: =IF(Tareas[[#This Row],[Activo]]="sí",1,0) -> 0 | N31: 30 | O31: 3
A32: 08 Revision y confirmacion de actividades programadas - PROYECTOS | B32: =IF(Tareas[[#This Row],[ID]]=1,100/SUM($M$25:$M$32),0) -> 0 | C32: Meriño Martinez Máximo E. (MEMERINO@collahuasi.cl) | D32: B. REVISION Y VALIDACION ACTIVIDADES PROGRAMADAS | E32: =(IF(I32<=TODAY(),1,0))*B32 -> 0 | F32: 0 | H32: =I32-O32 -> 44001 | I32: ='Matriz de riesgo SD'!$I$2-N32 -> 44004 | J32: No | K32: 0 | M32: =IF(Tareas[[#This Row],[Activo]]="sí",1,0) -> 0 | N32: 30 | O32: 3
A33: 01 Revision de Registros de incidentes SSO, mantenciones anteriores | B33: =IF(Tareas[[#This Row],[ID]]=1,100/SUM($M$33:$M$46),0) -> 9.0909091 | C33: Meriño Martinez Máximo E. (MEMERINO@collahuasi.cl) | D33: C. GESTION DE SEGURIDAD Y SALUD | E33: =(IF(I33<=TODAY(),1,0))*B33 -> 9.0909091 | F33: 9.1 | H33: =I33-O33 -> 43992 | I33: ='Matriz de riesgo SD'!$I$2-N33 -> 43994 | J33: Sí | K33: 0 | M33: =IF(Tareas[[#This Row],[Activo]]="sí",1,0) -> 1 | N33: 40 | O33: 2
A34: 02 Programa de trabajo Seguridad y Salud | B34: =IF(Tareas[[#This Row],[ID]]=1,100/SUM($M$33:$M$46),0) -> 9.0909091 | C34: Meriño Martinez Máximo E. (MEMERINO@collahuasi.cl) | D34: C. GESTION DE SEGURIDAD Y SALUD | E34: =(IF(I34<=TODAY(),1,0))*B34 -> 9.0909091 | F34: 9.1 | H34: =I34-O34 -> 43991 | I34: ='Matriz de riesgo SD'!$I$2-N34 -> 43994 | J34: Sí | K34: 0 | M34: =IF(Tareas[[#This Row],[Activo]]="sí",1,0) -> 1 | N34: 40 | O34: 3
A35: 03 Reunion N°1 - Gestion de Riesgos asociados a la Mantencion | B35: =IF(Tareas[[#This Row],[ID]]=1,100/SUM($M$33:$M$46),0) -> 9.0909091 | C35: Meriño Martinez Máximo E. (MEMERINO@collahuasi.cl) | D35: C. GESTION DE SEGURIDAD Y SALUD | E35: =(IF(I35<=TODAY(),1,0))*B35 -> 9.0909091 | F35: 9.1 | H35: =I35-O35 -> 44003 | I35: ='Matriz de riesgo SD'!$I$2-N35 -> 44004 | J35: Sí | K35: 0 | M35: =IF(Tareas[[#This Row],[Activo]]="sí",1,0) -> 1 | N35: 30 | O35: 1
A36: 04 Reunion N°2 - Gestion de Riesgos asociados a la Mantencion | B36: =IF(Tareas[[#This Row],[ID]]=1,100/SUM($M$33:$M$46),0) -> 9.0909091 | C36: Meriño Martinez Máximo E. (MEMERINO@collahuasi.cl) | D36: C. GESTION DE SEGURIDAD Y SALUD | E36: =(IF(I36<=TODAY(),1,0))*B36 -> 9.0909091 | F36: 0 | H36: =I36-O36 -> 44021 | I36: ='Matriz de riesgo SD'!$I$2-N36 -> 44022 | J36: Sí | K36: 0 | M36: =IF(Tareas[[#This Row],[Activo]]="sí",1,0) -> 1 | N36: 12 | O36: 1
A37: 05 Revision, actualización de diagramas de bloqueo | B37: =IF(Tareas[[#This Row],[ID]]=1,100/SUM($M$33:$M$46),0) -> 9.0909091 | C37: Meriño Martinez Máximo E. (MEMERINO@collahuasi.cl) | D37: C. GESTION DE SEGURIDAD Y SALUD | E37: =(IF(I37<=TODAY(),1,0))*B37 -> 9.0909091 | F37: 0 | H37: =I37-O37 -> 44013 | I37: ='Matriz de riesgo SD'!$I$2-N37 -> 44014 | J37: Sí | K37: 0 | M37: =IF(Tareas[[#This Row],[Activo]]="sí",1,0) -> 1 | N37: 20 | O37: 1
A38: 06 Envio Plan de bloqueo | B38: =IF(Tareas[[#This Row],[ID]]=1,100/SUM($M$33:$M$46),0) -> 9.0909091 | C38: Meriño Martinez Máximo E. (MEMERINO@collahuasi.cl) | D38: C. GESTION DE SEGURIDAD Y SALUD | E38: =(IF(I38<=TODAY(),1,0))*B38 -> 9.0909091 | F38: 0 | H38: =I38-O38 -> 44015 | I38: ='Matriz de riesgo SD'!$I$2-N38 -> 44016 | J38: Sí | K38: 0 | M38: =IF(Tareas[[#This Row],[Activo]]="sí",1,0) -> 1 | N38: 18 | O38: 1
A39: 07 Reunion de Bloqueo | B39: =IF(Tareas[[#This Row],[ID]]=1,100/SUM($M$33:$M$46),0) -> 9.0909091 | C39: Meriño Martinez Máximo E. (MEMERINO@collahuasi.cl) | D39: C. GESTION DE SEGURIDAD Y SALUD | E39: =(IF(I39<=TODAY(),1,0))*B39 -> 9.0909091 | F39: 0 | H39: =I39-O39 -> 44022 | I39: ='Matriz de riesgo SD'!$I$2-N39 -> 44023 | J39: Sí | K39: 0 | M39: =IF(Tareas[[#This Row],[Activo]]="sí",1,0) -> 1 | N39: 11 | O39: 1
A40: 08 Validación de actividades en Matriz de Riesgo y sus controles / ELECTRICOS | B40: =IF(Tareas[[#This Row],[ID]]=1,100/SUM($M$33:$M$46),0) -> 9.0909091 | C40: Hurtado Olcay Marcelo S (MSHURTADO@collahuasi.cl) | D40: C. GESTION DE SEGURIDAD Y SALUD | E40: =(IF(I40<=TODAY(),1,0))*B40 -> 9.0909091 | F40: 0 | H40: =I40-O40 -> 44021 | I40: ='Matriz de riesgo SD'!$I$2-N40 -> 44022 | J40: Sí | K40: 0 | M40: =IF(Tareas[[#This Row],[Activo]]="sí",1,0) -> 1 | N40: 12 | O40: 1
A41: 09 Validación de actividades en Matriz de Riesgo y sus controles / DCS | B41: =IF(Tareas[[#This Row],[ID]]=1,100/SUM($M$33:$M$46),0) -> 0 | C41: Hurtado Olcay Marcelo S (MSHURTADO@collahuasi.cl) | D41: C. GESTION DE SEGURIDAD Y SALUD | E41: =(IF(I41<=TODAY(),1,0))*B41 -> 0 | F41: 0 | H41: =I41-O41 -> 44017 | I41: ='Matriz de riesgo SD'!$I$2-N41 -> 44018 | J41: No | K41: 0 | M41: =IF(Tareas[[#This Row],[Activo]]="sí",1,0) -> 0 | N41: 16 | O41: 1
A42: 10 Validación de actividades en Matriz de Riesgo y sus controles / INSTRUMENTACION | B42: =IF(Tareas[[#This Row],[ID]]=1,100/SUM($M$33:$M$46),0) -> 9.0909091 | C42: Hurtado Olcay Marcelo S (MSHURTADO@collahuasi.cl) | D42: C. GESTION DE SEGURIDAD Y SALUD | E42: =(IF(I42<=TODAY(),1,0))*B42 -> 9.0909091 | F42: 0 | H42: =I42-O42 -> 44017 | I42: ='Matriz de riesgo SD'!$I$2-N42 -> 44018 | J42: Sí | K42: 0 | M42: =IF(Tareas[[#This Row],[Activo]]="sí",1,0) -> 1 | N42: 16 | O42: 1
A43: 11 Validación de actividades en Matriz de Riesgo y sus controles / MECANICOS | B43: =IF(Tareas[[#This Row],[ID]]=1,100/SUM($M$33:$M$46),0) -> 9.0909091 | C43: Hurtado Olcay Marcelo S (MSHURTADO@collahuasi.cl) | D43: C. GESTION DE SEGURIDAD Y SALUD | E43: =(IF(I43<=TODAY(),1,0))*B43 -> 9.0909091 | F43: 0 | H43: =I43-O43 -> 44017 | I43: ='Matriz de riesgo SD'!$I$2-N43 -> 44018 | J43: Sí | K43: 0 | M43: =IF(Tareas[[#This Row],[Activo]]="sí",1,0) -> 1 | N43: 16 | O43: 1
A44: 12 Validación de actividades en Matriz de Riesgo y sus controles / LUBRICACION | B44: =IF(Tareas[[#This Row],[ID]]=1,100/SUM($M$33:$M$46),0) -> 9.0909091 | C44: Hurtado Olcay Marcelo S (MSHURTADO@collahuasi.cl) | D44: C. GESTION DE SEGURIDAD Y SALUD | E44: =(IF(I44<=TODAY(),1,0))*B44 -> 9.0909091 | F44: 0 | H44: =I44-O44 -> 44017 | I44: ='Matriz de riesgo SD'!$I$2-N44 -> 44018 | J44: Sí | K44: 0 | M44: =IF(Tareas[[#This Row],[Activo]]="sí",1,0) -> 1 | N44: 16 | O44: 1
... A46: 14 Validación de actividades en Matriz de Riesgo y sus controles / OPERACIONES | B46: =IF(Tareas[[#This Row],[ID]]=1,100/SUM($M$33:$M$46),0) -> 0 | C46: Meriño Martinez Máximo E. (MEMERINO@collahuasi.cl) | D46: C. GESTION DE SEGURIDAD Y SALUD | E46: =(IF(I46<=TODAY(),1,0))*B46 -> 0 | F46: 0 | H46: =I46-O46 -> 44013 | I46: ='Matriz de riesgo SD'!$I$2-N46 -> 44014 | J46: No | K46: 0 | M46: =IF(Tareas[[#This Row],[Activo]]="sí",1,0) -> 0 | N46: 20 | O46: 1
A47: 01 Plan Gestion de Residuos mantención | B47: =IF(Tareas[[#This Row],[ID]]=1,100/SUM($M$47:$M$50),0) -> 50 | C47: Hurtado Olcay Marcelo S (MSHURTADO@collahuasi.cl) | D47: D. GESTION MEDIO AMBIENTE | E47: =(IF(I47<=TODAY(),1,0))*B47 -> 50 | F47: 50 | H47: =I47-O47 -> 43998 | I47: ='Matriz de riesgo SD'!$I$2-N47 -> 43999 | J47: Sí | K47: 0 | M47: =IF(Tareas[[#This Row],[Activo]]="sí",1,0) -> 1 | N47: 35 | O47: 1
A48: 02 Solicitud de contenedor de residuos y layout de ubicación en Planta | B48: =IF(Tareas[[#This Row],[ID]]=1,100/SUM($M$47:$M$50),0) -> 0 | C48: Meriño Martinez Máximo E. (MEMERINO@collahuasi.cl) | D48: D. GESTION MEDIO AMBIENTE | E48: =(IF(I48<=TODAY(),1,0))*B48 -> 0 | F48: 0 | H48: =I48-O48 -> 44008 | I48: ='Matriz de riesgo SD'!$I$2-N48 -> 44009 | J48: No | K48: 0 | M48: =IF(Tareas[[#This Row],[Activo]]="sí",1,0) -> 0 | N48: 25 | O48: 1
A49: 03 Instalación contenedores residuos según Layout | B49: =IF(Tareas[[#This Row],[ID]]=1,100/SUM($M$47:$M$50),0) -> 0 | C49: Meriño Martinez Máximo E. (MEMERINO@collahuasi.cl) | D49: D. GESTION MEDIO AMBIENTE | E49: =(IF(I49<=TODAY(),1,0))*B49 -> 0 | F49: 0 | H49: =I49-O49 -> 44028 | I49: ='Matriz de riesgo SD'!$I$2-N49 -> 44029 | J49: No | K49: 0 | M49: =IF(Tareas[[#This Row],[Activo]]="sí",1,0) -> 0 | N49: 5 | O49: 1
A50: 04 Plan de retiro de contenedores residuos | B50: =IF(Tareas[[#This Row],[ID]]=1,100/SUM($M$47:$M$50),0) -> 50 | C50: Meriño Martinez Máximo E. (MEMERINO@collahuasi.cl) | D50: D. GESTION MEDIO AMBIENTE | E50: =(IF(I50<=TODAY(),1,0))*B50 -> 50 | F50: 0 | H50: =I50-O50 -> 44013 | I50: ='Matriz de riesgo SD'!$I$2-N50 -> 44014 | J50: Sí | K50: 0 | M50: =IF(Tareas[[#This Row],[Activo]]="sí",1,0) -> 1 | N50: 20 | O50: 1
A51: 01 Solicitud dotaciones adicionales | B51: =IF(Tareas[[#This Row],[ID]]=1,100/SUM($M$51:$M$58),0) -> 14.285714 | C51: Meriño Martinez Máximo E. (MEMERINO@collahuasi.cl) | D51: E. DOTACIONES DEL MANTENIMIENTO | E51: =(IF(I51<=TODAY(),1,0))*B51 -> 14.285714 | F51: 14.3 | H51: =I51-O51 -> 43998 | I51: ='Matriz de riesgo SD'!$I$2-N51 -> 43999 | J51: Sí | K51: 0 | M51: =IF(Tareas[[#This Row],[Activo]]="sí",1,0) -> 1 | N51: 35 | O51: 1
A52: 02 Generacion de distribucion del personal de mantenimiento | B52: =IF(Tareas[[#This Row],[ID]]=1,100/SUM($M$51:$M$58),0) -> 14.285714 | C52: Meriño Martinez Máximo E. (MEMERINO@collahuasi.cl) | D52: E. DOTACIONES DEL MANTENIMIENTO | E52: =(IF(I52<=TODAY(),1,0))*B52 -> 14.285714 | F52: 0 | H52: =I52-O52 -> 44021 | I52: ='Matriz de riesgo SD'!$I$2-N52 -> 44022 | J52: Sí | K52: 0 | M52: =IF(Tareas[[#This Row],[Activo]]="sí",1,0) -> 1 | N52: 12 | O52: 1
A53: 03 Confirmacion de dotaciones solicitadas | B53: =IF(Tareas[[#This Row],[ID]]=1,100/SUM($M$51:$M$58),0) -> 14.285714 | C53: Meriño Martinez Máximo E. (MEMERINO@collahuasi.cl) | D53: E. DOTACIONES DEL MANTENIMIENTO | E53: =(IF(I53<=TODAY(),1,0))*B53 -> 14.285714 | F53: 14.3 | H53: =I53-O53 -> 44003 | I53: ='Matriz de riesgo SD'!$I$2-N53 -> 44004 | J53: Sí | K53: 0 | M53: =IF(Tareas[[#This Row],[Activo]]="sí",1,0) -> 1 | N53: 30 | O53: 1
A54: 04 Envio Calendario de turnos y responsables por equipos | B54: =IF(Tareas[[#This Row],[ID]]=1,100/SUM($M$51:$M$58),0) -> 14.285714 | C54: Meriño Martinez Máximo E. (MEMERINO@collahuasi.cl) | D54: E. DOTACIONES DEL MANTENIMIENTO | E54: =(IF(I54<=TODAY(),1,0))*B54 -> 14.285714 | F54: 0 | H54: =I54-O54 -> 44018 | I54: ='Matriz de riesgo SD'!$I$2-N54 -> 44019 | J54: Sí | K54: 0 | M54: =IF(Tareas[[#This Row],[Activo]]="sí",1,0) -> 1 | N54: 15 | O54: 1
A55: 05 Definición de Responsables del control de trabajos por equipos - MECANICOS | B55: =IF(Tareas[[#This Row],[ID]]=1,100/SUM($M$51:$M$58),0) -> 14.285714 | C55: Hurtado Olcay Marcelo S (MSHURTADO@collahuasi.cl) | D55: E. DOTACIONES DEL MANTENIMIENTO | E55: =(IF(I55<=TODAY(),1,0))*B55 -> 14.285714 | F55: 0 | H55: =I55-O55 -> 44018 | I55: ='Matriz de riesgo SD'!$I$2-N55 -> 44019 | J55: Sí | K55: 0 | M55: =IF(Tareas[[#This Row],[Activo]]="sí",1,0) -> 1 | N55: 15 | O55: 1
A56: 06 Definición de Responsables del control de trabajos por equipos - SIAC | B56: =IF(Tareas[[#This Row],[ID]]=1,100/SUM($M$51:$M$58),0) -> 0 | C56: Hurtado Olcay Marcelo S (MSHURTADO@collahuasi.cl) | D56: E. DOTACIONES DEL MANTENIMIENTO | E56: =(IF(I56<=TODAY(),1,0))*B56 -> 0 | F56: 0 | H56: =I56-O56 -> 44018 | I56: ='Matriz de riesgo SD'!$I$2-N56 -> 44019 | J56: No | K56: 0 | M56: =IF(Tareas[[#This Row],[Activo]]="sí",1,0) -> 0 | N56: 15 | O56: 1
A57: 07 Definición Responsables control trabajos equipos - CONFIABILIDAD/PREDICTIVO | B57: =IF(Tareas[[#This Row],[ID]]=1,100/SUM($M$51:$M$58),0) -> 14.285714 | C57: Meriño Martinez Máximo E. (MEMERINO@collahuasi.cl) | D57: E. DOTACIONES DEL MANTENIMIENTO | E57: =(IF(I57<=TODAY(),1,0))*B57 -> 14.285714 | F57: 0 | H57: =I57-O57 -> 44018 | I57: ='Matriz de riesgo SD'!$I$2-N57 -> 44019 | J57: Sí | K57: 0 | M57: =IF(Tareas[[#This Row],[Activo]]="sí",1,0) -> 1 | N57: 15 | O57: 1
A58: 08 Definición de Responsables del control de trabajos por equipos - OPERACIONES | B58: =IF(Tareas[[#This Row],[ID]]=1,100/SUM($M$51:$M$58),0) -> 14.285714 | C58: Meriño Martinez Máximo E. (MEMERINO@collahuasi.cl) | D58: E. DOTACIONES DEL MANTENIMIENTO | E58: =(IF(I58<=TODAY(),1,0))*B58 -> 14.285714 | F58: 0 | H58: =I58-O58 -> 44018 | I58: ='Matriz de riesgo SD'!$I$2-N58 -> 44019 | J58: Sí | K58: 0 | M58: =IF(Tareas[[#This Row],[Activo]]="sí",1,0) -> 1 | N58: 15 | O58: 1
A59: 01 Solicitud de repuestos a utilizar - Jefes de area | B59: =IF(Tareas[[#This Row],[ID]]=1,100/SUM($M$59:$M$83),0) -> 4.5454545 | C59: Hurtado Olcay Marcelo S (MSHURTADO@collahuasi.cl) | D59: F. GESTION DE REPUESTOS Y MATERIALES | E59: =(IF(I59<=TODAY(),1,0))*B59 -> 4.5454545 | F59: 4.5 | H59: =I59-O59 -> 43992 | I59: ='Matriz de riesgo SD'!$I$2-N59 -> 43994 | J59: Sí | K59: 0 | M59: =IF(Tareas[[#This Row],[Activo]]="sí",1,0) -> 1 | N59: 40 | O59: 2
A60: 02 Validacion de repuestos (Listado) a utilizar - MECANICOS | B60: =IF(Tareas[[#This Row],[ID]]=1,100/SUM($M$59:$M$83),0) -> 4.5454545 | C60: Hurtado Olcay Marcelo S (MSHURTADO@collahuasi.cl) | D60: F. GESTION DE REPUESTOS Y MATERIALES | E60: =(IF(I60<=TODAY(),1,0))*B60 -> 4.5454545 | F60: 4.5 | H60: =I60-O60 -> 43998 | I60: ='Matriz de riesgo SD'!$I$2-N60 -> 43999 | J60: Sí | K60: 0 | M60: =IF(Tareas[[#This Row],[Activo]]="sí",1,0) -> 1 | N60: 35 | O60: 1
A61: 03 Validacion de repuestos (Listado) a utilizar - INSTRUMENTISTA | B61: =IF(Tareas[[#This Row],[ID]]=1,100/SUM($M$59:$M$83),0) -> 4.5454545 | C61: Hurtado Olcay Marcelo S (MSHURTADO@collahuasi.cl) | D61: F. GESTION DE REPUESTOS Y MATERIALES | E61: =(IF(I61<=TODAY(),1,0))*B61 -> 4.5454545 | F61: 4.5 | H61: =I61-O61 -> 43998 | I61: ='Matriz de riesgo SD'!$I$2-N61 -> 43999 | J61: Sí | K61: 0 | M61: =IF(Tareas[[#This Row],[Activo]]="sí",1,0) -> 1 | N61: 35 | O61: 1
A62: 04 Validacion de repuestos (Listado) a utilizar - ELECTRICOS | B62: =IF(Tareas[[#This Row],[ID]]=1,100/SUM($M$59:$M$83),0) -> 4.5454545 | C62: Hurtado Olcay Marcelo S (MSHURTADO@collahuasi.cl) | D62: F. GESTION DE REPUESTOS Y MATERIALES | E62: =(IF(I62<=TODAY(),1,0))*B62 -> 4.5454545 | F62: 4.5 | H62: =I62-O62 -> 43998 | I62: ='Matriz de riesgo SD'!$I$2-N62 -> 43999 | J62: Sí | K62: 0 | M62: =IF(Tareas[[#This Row],[Activo]]="sí",1,0) -> 1 | N62: 35 | O62: 1
A63: 05 Validacion de repuestos (Listado) a utilizar - LUBRICACION | B63: =IF(Tareas[[#This Row],[ID]]=1,100/SUM($M$59:$M$83),0) -> 4.5454545 | C63: Hurtado Olcay Marcelo S (MSHURTADO@collahuasi.cl) | D63: F. GESTION DE REPUESTOS Y MATERIALES | E63: =(IF(I63<=TODAY(),1,0))*B63 -> 4.5454545 | F63: 4.5 | H63: =I63-O63 -> 43998 | I63: ='Matriz de riesgo SD'!$I$2-N63 -> 43999 | J63: Sí | K63: 0 | M63: =IF(Tareas[[#This Row],[Activo]]="sí",1,0) -> 1 | N63: 35 | O63: 1
A64: 06 Validacion de repuestos (Listado) a utilizar - FUNGIBLES | B64: =IF(Tareas[[#This Row],[ID]]=1,100/SUM($M$59:$M$83),0) -> 4.5454545 | C64: Hurtado Olcay Marcelo S (MSHURTADO@collahuasi.cl) | D64: F. GESTION DE REPUESTOS Y MATERIALES | E64: =(IF(I64<=TODAY(),1,0))*B64 -> 4.5454545 | F64: 4.5 | H64: =I64-O64 -> 43998 | I64: ='Matriz de riesgo SD'!$I$2-N64 -> 43999 | J64: Sí | K64: 0 | M64: =IF(Tareas[[#This Row],[Activo]]="sí",1,0) -> 1 | N64: 35 | O64: 1
A65: 07 Solicitud de compra repuestos según carta gantt | B65: =IF(Tareas[[#This Row],[ID]]=1,100/SUM($M$59:$M$83),0) -> 4.5454545 | C65: Meriño Martinez Máximo E. (MEMERINO@collahuasi.cl) | D65: F. GESTION DE REPUESTOS Y MATERIALES | E65: =(IF(I65<=TODAY(),1,0))*B65 -> 4.5454545 | F65: 4.5 | H65: =I65-O65 -> 44003 | I65: ='Matriz de riesgo SD'!$I$2-N65 -> 44004 | J65: Sí | K65: 0 | M65: =IF(Tareas[[#This Row],[Activo]]="sí",1,0) -> 1 | N65: 30 | O65: 1
A66: 08 Generar RQ por repuestos con codigo Stock | B66: =IF(Tareas[[#This Row],[ID]]=1,100/SUM($M$59:$M$83),0) -> 4.5454545 | C66: Meriño Martinez Máximo E. (MEMERINO@collahuasi.cl) | D66: F. GESTION DE REPUESTOS Y MATERIALES | E66: =(IF(I66<=TODAY(),1,0))*B66 -> 4.5454545 | F66: 4.5 | H66: =I66-O66 -> 44003 | I66: ='Matriz de riesgo SD'!$I$2-N66 -> 44004 | J66: Sí | K66: 0 | M66: =IF(Tareas[[#This Row],[Activo]]="sí",1,0) -> 1 | N66: 30 | O66: 1
A67: 09 Generar PRQ por repuestos cargo directos | B67: =IF(Tareas[[#This Row],[ID]]=1,100/SUM($M$59:$M$83),0) -> 4.5454545 | C67: Saravia Ibacache Alain J. (AJSARAVIA@collahuasi.cl) | D67: F. GESTION DE REPUESTOS Y MATERIALES | E67: =(IF(I67<=TODAY(),1,0))*B67 -> 4.5454545 | F67: 4.5 | H67: =I67-O67 -> 44003 | I67: ='Matriz de riesgo SD'!$I$2-N67 -> 44004 | J67: Sí | K67: 0 | M67: =IF(Tareas[[#This Row],[Activo]]="sí",1,0) -> 1 | N67: 30 | O67: 1
A68: 10 Generar compras de Fungibles e insumos | B68: =IF(Tareas[[#This Row],[ID]]=1,100/SUM($M$59:$M$83),0) -> 4.5454545 | C68: Meriño Martinez Máximo E. (MEMERINO@collahuasi.cl) | D68: F. GESTION DE REPUESTOS Y MATERIALES | E68: =(IF(I68<=TODAY(),1,0))*B68 -> 4.5454545 | F68: 4.5 | H68: =I68-O68 -> 44003 | I68: ='Matriz de riesgo SD'!$I$2-N68 -> 44004 | J68: Sí | K68: 0 | M68: =IF(Tareas[[#This Row],[Activo]]="sí",1,0) -> 1 | N68: 30 | O68: 1
A69: 11 Envio Listado de repuestos a bodega con requisiciones (PRQ - RQ) | B69: =IF(Tareas[[#This Row],[ID]]=1,100/SUM($M$59:$M$83),0) -> 4.5454545 | C69: Meriño Martinez Máximo E. (MEMERINO@collahuasi.cl) | D69: F. GESTION DE REPUESTOS Y MATERIALES | E69: =(IF(I69<=TODAY(),1,0))*B69 -> 4.5454545 | F69: 4.5 | H69: =I69-O69 -> 44004 | I69: ='Matriz de riesgo SD'!$I$2-N69 -> 44005 | J69: Sí | K69: 0 | M69: =IF(Tareas[[#This Row],[Activo]]="sí",1,0) -> 1 | N69: 29 | O69: 1
A70: 12 Confirmacion Listado Repuestos desde bodega | B70: =IF(Tareas[[#This Row],[ID]]=1,100/SUM($M$59:$M$83),0) -> 4.5454545 | C70: Meriño Martinez Máximo E. (MEMERINO@collahuasi.cl) | D70: F. GESTION DE REPUESTOS Y MATERIALES | E70: =(IF(I70<=TODAY(),1,0))*B70 -> 4.5454545 | F70: 0 | H70: =I70-O70 -> 44008 | I70: ='Matriz de riesgo SD'!$I$2-N70 -> 44009 | J70: Sí | K70: 0 | M70: =IF(Tareas[[#This Row],[Activo]]="sí",1,0) -> 1 | N70: 25 | O70: 1
... A83: 22 Informe de Costos de Repuestos Mantencion | B83: =IF(Tareas[[#This Row],[ID]]=1,100/SUM($M$59:$M$83),0) -> 4.5454545 | C83: Meriño Martinez Máximo E. (MEMERINO@collahuasi.cl) | D83: F. GESTION DE REPUESTOS Y MATERIALES | E83: =(IF(I83<=TODAY(),1,0))*B83 -> 4.5454545 | F83: 0 | H83: =I83-O83 -> 44028 | I83: ='Matriz de riesgo SD'!$I$2-N83 -> 44029 | J83: Sí | K83: 0 | M83: =IF(Tareas[[#This Row],[Activo]]="sí",1,0) -> 1 | N83: 5 | O83: 1
A84: 01 ReunionN°1(Serv Personal) Solicitud inicial, revision requerimientos, comida y otros | B84: =IF(Tareas[[#This Row],[ID]]=1,100/SUM($M$84:$M$88),0) -> 25 | C84: Meriño Martinez Máximo E. (MEMERINO@collahuasi.cl) | D84: G. SERVICIOS AL PERSONAL | E84: =(IF(I84<=TODAY(),1,0))*B84 -> 25 | F84: 25 | H84: =I84-O84 -> 44003 | I84: ='Matriz de riesgo SD'!$I$2-N84 -> 44004 | J84: Sí | K84: 0 | M84: =IF(Tareas[[#This Row],[Activo]]="sí",1,0) -> 1 | N84: 30 | O84: 1
A85: 02 Consolidar y enviar solicitud comida a servicio a las personas CMDIC | B85: =IF(Tareas[[#This Row],[ID]]=1,100/SUM($M$84:$M$88),0) -> 25 | C85: Meriño Martinez Máximo E. (MEMERINO@collahuasi.cl) | D85: G. SERVICIOS AL PERSONAL | E85: =(IF(I85<=TODAY(),1,0))*B85 -> 25 | F85: 25 | H85: =I85-O85 -> 44005 | I85: ='Matriz de riesgo SD'!$I$2-N85 -> 44006 | J85: Sí | K85: 0 | M85: =IF(Tareas[[#This Row],[Activo]]="sí",1,0) -> 1 | N85: 28 | O85: 1
A86: 03 Confirmacion de solicitud por parte servicio a las personas CMDIC | B86: =IF(Tareas[[#This Row],[ID]]=1,100/SUM($M$84:$M$88),0) -> 25 | C86: Meriño Martinez Máximo E. (MEMERINO@collahuasi.cl) | D86: G. SERVICIOS AL PERSONAL | E86: =(IF(I86<=TODAY(),1,0))*B86 -> 25 | F86: 25 | H86: =I86-O86 -> 44005 | I86: ='Matriz de riesgo SD'!$I$2-N86 -> 44006 | J86: Sí | K86: 0 | M86: =IF(Tareas[[#This Row],[Activo]]="sí",1,0) -> 1 | N86: 28 | O86: 1
A87: 04 Envio solicitudes y requerimientos adicionales (Colaciones, Servicio Cafeteria, etc.) | B87: =IF(Tareas[[#This Row],[ID]]=1,100/SUM($M$84:$M$88),0) -> 25 | C87: Meriño Martinez Máximo E. (MEMERINO@collahuasi.cl) | D87: G. SERVICIOS AL PERSONAL | E87: =(IF(I87<=TODAY(),1,0))*B87 -> 25 | F87: 0 | H87: =I87-O87 -> 44018 | I87: ='Matriz de riesgo SD'!$I$2-N87 -> 44019 | J87: Sí | K87: 0 | M87: =IF(Tareas[[#This Row],[Activo]]="sí",1,0) -> 1 | N87: 15 | O87: 1
A88: 05 Envio Flujos de personas a casino | B88: =IF(Tareas[[#This Row],[ID]]=1,100/SUM($M$84:$M$88),0) -> 0 | C88: Meriño Martinez Máximo E. (MEMERINO@collahuasi.cl) | D88: G. SERVICIOS AL PERSONAL | E88: =(IF(I88<=TODAY(),1,0))*B88 -> 0 | F88: 0 | H88: =I88-O88 -> 44022 | I88: ='Matriz de riesgo SD'!$I$2-N88 -> 44023 | J88: No | K88: 0 | M88: =IF(Tareas[[#This Row],[Activo]]="sí",1,0) -> 0 | N88: 11 | O88: 1
A89: 01 Solicitud requerimientos operaciones (Limpieza, correas, Interferencias, energias) | B89: =IF(Tareas[[#This Row],[ID]]=1,100/SUM($M$89:$M$99),0) -> 11.111111 | C89: Meriño Martinez Máximo E. (MEMERINO@collahuasi.cl) | D89: H. SERVICIOS DE APOYO Y EQUIPOS | E89: =(IF(I89<=TODAY(),1,0))*B89 -> 11.111111 | F89: 0 | H89: =I89-O89 -> 44018 | I89: ='Matriz de riesgo SD'!$I$2-N89 -> 44019 | J89: Sí | K89: 0 | M89: =IF(Tareas[[#This Row],[Activo]]="sí",1,0) -> 1 | N89: 15 | O89: 1
A90: 02 Solicitud equipos apoyo mantencion (Gruas, Horquillas, camiones, generadores, etc) | B90: =IF(Tareas[[#This Row],[ID]]=1,100/SUM($M$89:$M$99),0) -> 11.111111 | C90: Meriño Martinez Máximo E. (MEMERINO@collahuasi.cl) | D90: H. SERVICIOS DE APOYO Y EQUIPOS | E90: =(IF(I90<=TODAY(),1,0))*B90 -> 11.111111 | F90: 0 | H90: =I90-O90 -> 44013 | I90: ='Matriz de riesgo SD'!$I$2-N90 -> 44014 | J90: Sí | K90: 0 | M90: =IF(Tareas[[#This Row],[Activo]]="sí",1,0) -> 1 | N90: 20 | O90: 1
A91: 03 Solicitud de andamios para ejecución del Mantenimiento | B91: =IF(Tareas[[#This Row],[ID]]=1,100/SUM($M$89:$M$99),0) -> 11.111111 | C91: Meriño Martinez Máximo E. (MEMERINO@collahuasi.cl) | D91: H. SERVICIOS DE APOYO Y EQUIPOS | E91: =(IF(I91<=TODAY(),1,0))*B91 -> 11.111111 | F91: 0 | H91: =I91-O91 -> 44013 | I91: ='Matriz de riesgo SD'!$I$2-N91 -> 44014 | J91: Sí | K91: 0 | M91: =IF(Tareas[[#This Row],[Activo]]="sí",1,0) -> 1 | N91: 20 | O91: 1
A92: 04 Solicitud apoyo area Predictivo / Confiabilidad | B92: =IF(Tareas[[#This Row],[ID]]=1,100/SUM($M$89:$M$99),0) -> 11.111111 | C92: Meriño Martinez Máximo E. (MEMERINO@collahuasi.cl) | D92: H. SERVICIOS DE APOYO Y EQUIPOS | E92: =(IF(I92<=TODAY(),1,0))*B92 -> 11.111111 | F92: 0 | H92: =I92-O92 -> 44003 | I92: ='Matriz de riesgo SD'!$I$2-N92 -> 44004 | J92: Sí | K92: 0 | M92: =IF(Tareas[[#This Row],[Activo]]="sí",1,0) -> 1 | N92: 30 | O92: 1
A93: 05 Solicitud apoyo personal Mecanicos correas CMDIC | B93: =IF(Tareas[[#This Row],[ID]]=1,100/SUM($M$89:$M$99),0) -> 0 | C93: Meriño Martinez Máximo E. (MEMERINO@collahuasi.cl) | D93: H. SERVICIOS DE APOYO Y EQUIPOS | E93: =(IF(I93<=TODAY(),1,0))*B93 -> 0 | F93: 10 | H93: =I93-O93 -> 44003 | I93: ='Matriz de riesgo SD'!$I$2-N93 -> 44004 | J93: No | K93: 0 | M93: =IF(Tareas[[#This Row],[Activo]]="sí",1,0) -> 0 | N93: 30 | O93: 1
A94: 06 Revision y mantención Puentes Gruas | B94: =IF(Tareas[[#This Row],[ID]]=1,100/SUM($M$89:$M$99),0) -> 11.111111 | C94: Meriño Martinez Máximo E. (MEMERINO@collahuasi.cl) | D94: H. SERVICIOS DE APOYO Y EQUIPOS | E94: =(IF(I94<=TODAY(),1,0))*B94 -> 11.111111 | F94: 0 | H94: =I94-O94 -> 44018 | I94: ='Matriz de riesgo SD'!$I$2-N94 -> 44019 | J94: Sí | K94: 0 | M94: =IF(Tareas[[#This Row],[Activo]]="sí",1,0) -> 1 | N94: 15 | O94: 1
A95: 07 Revision y mantención Ascensores | B95: =IF(Tareas[[#This Row],[ID]]=1,100/SUM($M$89:$M$99),0) -> 0 | C95: Meriño Martinez Máximo E. (MEMERINO@collahuasi.cl) | D95: H. SERVICIOS DE APOYO Y EQUIPOS | E95: =(IF(I95<=TODAY(),1,0))*B95 -> 0 | F95: 0 | H95: =I95-O95 -> 44018 | I95: ='Matriz de riesgo SD'!$I$2-N95 -> 44019 | J95: No | K95: 0 | M95: =IF(Tareas[[#This Row],[Activo]]="sí",1,0) -> 0 | N95: 15 | O95: 1
A96: 08 Revision Iluminacion edificio en los puntos de mantencion | B96: =IF(Tareas[[#This Row],[ID]]=1,100/SUM($M$89:$M$99),0) -> 11.111111 | C96: Meriño Martinez Máximo E. (MEMERINO@collahuasi.cl) | D96: H. SERVICIOS DE APOYO Y EQUIPOS | E96: =(IF(I96<=TODAY(),1,0))*B96 -> 11.111111 | F96: 0 | H96: =I96-O96 -> 44008 | I96: ='Matriz de riesgo SD'!$I$2-N96 -> 44009 | J96: Sí | K96: 0 | M96: =IF(Tareas[[#This Row],[Activo]]="sí",1,0) -> 1 | N96: 25 | O96: 1
A97: 09 Verificar instalación de Andamios previo al mantenimiento | B97: =IF(Tareas[[#This Row],[ID]]=1,100/SUM($M$89:$M$99),0) -> 11.111111 | C97: Meriño Martinez Máximo E. (MEMERINO@collahuasi.cl) | D97: H. SERVICIOS DE APOYO Y EQUIPOS | E97: =(IF(I97<=TODAY(),1,0))*B97 -> 11.111111 | F97: 0 | H97: =I97-O97 -> 44028 | I97: ='Matriz de riesgo SD'!$I$2-N97 -> 44029 | J97: Sí | K97: 0 | M97: =IF(Tareas[[#This Row],[Activo]]="sí",1,0) -> 1 | N97: 5 | O97: 1
A98: 10 Verificar de limpiezas solicitadas previo al mantenimiento | B98: =IF(Tareas[[#This Row],[ID]]=1,100/SUM($M$89:$M$99),0) -> 11.111111 | C98: Meriño Martinez Máximo E. (MEMERINO@collahuasi.cl) | D98: H. SERVICIOS DE APOYO Y EQUIPOS | E98: =(IF(I98<=TODAY(),1,0))*B98 -> 11.111111 | F98: 0 | H98: =I98-O98 -> 44030 | I98: ='Matriz de riesgo SD'!$I$2-N98 -> 44031 | J98: Sí | K98: 0 | M98: =IF(Tareas[[#This Row],[Activo]]="sí",1,0) -> 1 | N98: 3 | O98: 1
A99: 11 Verificar llegada de equipos de apoyo solicitados | B99: =IF(Tareas[[#This Row],[ID]]=1,100/SUM($M$89:$M$99),0) -> 11.111111 | C99: Meriño Martinez Máximo E. (MEMERINO@collahuasi.cl) | D99: H. SERVICIOS DE APOYO Y EQUIPOS | E99: =(IF(I99<=TODAY(),1,0))*B99 -> 11.111111 | F99: 0 | H99: =I99-O99 -> 44028 | I99: ='Matriz de riesgo SD'!$I$2-N99 -> 44029 | J99: Sí | K99: 0 | M99: =IF(Tareas[[#This Row],[Activo]]="sí",1,0) -> 1 | N99: 5 | O99: 1
A100: ​01 Induccion tecnica del trabajo (induccion tecnica) - MECANICOS | B100: =IF(Tareas[[#This Row],[ID]]=1,100/SUM($M$100:$M$107),0) -> 25 | C100: Hurtado Olcay Marcelo S (MSHURTADO@collahuasi.cl) | D100: I. GESTION DE PERSONAS | E100: =(IF(I100<=TODAY(),1,0))*B100 -> 25 | F100: 0 | H100: =I100-O100 -> 44022 | I100: ='Matriz de riesgo SD'!$I$2-N100 -> 44023 | J100: Sí | K100: 0 | M100: =IF(Tareas[[#This Row],[Activo]]="sí",1,0) -> 1 | N100: 11 | O100: 1
A101: ​02 Induccion tecnica del trabajo (induccion tecnica) - INSTRUMENTACION | B101: =IF(Tareas[[#This Row],[ID]]=1,100/SUM($M$100:$M$107),0) -> 25 | C101: Hurtado Olcay Marcelo S (MSHURTADO@collahuasi.cl) | D101: I. GESTION DE PERSONAS | E101: =(IF(I101<=TODAY(),1,0))*B101 -> 25 | F101: 0 | H101: =I101-O101 -> 44022 | I101: ='Matriz de riesgo SD'!$I$2-N101 -> 44023 | J101: Sí | K101: 0 | M101: =IF(Tareas[[#This Row],[Activo]]="sí",1,0) -> 1 | N101: 11 | O101: 1
A102: ​03 Induccion tecnica del trabajo (induccion tecnica) - LUBRICACION | B102: =IF(Tareas[[#This Row],[ID]]=1,100/SUM($M$100:$M$107),0) -> 25 | C102: Hurtado Olcay Marcelo S (MSHURTADO@collahuasi.cl) | D102: I. GESTION DE PERSONAS | E102: =(IF(I102<=TODAY(),1,0))*B102 -> 25 | F102: 0 | H102: =I102-O102 -> 44022 | I102: ='Matriz de riesgo SD'!$I$2-N102 -> 44023 | J102: Sí | K102: 0 | M102: =IF(Tareas[[#This Row],[Activo]]="sí",1,0) -> 1 | N102: 11 | O102: 1
A103: 05 Induccion tecnica del trabajo (induccion tecnica) - ELECTRICO | B103: =IF(Tareas[[#This Row],[ID]]=1,100/SUM($M$100:$M$107),0) -> 25 | C103: Hurtado Olcay Marcelo S (MSHURTADO@collahuasi.cl) | D103: I. GESTION DE PERSONAS | E103: =(IF(I103<=TODAY(),1,0))*B103 -> 25 | F103: 0 | H103: =I103-O103 -> 44022 | I103: ='Matriz de riesgo SD'!$I$2-N103 -> 44023 | J103: Sí | K103: 0 | M103: =IF(Tareas[[#This Row],[Activo]]="sí",1,0) -> 1 | N103: 11 | O103: 1
A104: 06 Plan Gestion de competencias - MECANICOS | B104: =IF(Tareas[[#This Row],[ID]]=1,100/SUM($M$100:$M$107),0) -> 0 | C104: Hurtado Olcay Marcelo S (MSHURTADO@collahuasi.cl) | D104: I. GESTION DE PERSONAS | E104: =(IF(I104<=TODAY(),1,0))*B104 -> 0 | F104: 0 | H104: =I104-O104 -> 44028 | I104: ='Matriz de riesgo SD'!$I$2-N104 -> 44029 | J104: No | K104: 0 | M104: =IF(Tareas[[#This Row],[Activo]]="sí",1,0) -> 0 | N104: 5 | O104: 1
A105: 07 Plan Gestion de competencias - ELECTRICOS | B105: =IF(Tareas[[#This Row],[ID]]=1,100/SUM($M$100:$M$107),0) -> 0 | C105: Hurtado Olcay Marcelo S (MSHURTADO@collahuasi.cl) | D105: I. GESTION DE PERSONAS | E105: =(IF(I105<=TODAY(),1,0))*B105 -> 0 | F105: 0 | H105: =I105-O105 -> 44028 | I105: ='Matriz de riesgo SD'!$I$2-N105 -> 44029 | J105: No | K105: 0 | M105: =IF(Tareas[[#This Row],[Activo]]="sí",1,0) -> 0 | N105: 5 | O105: 1
A106: 08 Plan Gestion de competencias - SIAC | B106: =IF(Tareas[[#This Row],[ID]]=1,100/SUM($M$100:$M$107),0) -> 0 | C106: Hurtado Olcay Marcelo S (MSHURTADO@collahuasi.cl) | D106: I. GESTION DE PERSONAS | E106: =(IF(I106<=TODAY(),1,0))*B106 -> 0 | F106: 0 | H106: =I106-O106 -> 44028 | I106: ='Matriz de riesgo SD'!$I$2-N106 -> 44029 | J106: No | K106: 0 | M106: =IF(Tareas[[#This Row],[Activo]]="sí",1,0) -> 0 | N106: 5 | O106: 1
A107: 09 Habilitar al personal para ingreso y trabajos en Faena Puerto | B107: =IF(Tareas[[#This Row],[ID]]=1,100/SUM($M$100:$M$107),0) -> 0 | C107: Hurtado Olcay Marcelo S (MSHURTADO@collahuasi.cl) | D107: I. GESTION DE PERSONAS | E107: =(IF(I107<=TODAY(),1,0))*B107 -> 0 | F107: 0 | H107: =I107-O107 -> 44028 | I107: ='Matriz de riesgo SD'!$I$2-N107 -> 44029 | J107: No | K107: 0 | M107: =IF(Tareas[[#This Row],[Activo]]="sí",1,0) -> 0 | N107: 5 | O107: 1
A108: 01 Listado de equipos y sus controles de calidad | B108: =IF(Tareas[[#This Row],[ID]]=1,100/SUM($M$108:$M$116),0) -> 12.5 | C108: Meriño Martinez Máximo E. (MEMERINO@collahuasi.cl) | D108: J. GESTION Y CONTROL DE LA EJECUCION DEL MANTENIMIENTO | E108: =(IF(I108<=TODAY(),1,0))*B108 -> 12.5 | F108: 0 | H108: =I108-O108 -> 44023 | I108: ='Matriz de riesgo SD'!$I$2-N108 -> 44024 | J108: Sí | K108: 0 | M108: =IF(Tareas[[#This Row],[Activo]]="sí",1,0) -> 1 | N108: 10 | O108: 1
A109: 02 Plan de tiempos asociados a pruebas y puesta en marcha (Según listado) | B109: =IF(Tareas[[#This Row],[ID]]=1,100/SUM($M$108:$M$116),0) -> 12.5 | C109: Meriño Martinez Máximo E. (MEMERINO@collahuasi.cl) | D109: J. GESTION Y CONTROL DE LA EJECUCION DEL MANTENIMIENTO | E109: =(IF(I109<=TODAY(),1,0))*B109 -> 12.5 | F109: 0 | H109: =I109-O109 -> 44028 | I109: ='Matriz de riesgo SD'!$I$2-N109 -> 44029 | J109: Sí | K109: 1 | M109: =IF(Tareas[[#This Row],[Activo]]="sí",1,0) -> 1 | N109: 5 | O109: 1
A110: 03 Generar comité de puesta en marcha Filtro | B110: =IF(Tareas[[#This Row],[ID]]=1,100/SUM($M$108:$M$116),0) -> 0 | C110: Meriño Martinez Máximo E. (MEMERINO@collahuasi.cl) | D110: J. GESTION Y CONTROL DE LA EJECUCION DEL MANTENIMIENTO | E110: =(IF(I110<=TODAY(),1,0))*B110 -> 0 | F110: 0 | H110: =I110-O110 -> 44018 | I110: ='Matriz de riesgo SD'!$I$2-N110 -> 44019 | J110: No | K110: 2 | M110: =IF(Tareas[[#This Row],[Activo]]="sí",1,0) -> 0 | N110: 15 | O110: 1
A111: 04 Reunion diaria avances mantencion | B111: =IF(Tareas[[#This Row],[ID]]=1,100/SUM($M$108:$M$116),0) -> 12.5 | C111: Meriño Martinez Máximo E. (MEMERINO@collahuasi.cl) | D111: J. GESTION Y CONTROL DE LA EJECUCION DEL MANTENIMIENTO | E111: =(IF(I111<=TODAY(),1,0))*B111 -> 12.5 | F111: 0 | H111: =I111-O111 -> 44032 | I111: ='Matriz de riesgo SD'!$I$2-N111 -> 44033 | J111: Sí | K111: 3 | M111: =IF(Tareas[[#This Row],[Activo]]="sí",1,0) -> 1 | N111: 1 | O111: 1
A112: 05 Envio reporte de avances de Mantención | B112: =IF(Tareas[[#This Row],[ID]]=1,100/SUM($M$108:$M$116),0) -> 12.5 | C112: Meriño Martinez Máximo E. (MEMERINO@collahuasi.cl) | D112: J. GESTION Y CONTROL DE LA EJECUCION DEL MANTENIMIENTO | E112: =(IF(I112<=TODAY(),1,0))*B112 -> 12.5 | F112: 0 | H112: =I112-O112 -> 44032 | I112: ='Matriz de riesgo SD'!$I$2-N112 -> 44033 | J112: Sí | K112: 4 | M112: =IF(Tareas[[#This Row],[Activo]]="sí",1,0) -> 1 | N112: 1 | O112: 1
A113: 06 Reporte diario QA/QC | B113: =IF(Tareas[[#This Row],[ID]]=1,100/SUM($M$108:$M$116),0) -> 12.5 | C113: Meriño Martinez Máximo E. (MEMERINO@collahuasi.cl) | D113: J. GESTION Y CONTROL DE LA EJECUCION DEL MANTENIMIENTO | E113: =(IF(I113<=TODAY(),1,0))*B113 -> 12.5 | F113: 0 | H113: =I113-O113 -> 44032 | I113: ='Matriz de riesgo SD'!$I$2-N113 -> 44033 | J113: Sí | K113: 5 | M113: =IF(Tareas[[#This Row],[Activo]]="sí",1,0) -> 1 | N113: 1 | O113: 1
A114: 07 Validacion de Formularios Postergacion Actividades Mant | B114: =IF(Tareas[[#This Row],[ID]]=1,100/SUM($M$108:$M$116),0) -> 12.5 | C114: Meriño Martinez Máximo E. (MEMERINO@collahuasi.cl) | D114: J. GESTION Y CONTROL DE LA EJECUCION DEL MANTENIMIENTO | E114: =(IF(I114<=TODAY(),1,0))*B114 -> 12.5 | F114: 0 | H114: =I114-O114 -> 44031 | I114: ='Matriz de riesgo SD'!$I$2-N114 -> 44032 | J114: Sí | K114: 6 | M114: =IF(Tareas[[#This Row],[Activo]]="sí",1,0) -> 1 | N114: 2 | O114: 1
A115: 08 HouseKeeping final del mantenimiento | B115: =IF(Tareas[[#This Row],[ID]]=1,100/SUM($M$108:$M$116),0) -> 12.5 | C115: Meriño Martinez Máximo E. (MEMERINO@collahuasi.cl) | D115: J. GESTION Y CONTROL DE LA EJECUCION DEL MANTENIMIENTO | E115: =(IF(I115<=TODAY(),1,0))*B115 -> 12.5 | F115: 0 | H115: =I115-O115 -> 44032 | I115: ='Matriz de riesgo SD'!$I$2-N115 -> 44033 | J115: Sí | K115: 7 | M115: =IF(Tareas[[#This Row],[Activo]]="sí",1,0) -> 1 | N115: 1 | O115: 1
A116: 09 Entrega protocolos de QA/QC de equipos en control | B116: =IF(Tareas[[#This Row],[ID]]=1,100/SUM($M$108:$M$116),0) -> 12.5 | C116: Meriño Martinez Máximo E. (MEMERINO@collahuasi.cl) | D116: J. GESTION Y CONTROL DE LA EJECUCION DEL MANTENIMIENTO | E116: =(IF(I116<=TODAY(),1,0))*B116 -> 12.5 | F116: 0 | H116: =I116-O116 -> 44032 | I116: ='Matriz de riesgo SD'!$I$2-N116 -> 44033 | J116: Sí | K116: 8 | M116: =IF(Tareas[[#This Row],[Activo]]="sí",1,0) -> 1 | N116: 1 | O116: 1
A117: 01 Cumplimiento de Programa | B117: =IF(Tareas[[#This Row],[ID]]=1,100/SUM($M$117:$M$128),0) -> 8.3333333 | C117: Meriño Martinez Máximo E. (MEMERINO@collahuasi.cl) | D117: K. GESTION CIERRE MANTENIMIENTO | E117: =(IF(I117<=TODAY(),1,0))*B117 -> 8.3333333 | F117: 0 | H117: =I117-O117 -> 44032 | I117: ='Matriz de riesgo SD'!$I$2-N117 -> 44033 | J117: Sí | K117: 9 | M117: =IF(Tareas[[#This Row],[Activo]]="sí",1,0) -> 1 | N117: 1 | O117: 1
A118: 02 Resumen Aprendizajes (caja 6) CMDIC - ESED | B118: =IF(Tareas[[#This Row],[ID]]=1,100/SUM($M$117:$M$128),0) -> 8.3333333 | C118: Meriño Martinez Máximo E. (MEMERINO@collahuasi.cl) | D118: K. GESTION CIERRE MANTENIMIENTO | E118: =(IF(I118<=TODAY(),1,0))*B118 -> 8.3333333 | F118: 0 | H118: =I118-O118 -> 44030 | I118: ='Matriz de riesgo SD'!$I$2-N118 -> 44031 | J118: Sí | K118: 0 | M118: =IF(Tareas[[#This Row],[Activo]]="sí",1,0) -> 1 | N118: 3 | O118: 1
A119: 03 Cierre de OT en Ellipse por parte de empresas ESED | B119: =IF(Tareas[[#This Row],[ID]]=1,100/SUM($M$117:$M$128),0) -> 8.3333333 | C119: Hurtado Olcay Marcelo S (MSHURTADO@collahuasi.cl) | D119: K. GESTION CIERRE MANTENIMIENTO | E119: =(IF(I119<=TODAY(),1,0))*B119 -> 8.3333333 | F119: 0 | H119: =I119-O119 -> 44020 | I119: ='Matriz de riesgo SD'!$I$2-N119 -> 44027 | J119: Sí | K119: 0 | M119: =IF(Tareas[[#This Row],[Activo]]="sí",1,0) -> 1 | N119: 7 | O119: 7
A120: 04 Cierre de OT en Ellipse por parte de CMDIC | B120: =IF(Tareas[[#This Row],[ID]]=1,100/SUM($M$117:$M$128),0) -> 8.3333333 | C120: Hurtado Olcay Marcelo S (MSHURTADO@collahuasi.cl) | D120: K. GESTION CIERRE MANTENIMIENTO | E120: =(IF(I120<=TODAY(),1,0))*B120 -> 8.3333333 | F120: 0 | H120: =I120-O120 -> 44020 | I120: ='Matriz de riesgo SD'!$I$2-N120 -> 44027 | J120: Sí | K120: 0 | M120: =IF(Tareas[[#This Row],[Activo]]="sí",1,0) -> 1 | N120: 7 | O120: 7
...

Sheet Proceso
A1: ID | B1: Title | C1: l ids
A2: 1 | B2: Chancado y Transporte
A3: 2 | B3: Molienda
A4: 3 | B4: Chancado Pebbles
A5: 4 | B5: Lavado Pebbles
A6: 5 | B6: Flotación
A7: 6 | B7: Cal y Reactivos
A8: 7 | B8: Espesamiento
A9: 8 | B9: Tranque
A10: 9 | B10: Suministro y Calidad de Aguas
A11: 10 | B11: Mineroducto
A12: 11 | B12: Puerto
A13: 12 | B13: Lixiviación

Sheet Areas
A1: ID | B1: Title | C1: l ids
A2: 1 | B2: Concentradora Linea 1
A3: 2 | B3: Concentradora Linea 2
A4: 3 | B4: Concentradora Linea 3
A5: 4 | B5: Planta Lavado Pebbles
A6: 5 | B6: Planta chancado Pebbles
A7: 6 | B7: Planta CAL 1
A8: 7 | B8: Planta CAL 2
A9: 8 | B9: Planta Xantato
A10: 9 | B10: Planta Floculante
A11: 10 | B11: Chancado – Area 2 / Fase 2
A12: 11 | B12: Chancado – Area 3
A13: 12 | B13: Chancado Fase 1
... A23: 23 | B23: Area Seca

Sheet Responsables
A1: Chars
A2: Alfaro Morgado Leonardo I. (LIALFARO@collahuasi.cl)
A3: Avalos Gabilondo Luis E. (LEAVALOS@collahuasi.cl)
A4: Bugueño Gonzalez Julio A. (JABUGUENO@COLLAHUASI.CL)
A5: Cornejo Sanchez Fernando A. (FACORNEJO@collahuasi.cl)
A6: Donoso Nogales Pedro A. (PADONOSO@collahuasi.cl)
A7: Figueroa Garrido Fabian E. (FEFIGUEROA@collahuasi.cl)
A8: Gomez Araya Freddy Andres (FAGOMEZ@collahuasi.cl)
A9: Isasmendi Merino Javier I. (Javier.isasmendi@collahuasi.cl)
A10: Jara Inostroza Marcelo I. (MIJARA@collahuasi.cl)
A11: Lizama Donoso Andrés A. (AALIZAMA@collahuasi.cl)
A12: Melo Miranda Fernando A. (FMELO@collahuasi.cl)
... A105: Veloso Salazar Rene A. (RAVELOSO.ESED@collahuasi.cl)

Sheet Actividades
A1: ID | B1: Titulo | C1: Tareas | D1: AvancePlanificado | E1: AvanceReal | F1: Ponderacion | G1: PonderacionActividad
A2: 1 | B2: A. PLANIFICACION DEL MANTENIMIENTO | C2: =COUNTIF(Tareas!M2:M24,1) -> 21 | D2: =SUM(Tareas!E2:E24) -> 100 | E2: =SUM(Tareas!F2:F24) -> 57.6 | F2: =E2*G2/100 -> 5.76 | G2: 10
A3: 2 | B3: B. REVISION Y VALIDACION ACTIVIDADES PROGRAMADAS | C3: =COUNTIF(Tareas!M25:M32,1) -> 4 | D3: =SUM(Tareas!E25:E32) -> 100 | E3: =SUM(Tareas!F25:F32) -> 100 | F3: =E3*G3/100 -> 10 | G3: 10
A4: 3 | B4: C. GESTION DE SEGURIDAD Y SALUD | C4: =COUNTIF(Tareas!M33:M46,1) -> 11 | D4: =SUM(Tareas!E33:E46) -> 100 | E4: =SUM(Tareas!F33:F46) -> 27.3 | F4: =E4*G4/100 -> 2.73 | G4: 10
A5: 4 | B5: D. GESTION MEDIO AMBIENTE | C5: =COUNTIF(Tareas!M47:M50,1) -> 2 | D5: =SUM(Tareas!E47:E50) -> 100 | E5: =SUM(Tareas!F47:F50) -> 50 | F5: =E5*G5/100 -> 5 | G5: 10
A6: 5 | B6: E. DOTACIONES DEL MANTENIMIENTO | C6: =COUNTIF(Tareas!M51:M58,1) -> 7 | D6: =SUM(Tareas!E51:E58) -> 100 | E6: =SUM(Tareas!F51:F58) -> 28.6 | F6: =E6*G6/100 -> 2.86 | G6: 10
A7: 6 | B7: F. GESTION DE REPUESTOS Y MATERIALES | C7: =COUNTIF(Tareas!M59:M83,1) -> 22 | D7: =SUM(Tareas!E59:E83) -> 100 | E7: =SUM(Tareas!F59:F83) -> 54 | F7: =E7*G7/100 -> 5.4 | G7: 10
A8: 7 | B8: G. SERVICIOS AL PERSONAL | C8: =COUNTIF(Tareas!M84:M88,1) -> 4 | D8: =SUM(Tareas!E84:E88) -> 100 | E8: =SUM(Tareas!F84:F88) -> 75 | F8: =E8*G8/100 -> 3.75 | G8: 5
A9: 8 | B9: H. SERVICIOS DE APOYO Y EQUIPOS | C9: =COUNTIF(Tareas!M89:M99,1) -> 9 | D9: =SUM(Tareas!E89:E99) -> 100 | E9: =SUM(Tareas!F89:F99) -> 10 | F9: =E9*G9/100 -> 1 | G9: 10
A10: 9 | B10: I. GESTION DE PERSONAS | C10: =COUNTIF(Tareas!M100:M107,1) -> 4 | D10: =SUM(Tareas!E100:E107) -> 100 | E10: =SUM(Tareas!F100:F107) -> 0 | F10: =E10*G10/100 -> 0 | G10: 10
A11: 10 | B11: J. GESTION Y CONTROL DE LA EJECUCION DEL MANTENIMIENTO | C11: =COUNTIF(Tareas!M108:M116,1) -> 8 | D11: =SUM(Tareas!E108:E116) -> 100 | E11: =SUM(Tareas!F108:F116) -> 0 | F11: =E11*G11/100 -> 0 | G11: 10
A12: 11 | B12: K. GESTION CIERRE MANTENIMIENTO | C12: =COUNTIF(Tareas!M117:M128,1) -> 12 | D12: =SUM(Tareas!E117:E128) -> 100 | E12: =SUM(Tareas!F117:F128) -> 0 | F12: =E12*G12/100 -> 0 | G12: 5

Sheet Grafico
A1: ID | B1: Titulo | C1: Tareas | D1: AvancePlanificado | E1: AvanceReal | F1: REAL | G1: PonderacionActividad | H1: Planificado
A2: 1 | B2: A. PLANIFICACION DEL MANTENIMIENTO | C2: =Actividades!C2 -> 21 | D2: =Actividades!D2 -> 100 | E2: =Actividades!E2 -> 57.6 | F2: =Actividades!F2 -> 5.76 | G2: =Actividades!G2 -> 10 | H2: =D2*G2/100 -> 10
A3: 2 | B3: B. REVISION Y VALIDACION ACTIVIDADES PROGRAMADAS | C3: =Actividades!C3 -> 4 | D3: =Actividades!D3 -> 100 | E3: =Actividades!E3 -> 100 | F3: =Actividades!F3 -> 10 | G3: =Actividades!G3 -> 10 | H3: =D3*G3/100 -> 10
A4: 3 | B4: C. GESTION DE SEGURIDAD Y SALUD | C4: =Actividades!C4 -> 11 | D4: =Actividades!D4 -> 100 | E4: =Actividades!E4 -> 27.3 | F4: =Actividades!F4 -> 2.73 | G4: =Actividades!G4 -> 10 | H4: =D4*G4/100 -> 10
A5: 4 | B5: D. GESTION MEDIO AMBIENTE | C5: =Actividades!C5 -> 2 | D5: =Actividades!D5 -> 100 | E5: =Actividades!E5 -> 50 | F5: =Actividades!F5 -> 5 | G5: =Actividades!G5 -> 10 | H5: =D5*G5/100 -> 10
A6: 5 | B6: E. DOTACIONES DEL MANTENIMIENTO | C6: =[2]Actividades!C6 -> 7 | D6: =Actividades!D6 -> 100 | E6: =Actividades!E6 -> 28.6 | F6: =Actividades!F6 -> 2.86 | G6: =Actividades!G6 -> 10 | H6: =D6*G6/100 -> 10
A7: 6 | B7: F. GESTION DE REPUESTOS Y MATERIALES | C7: =[2]Actividades!C7 -> 22 | D7: =Actividades!D7 -> 100 | E7: =Actividades!E7 -> 54 | F7: =Actividades!F7 -> 5.4 | G7: =Actividades!G7 -> 10 | H7: =D7*G7/100 -> 10
A8: 7 | B8: G. SERVICIOS AL PERSONAL | C8: =[2]Actividades!C8 -> 5 | D8: =Actividades!D8 -> 100 | E8: =Actividades!E8 -> 75 | F8: =Actividades!F8 -> 3.75 | G8: =Actividades!G8 -> 5 | H8: =D8*G8/100 -> 5
A9: 8 | B9: H. SERVICIOS DE APOYO Y EQUIPOS | C9: =[2]Actividades!C9 -> 8 | D9: =Actividades!D9 -> 100 | E9: =Actividades!E9 -> 10 | F9: =Actividades!F9 -> 1 | G9: =Actividades!G9 -> 10 | H9: =D9*G9/100 -> 10
A10: 9 | B10: I. GESTION DE PERSONAS | C10: =[2]Actividades!C10 -> 4 | D10: =Actividades!D10 -> 100 | E10: =Actividades!E10 -> 0 | F10: =Actividades!F10 -> 0 | G10: =Actividades!G10 -> 10 | H10: =D10*G10/100 -> 10
A11: 10 | B11: J. GESTION Y CONTROL DE LA EJECUCION DEL MANTENIMIENTO | C11: =[2]Actividades!C11 -> 8 | D11: =Actividades!D11 -> 100 | E11: =Actividades!E11 -> 0 | F11: =Actividades!F11 -> 0 | G11: =Actividades!G11 -> 10 | H11: =D11*G11/100 -> 10
A12: 11 | B12: K. GESTION CIERRE MANTENIMIENTO | C12: =[2]Actividades!C12 -> 12 | D12: =Actividades!D12 -> 100 | E12: =Actividades!E12 -> 0 | F12: =Actividades!F12 -> 0 | G12: =Actividades!G12 -> 5 | H12: =D12*G12/100 -> 5
B14: SUMA | C14: =SUM(C2:C12) -> 104 | D14: =SUM(D2:D12) -> 1100 | E14: =SUM(E2:E12) -> 402.5 | F14: =SUM(F2:F12) -> 36.5 | G14: =SUM(G2:G12) -> 100 | H14: =SUM(H2:H12) -> 100

Sheet MATRIZ REPUESTOS LUBRICACION
G1: MATRIZ DE REPUESTOS LUBRICACION.
F4: FAENA : | G4: PUERTO CMDIC GMT1401A
F5: EQUIPO APL : | G5: FILTROS PUERTO
B7: INICIO DEL MANTENIMIENTO | G7: 44819 | N7: Real | O7: Esperado a la fecha
B8: Area: | G8: Filtrado y Embarque | L8: =G17 -> REPUESTOS HIDRAULICOS | N8: =M17*0.5 -> 0 | O8: =P17*0.5 -> 0.5 | P8: n
B9: Revisado por: | F9: Armando Pizarro/ Pedro Perez | P9: n
B10: Jefe de Área | F10: Juan Marisio
B11: Equipo | F11: 310FL003 | G11: ='[3]MATRIZ REPUESTOS MECANICOS'!G11 -> MANTENCION SEMESTRAL FILTRO PRENSA
B12: Fecha de Hoy | F12: =TODAY() -> 46163 | G12: =TODAY() -> 46163
B13: SD | F13: =[4]!HAZOP[Codigo] -> #REF!
L14: Cumplimiento del Area | N14: =SUM(N8:N12) -> 0 | O14: =SUM(O8:O12) -> 0.5 | P14: n
B16: ID | C16: CODIGO | D16: Stock Bodega | E16: Cant. Req. | F16: SALDO STOCK | G16: REPUESTOS | H16: APLICA | I16: Pond | J16: Frec | K16: DeadLine | L16: Avance | M16: Avance Ponderado | N16: Observaciones | O16: Evidencia | P16: Esperado
B17: 1 | C17: CODIGO | D17: Stock Bodega | E17: Cant. Req. | F17: SALDO STOCK | G17: REPUESTOS HIDRAULICOS | H17: APLICA | I17: =SUM(I23:I30) -> 1 | J17: FREC | K17: DEAD LINE | L17: =AVERAGE(L23:L30) -> 0 | M17: =SUM(M23:M30) -> 0 | N17: OBSERVACIONES | O17: RQ: | P17: =SUM(P23:P30) -> 1
B18: 1.0.1 | C18: 55442 | D18: =IFERROR(VLOOKUP(C18,Tabla_APL[[STOCKCODE]:[TYPE]],3,FALSE),"") -> 6 | E18: =[5]Repuestos!F37 -> 1 | F18: =D18-E18 -> 5 | G18: FILTRO DE VENTILACION | H18: 0 | I18: =IF(H18=1,1/SUM(H$18:H$22),0) -> 0 | J18: 40 | K18: ='[3]MATRIZ REPUESTOS ELEC. INSTRU.'!$G$7-J18 -> 44779 | L18: 0 | M18: =I18*L18 -> 0 | P18: =(IF(K18<=TODAY(),1,0))*I18 -> 0
B19: 1.0.2 | C19: 16584 | D19: =IFERROR(VLOOKUP(C19,Tabla_APL[[STOCKCODE]:[TYPE]],3,FALSE),"") -> 6 | E19: =[5]Repuestos!F38 -> 5 | F19: =D19-E19 -> 1 | G19: FILTRO DESECHABLE FS06C | H19: 0 | I19: =IF(H19=1,1/SUM(H$18:H$22),0) -> 0 | J19: 40 | K19: ='[3]MATRIZ REPUESTOS ELEC. INSTRU.'!$G$7-J19 -> 44779 | L19: 0 | M19: =I19*L19 -> 0 | P19: =(IF(K19<=TODAY(),1,0))*I19 -> 0
B20: 1.0.3 | C20: 300798 | D20: =IFERROR(VLOOKUP(C20,Tabla_APL[[STOCKCODE]:[TYPE]],3,FALSE),"") -> 5 | E20: =[5]Repuestos!F39 -> 5 | F20: =D20-E20 -> 0 | G20: MANOMETRO PRESION 0-400 BAR | H20: 0 | I20: =IF(H20=1,1/SUM(H$18:H$22),0) -> 0 | J20: 40 | K20: ='[3]MATRIZ REPUESTOS ELEC. INSTRU.'!$G$7-J20 -> 44779 | L20: 0 | M20: =I20*L20 -> 0 | N20: SOLICITAR A FERRETERIA | P20: =(IF(K20<=TODAY(),1,0))*I20 -> 0
B21: 1.0.4 | C21: 300780 | D21: =IFERROR(VLOOKUP(C21,Tabla_APL[[STOCKCODE]:[TYPE]],3,FALSE),"") -> 15 | E21: =[5]Repuestos!F40 -> 5 | F21: =D21-E21 -> 10 | G21: MANOMETRO PRESION 0-60 BAR | H21: 1 | I21: =IF(H21=1,1/SUM(H$18:H$22),0) -> 1 | J21: 40 | K21: ='[3]MATRIZ REPUESTOS ELEC. INSTRU.'!$G$7-J21 -> 44779 | L21: 0 | M21: =I21*L21 -> 0 | N21: SOLICITAR A FERRETERIA | P21: =(IF(K21<=TODAY(),1,0))*I21 -> 1
B22: 1.0.5 | C22: 744049 | D22: =IFERROR(VLOOKUP(C22,Tabla_APL[[STOCKCODE]:[TYPE]],3,FALSE),"") -> 56 | E22: =[5]Repuestos!F41 -> 2 | F22: =D22-E22 -> 54 | G22: MINI LUBER MODEL 125CC | H22: 0 | I22: =IF(H22=1,1/SUM(H$18:H$22),0) -> 0 | J22: 40 | K22: ='[3]MATRIZ REPUESTOS ELEC. INSTRU.'!$G$7-J22 -> 44779 | L22: 0 | M22: =I22*L22 -> 0 | P22: =(IF(K22<=TODAY(),1,0))*I22 -> 0
B23: 1.0.7 | C23: 758539 | D23: =IFERROR(VLOOKUP(C23,Tabla_APL[[STOCKCODE]:[TYPE]],3,FALSE),"") -> 0 | E23: 4 | F23: =D23-E23 -> -4 | G23: PORTAFILTRO | H23: 0 | I23: =IF(H23=1,1/SUM(H$23:H$30),0) -> 0 | J23: 40 | K23: =$G$7-J23 -> 44779 | L23: 0 | M23: =I23*L23 -> 0 | P23: =(IF(K23<=TODAY(),1,0))*I23 -> 0
B24: 1.0.9 | C24: 395343 | D24: =IFERROR(VLOOKUP(C24,Tabla_APL[[STOCKCODE]:[TYPE]],3,FALSE),"") -> 0 | E24: 1 | F24: =D24-E24 -> -1 | G24: HYDRAULCI HOSE, 1014-20 BLOQUEADO PROCESO OBSOLETO 2012 | H24: 0 | I24: =IF(H24=1,1/SUM(H$23:H$30),0) -> 0 | J24: 40 | K24: =$G$7-J24 -> 44779 | L24: 0 | M24: =I24*L24 -> 0 | P24: =(IF(K24<=TODAY(),1,0))*I24 -> 0
B25: 1.0.10 | C25: 395350 | D25: =IFERROR(VLOOKUP(C25,Tabla_APL[[STOCKCODE]:[TYPE]],3,FALSE),"") -> 0 | E25: 1 | F25: =D25-E25 -> -1 | G25: HYDRAULCI HOSE, 1014-20 BLOQUEADO PROCESO OBSOLETO 2012 | H25: 0 | I25: =IF(H25=1,1/SUM(H$23:H$30),0) -> 0 | J25: 40 | K25: =$G$7-J25 -> 44779 | L25: 0 | M25: =I25*L25 -> 0 | P25: =(IF(K25<=TODAY(),1,0))*I25 -> 0
B26: 1.0.11 | C26: 395368 | D26: =IFERROR(VLOOKUP(C26,Tabla_APL[[STOCKCODE]:[TYPE]],3,FALSE),"") -> 0 | E26: 1 | F26: =D26-E26 -> -1 | G26: HYDRAULCI HOSE, 720-08 BLOQUEADO PROCESO OBSOLETO 2012 | H26: 0 | I26: =IF(H26=1,1/SUM(H$23:H$30),0) -> 0 | J26: 40 | K26: =$G$7-J26 -> 44779 | L26: 0 | M26: =I26*L26 -> 0 | P26: =(IF(K26<=TODAY(),1,0))*I26 -> 0
B27: 1.0.12 | C27: 395376 | D27: =IFERROR(VLOOKUP(C27,Tabla_APL[[STOCKCODE]:[TYPE]],3,FALSE),"") -> 0 | E27: 1 | F27: =D27-E27 -> -1 | G27: HYDRAULCI HOSE, 720-08 BLOQUEADO PROCESO OBSOLETO 2012 | H27: 0 | I27: =IF(H27=1,1/SUM(H$23:H$30),0) -> 0 | J27: 40 | K27: =$G$7-J27 -> 44779 | L27: 0 | M27: =I27*L27 -> 0 | P27: =(IF(K27<=TODAY(),1,0))*I27 -> 0
B28: 1.0.13 | C28: 395384 | D28: =IFERROR(VLOOKUP(C28,Tabla_APL[[STOCKCODE]:[TYPE]],3,FALSE),"") -> 0 | E28: 1 | F28: =D28-E28 -> -1 | G28: HYDRAULCI HOSE, 720-08 BLOQUEADO PROCESO OBSOLETO 2012 | H28: 0 | I28: =IF(H28=1,1/SUM(H$23:H$30),0) -> 0 | J28: 40 | K28: =$G$7-J28 -> 44779 | L28: 0 | M28: =I28*L28 -> 0 | P28: =(IF(K28<=TODAY(),1,0))*I28 -> 0
B29: 1.0.14 | C29: 128603 | D29: =IFERROR(VLOOKUP(C29,Tabla_APL[[STOCKCODE]:[TYPE]],3,FALSE),"") -> 1 | E29: 1 | F29: =D29-E29 -> 0 | G29: Código Ferreteria CS 000747913 | H29: 1 | I29: =IF(H29=1,1/SUM(H$23:H$30),0) -> 0.5 | J29: 40 | K29: =$G$7-J29 -> 44779 | L29: 0 | M29: =I29*L29 -> 0 | P29: =(IF(K29<=TODAY(),1,0))*I29 -> 0.5
B30: 1.0.16 | C30: 166801 | D30: =IFERROR(VLOOKUP(C30,Tabla_APL[[STOCKCODE]:[TYPE]],3,FALSE),"") -> 34 | E30: 6 | F30: =D30-E30 -> 28 | G30: LUBRICADOR AUTOMATICO 150 GRS | H30: 1 | I30: =IF(H30=1,1/SUM(H$23:H$30),0) -> 0.5 | J30: 40 | K30: =$G$7-J30 -> 44779 | L30: 0 | M30: =I30*L30 -> 0 | P30: =(IF(K30<=TODAY(),1,0))*I30 -> 0.5
B31: 1.0.20 | C31: 657148 | D31: =IFERROR(VLOOKUP(C31,Tabla_APL[[STOCKCODE]:[TYPE]],3,FALSE),"") -> 0 | E31: 4 | F31: =D31-E31 -> -4 | G31: Mobil SHC 632 | H31: 3 | I31: =IF(H31=1,1/SUM(H$23:H$30),0) -> 0 | J31: 42 | K31: =$G$7-J31 -> 44777 | L31: 0 | M31: =I31*L31 -> 0 | N31: CUANDO HAY CAMBIO DE ACEITE SOLICITAR 4 | P31: =(IF(K31<=TODAY(),1,0))*I31 -> 0
B32: 1.0.6 | C32: 73700 | D32: =IFERROR(VLOOKUP(C32,Tabla_APL[[STOCKCODE]:[TYPE]],3,FALSE),"") -> 2 | E32: 0 | F32: =D32-E32 -> 2 | G32: BOMBA ALTA PRESION | H32: 0 | I32: =IF(H32=1,1/SUM(H$23:H$30),0) -> 0 | J32: 40 | K32: =$G$7-J32 -> 44779 | L32: 0 | M32: =I32*L32 -> 0 | P32: =(IF(K32<=TODAY(),1,0))*I32 -> 0
C33: 537746 | G33: FILTRO RESPIRADERO SILICA GEL

Sheet Matriz Rep. Mec.
G1: MATRIZ DE REPUESTOS Y INSUMES MECÁNICOS
F4: FAENA : | G4: PUERTO CMDIC GMT1401A
F5: EQUIPO APL : | G5: FILTROS PUERTO
B7: INICIO DEL MANTENIMIENTO | G7: =HAZOP[FechaVencimiento]-13 -> 44021 | N7: Real | O7: Esperado a la fecha
B8: Area: | G8: Filtrado y Embarque | L8: =G16 -> REPUESTOS MECÁNICOS | N8: =((M17+M30+M54+M73+M88+M93+M102+M110+M116+M135)/10)*0.2 -> 0.054190476 | O8: =((P17+P30+P54+P73+P88+P93+P102+P110+P116+P135)/10)*0.2 -> 0.19492063 | P8: n
B9: Revisado por: | F9: Armando Pizarro/ Pedro Perez | L9: =G165 -> HERRAMIENTAS | N9: =M165*0.2 -> 0 | O9: =P165*0.2 -> 0.2 | P9: n
B10: Jefe de Área | F10: Juan Marisio | L10: =G197 -> INSTRUMENTO Y EQUIPO | N10: =M197*0.2 -> 0 | O10: =P197*0.2 -> 0.2 | P10: n
B11: Equipo | F11: 310FL003 | G11: 310FL00X | L11: =G217 -> MATERIALES GENERALES | N11: =M217*0.2 -> 0 | O11: =P217*0.2 -> 0.2 | P11: n
B12: Fecha de Hoy | F12: =TODAY() -> 46163 | G12: =TODAY() -> 46163 | L12: =G229 -> EPP | N12: =M229*0.2 -> 0 | O12: =P229*0.2 -> 0.2 | P12: n
B13: SD | F13: =[1]!HAZOP[Codigo] -> #REF! | G13: =HAZOP[Codigo] -> SD 2187
L14: Cumplimiento del Area | N14: =SUM(N8:N12) -> 0.054190476 | O14: =SUM(O8:O12) -> 0.99492063 | P14: n
B16: ID | C16: CODIGO | D16: Stock Bodega | E16: Cant. Req. | F16: SALDO STOCK | G16: REPUESTOS MECÁNICOS | H16: APLICA | I16: Pond | J16: Frec | K16: DeadLine | L16: Avance | M16: Avance Ponderado | N16: Observaciones | O16: Evidencia | P16: Esperado
B17: 1 | C17: CODIGO | D17: Stock Bodega | E17: Cant. Req. | F17: SALDO STOCK | G17: LINEA AIRE MEMBRANA | H17: APLICA | I17: =SUM(I18:I29) -> 1 | J17: FREC | K17: DEAD LINE | L17: =AVERAGE(L18:L29) -> 0.3 | M17: =SUM(M18:M29) -> 0.3 | N17: OBSERVACIONES | O17: RQ: | P17: =SUM(P18:P29) -> 1
B18: 1.0.1 | C18: 746231 | D18: =IFERROR(VLOOKUP(C18,Tabla_APL[[STOCKCODE]:[TYPE]],3,FALSE),"") -> 4 | E18: 1 | F18: =D18-E18 -> 3 | G18: CAÑERIA CON BRIDAS (CABEZAL FIJO) | H18: 1 | I18: =IF(H18=1,1/SUM(H$18:H$29),0) -> 0.083333333 | J18: 40 | K18: =$G$7-J18 -> 43981 | L18: 0.3 | M18: =I18*L18 -> 0.025 | N18: SE GENERA RQ CON 95 ITEM | O18: A64881 | P18: =(IF(K18<=TODAY(),1,0))*I18 -> 0.083333333
B19: 1.0.2 | C19: 746218 | D19: =IFERROR(VLOOKUP(C19,Tabla_APL[[STOCKCODE]:[TYPE]],3,FALSE),"") -> 4 | E19: 1 | F19: =D19-E19 -> 3 | G19: CAÑERIA CON BRIDAS (CUELLO CISNE) | H19: 1 | I19: =IF(H19=1,1/SUM(H$18:H$29),0) -> 0.083333333 | J19: 40 | K19: =$G$7-J19 -> 43981 | L19: 0.3 | M19: =I19*L19 -> 0.025 | P19: =(IF(K19<=TODAY(),1,0))*I19 -> 0.083333333
B20: 1.0.3 | C20: 746232 | D20: =IFERROR(VLOOKUP(C20,Tabla_APL[[STOCKCODE]:[TYPE]],3,FALSE),"") -> 8 | E20: 1 | F20: =D20-E20 -> 7 | G20: CAÑERIA CON BRIDAS (FLAUTA) | H20: 1 | I20: =IF(H20=1,1/SUM(H$18:H$29),0) -> 0.083333333 | J20: 40 | K20: =$G$7-J20 -> 43981 | L20: 0.3 | M20: =I20*L20 -> 0.025 | P20: =(IF(K20<=TODAY(),1,0))*I20 -> 0.083333333
B21: 1.0.4 | C21: 123216 | D21: =IFERROR(VLOOKUP(C21,Tabla_APL[[STOCKCODE]:[TYPE]],3,FALSE),"") -> 16 | E21: 1 | F21: =D21-E21 -> 15 | G21: VALVULA RETENCION (NO REPARABLE J. T.) | H21: 1 | I21: =IF(H21=1,1/SUM(H$18:H$29),0) -> 0.083333333 | J21: 40 | K21: =$G$7-J21 -> 43981 | L21: 0.3 | M21: =I21*L21 -> 0.025 | P21: =(IF(K21<=TODAY(),1,0))*I21 -> 0.083333333
B22: 1.0.5 | C22: 88948 | D22: =IFERROR(VLOOKUP(C22,Tabla_APL[[STOCKCODE]:[TYPE]],3,FALSE),"") -> 47 | E22: 1 | F22: =D22-E22 -> 46 | G22: VALVULA CHECK | H22: 1 | I22: =IF(H22=1,1/SUM(H$18:H$29),0) -> 0.083333333 | J22: 40 | K22: =$G$7-J22 -> 43981 | L22: 0.3 | M22: =I22*L22 -> 0.025 | P22: =(IF(K22<=TODAY(),1,0))*I22 -> 0.083333333
B23: 1.0.6 | C23: 123224 | D23: =IFERROR(VLOOKUP(C23,Tabla_APL[[STOCKCODE]:[TYPE]],3,FALSE),"") -> 28 | E23: 2 | F23: =D23-E23 -> 26 | G23: JUNTA EXPANSION 2" ANSI 150 LBS | H23: 1 | I23: =IF(H23=1,1/SUM(H$18:H$29),0) -> 0.083333333 | J23: 40 | K23: =$G$7-J23 -> 43981 | L23: 0.3 | M23: =I23*L23 -> 0.025 | P23: =(IF(K23<=TODAY(),1,0))*I23 -> 0.083333333
B24: 1.0.7 | C24: 114330 | D24: 28 | E24: 2 | F24: =D24-E24 -> 26 | G24: VALVULA V7 / V10/070-120 DN50/PN V10 | H24: 1 | I24: =IF(H24=1,1/SUM(H$18:H$29),0) -> 0.083333333 | J24: 40 | K24: =$G$7-J24 -> 43981 | L24: 0.3 | M24: =I24*L24 -> 0.025 | P24: =(IF(K24<=TODAY(),1,0))*I24 -> 0.083333333
B25: 1.0.8 | C25: 746233 | D25: =IFERROR(VLOOKUP(C25,Tabla_APL[[STOCKCODE]:[TYPE]],3,FALSE),"") -> 10 | E25: 2 | F25: =D25-E25 -> 8 | G25: CAÑERIA CON BRIDAS(top blow) | H25: 1 | I25: =IF(H25=1,1/SUM(H$18:H$29),0) -> 0.083333333 | J25: 40 | K25: =$G$7-J25 -> 43981 | L25: 0.3 | M25: =I25*L25 -> 0.025 | P25: =(IF(K25<=TODAY(),1,0))*I25 -> 0.083333333
B26: 1.0.9 | C26: 448068 | D26: =IFERROR(VLOOKUP(C26,Tabla_APL[[STOCKCODE]:[TYPE]],3,FALSE),"") -> 11 | E26: 1 | F26: =D26-E26 -> 10 | G26: VALVULA REGULADORA DE PRESION | H26: 1 | I26: =IF(H26=1,1/SUM(H$18:H$29),0) -> 0.083333333 | J26: 40 | K26: =$G$7-J26 -> 43981 | L26: 0.3 | M26: =I26*L26 -> 0.025 | P26: =(IF(K26<=TODAY(),1,0))*I26 -> 0.083333333
B27: 1.0.10 | C27: 746234 | D27: =IFERROR(VLOOKUP(C27,Tabla_APL[[STOCKCODE]:[TYPE]],3,FALSE),"") -> 5 | E27: 1 | F27: =D27-E27 -> 4 | G27: CAÑERIA CON BRIDAS | H27: 1 | I27: =IF(H27=1,1/SUM(H$18:H$29),0) -> 0.083333333 | J27: 40 | K27: =$G$7-J27 -> 43981 | L27: 0.3 | M27: =I27*L27 -> 0.025 | P27: =(IF(K27<=TODAY(),1,0))*I27 -> 0.083333333
B28: 1.0.11 | C28: 155762 | D28: =IFERROR(VLOOKUP(C28,Tabla_APL[[STOCKCODE]:[TYPE]],3,FALSE),"") -> 21 | E28: 1 | F28: =D28-E28 -> 20 | G28: VALVULA DN 50/PN10 (VV manual) | H28: 1 | I28: =IF(H28=1,1/SUM(H$18:H$29),0) -> 0.083333333 | J28: 40 | K28: =$G$7-J28 -> 43981 | L28: 0.3 | M28: =I28*L28 -> 0.025 | P28: =(IF(K28<=TODAY(),1,0))*I28 -> 0.083333333
B29: 1.0.12 | C29: 746235 | D29: =IFERROR(VLOOKUP(C29,Tabla_APL[[STOCKCODE]:[TYPE]],3,FALSE),"") -> 4 | E29: 1 | F29: =D29-E29 -> 3 | G29: CAÑERIA BRIDAS | H29: 1 | I29: =IF(H29=1,1/SUM(H$18:H$29),0) -> 0.083333333 | J29: 40 | K29: =$G$7-J29 -> 43981 | L29: 0.3 | M29: =I29*L29 -> 0.025 | P29: =(IF(K29<=TODAY(),1,0))*I29 -> 0.083333333
B30: 1.1 | C30: CODIGO | D30: Stock Bodega | E30: Cant. Req. | F30: EXISTENCIA | G30: LINEA SOPLADO SUPERIOR | H30: APLICA | I30: =SUM(I31:I53) -> 1 | J30: FREC | K30: DEAD LINE | L30: =AVERAGE(L31:L53) -> 0.3 | M30: =SUM(M31:M53) -> 0.3 | N30: OBSERVACIONES | O30: RQ: | P30: =SUM(P31:P53) -> 1
B31: 1.1.1 | C31: 123224 | D31: =IFERROR(VLOOKUP(C31,Tabla_APL[[STOCKCODE]:[TYPE]],3,FALSE),"") -> 28 | E31: 2 | F31: =D31-E31 -> 26 | G31: JUNTA EXPANSION 2" ANSI 150 LBS | H31: 1 | I31: =IF(H31=1,1/SUM(H$31:H$53),0) -> 0.045454545 | J31: 40 | K31: =$G$7-J31 -> 43981 | L31: 0.3 | M31: =I31*L31 -> 0.013636364 | P31: =(IF(K31<=TODAY(),1,0))*I31 -> 0.045454545
B32: 1.1.2 | C32: 746221 | D32: =IFERROR(VLOOKUP(C32,Tabla_APL[[STOCKCODE]:[TYPE]],3,FALSE),"") -> 10 | E32: 2 | F32: =D32-E32 -> 8 | G32: CAÑERIA CON BRIDAS | H32: 1 | I32: =IF(H32=1,1/SUM(H$31:H$53),0) -> 0.045454545 | J32: 40 | K32: =$G$7-J32 -> 43981 | L32: 0.3 | M32: =I32*L32 -> 0.013636364 | P32: =(IF(K32<=TODAY(),1,0))*I32 -> 0.045454545
B33: 1.1.3 | C33: 155762 | D33: =IFERROR(VLOOKUP(C33,Tabla_APL[[STOCKCODE]:[TYPE]],3,FALSE),"") -> 21 | E33: 2 | F33: =D33-E33 -> 19 | G33: VALVULA DN 50/PN10 (VV manual) | H33: 1 | I33: =IF(H33=1,1/SUM(H$31:H$53),0) -> 0.045454545 | J33: 40 | K33: =$G$7-J33 -> 43981 | L33: 0.3 | M33: =I33*L33 -> 0.013636364 | P33: =(IF(K33<=TODAY(),1,0))*I33 -> 0.045454545
B34: 1.1.4 | C34: 746222 | D34: =IFERROR(VLOOKUP(C34,Tabla_APL[[STOCKCODE]:[TYPE]],3,FALSE),"") -> 6 | E34: 1 | F34: =D34-E34 -> 5 | G34: CAÑERIA CON BRIDAS | H34: 1 | I34: =IF(H34=1,1/SUM(H$31:H$53),0) -> 0.045454545 | J34: 40 | K34: =$G$7-J34 -> 43981 | L34: 0.3 | M34: =I34*L34 -> 0.013636364 | P34: =(IF(K34<=TODAY(),1,0))*I34 -> 0.045454545
B35: 1.1.5 | C35: 746225 | D35: =IFERROR(VLOOKUP(C35,Tabla_APL[[STOCKCODE]:[TYPE]],3,FALSE),"") -> 10 | E35: 2 | F35: =D35-E35 -> 8 | G35: CAÑERIA CON BRIDAS | H35: 1 | I35: =IF(H35=1,1/SUM(H$31:H$53),0) -> 0.045454545 | J35: 40 | K35: =$G$7-J35 -> 43981 | L35: 0.3 | M35: =I35*L35 -> 0.013636364 | P35: =(IF(K35<=TODAY(),1,0))*I35 -> 0.045454545
B36: 1.1.6 | C36: 448068 | D36: =IFERROR(VLOOKUP(C36,Tabla_APL[[STOCKCODE]:[TYPE]],3,FALSE),"") -> 11 | E36: 1 | F36: =D36-E36 -> 10 | G36: VALVULA REGULADORA DE PRESION | H36: 1 | I36: =IF(H36=1,1/SUM(H$31:H$53),0) -> 0.045454545 | J36: 40 | K36: =$G$7-J36 -> 43981 | L36: 0.3 | M36: =I36*L36 -> 0.013636364 | P36: =(IF(K36<=TODAY(),1,0))*I36 -> 0.045454545
B37: 1.1.7 | C37: 155903 | D37: =IFERROR(VLOOKUP(C37,Tabla_APL[[STOCKCODE]:[TYPE]],3,FALSE),"") -> 8 | E37: 2 | F37: =D37-E37 -> 6 | G37: VALVULA DN50/PN16, RS-50/050-100 V6-V8 | H37: 1 | I37: =IF(H37=1,1/SUM(H$31:H$53),0) -> 0.045454545 | J37: 40 | K37: =$G$7-J37 -> 43981 | L37: 0.3 | M37: =I37*L37 -> 0.013636364 | P37: =(IF(K37<=TODAY(),1,0))*I37 -> 0.045454545
B38: 1.1.8 | C38: 6965 | D38: =IFERROR(VLOOKUP(C38,Tabla_APL[[STOCKCODE]:[TYPE]],3,FALSE),"") -> 78 | E38: 2 | F38: =D38-E38 -> 76 | G38: MANOMETRO; MANOMETRO 2-1/2"DIAL 0-200 PSI 1/4" NPT | H38: 1 | I38: =IF(H38=1,1/SUM(H$31:H$53),0) -> 0.045454545 | J38: 40 | K38: =$G$7-J38 -> 43981 | L38: 0.3 | M38: =I38*L38 -> 0.013636364 | P38: =(IF(K38<=TODAY(),1,0))*I38 -> 0.045454545
B39: 1.1.9 | C39: 155937 | D39: =IFERROR(VLOOKUP(C39,Tabla_APL[[STOCKCODE]:[TYPE]],3,FALSE),"") -> 10 | E39: 2 | F39: =D39-E39 -> 8 | G39: CAÑERIA CON BRIDAS | H39: 1 | I39: =IF(H39=1,1/SUM(H$31:H$53),0) -> 0.045454545 | J39: 40 | K39: =$G$7-J39 -> 43981 | L39: 0.3 | M39: =I39*L39 -> 0.013636364 | P39: =(IF(K39<=TODAY(),1,0))*I39 -> 0.045454545
B40: 1.1.15 | C40: 746224 | D40: =IFERROR(VLOOKUP(C40,Tabla_APL[[STOCKCODE]:[TYPE]],3,FALSE),"") -> 4 | E40: 1 | F40: =D40-E40 -> 3 | G40: DUCTO AIRE (2" cabezal movil) | H40: 1 | I40: =IF(H40=1,1/SUM(H$31:H$53),0) -> 0.045454545 | J40: 40 | K40: =$G$7-J40 -> 43981 | L40: 0.3 | M40: =I40*L40 -> 0.013636364 | P40: =(IF(K40<=TODAY(),1,0))*I40 -> 0.045454545
C41: 155762 | D41: =IFERROR(VLOOKUP(C41,Tabla_APL[[STOCKCODE]:[TYPE]],3,FALSE),"") -> 21 | G41: ´valvula mariposa 2"
B42: 1.1.16 | C42: 155853 | D42: =IFERROR(VLOOKUP(C42,Tabla_APL[[STOCKCODE]:[TYPE]],3,FALSE),"") -> 8 | E42: 2 | F42: =D42-E42 -> 6 | G42: ACOPLAMIENTO TUBO 2" | H42: 1 | I42: =IF(H42=1,1/SUM(H$31:H$53),0) -> 0.045454545 | J42: 40 | K42: =$G$7-J42 -> 43981 | L42: 0.3 | M42: =I42*L42 -> 0.013636364 | P42: =(IF(K42<=TODAY(),1,0))*I42 -> 0.045454545
B43: 1.1.17 | C43: 155861 | D43: =IFERROR(VLOOKUP(C43,Tabla_APL[[STOCKCODE]:[TYPE]],3,FALSE),"") -> 24 | E43: 2 | F43: =D43-E43 -> 22 | G43: ACOPLAMIENTO DE CAÑERIA RACOR DN50 (punta milano 2") | H43: 1 | I43: =IF(H43=1,1/SUM(H$31:H$53),0) -> 0.045454545 | J43: 40 | K43: =$G$7-J43 -> 43981 | L43: 0.3 | M43: =I43*L43 -> 0.013636364 | P43: =(IF(K43<=TODAY(),1,0))*I43 -> 0.045454545
B44: 1.1.18 | C44: 158147 | D44: =IFERROR(VLOOKUP(C44,Tabla_APL[[STOCKCODE]:[TYPE]],3,FALSE),"") -> 114 | E44: 17 | F44: =D44-E44 -> 97 | G44: ABRAZADERA SIN FIN 3" | H44: 1 | I44: =IF(H44=1,1/SUM(H$31:H$53),0) -> 0.045454545 | J44: 40 | K44: =$G$7-J44 -> 43981 | L44: 0.3 | M44: =I44*L44 -> 0.013636364 | P44: =(IF(K44<=TODAY(),1,0))*I44 -> 0.045454545
B45: 1.1.19 | C45: 158154 | D45: =IFERROR(VLOOKUP(C45,Tabla_APL[[STOCKCODE]:[TYPE]],3,FALSE),"") -> 34 | E45: 4 | F45: =D45-E45 -> 30 | G45: ABRAZADERA DE ALTA PRESION (HOSE CLAMP 2064.056065) | H45: 1 | I45: =IF(H45=1,1/SUM(H$31:H$53),0) -> 0.045454545 | J45: 40 | K45: =$G$7-J45 -> 43981 | L45: 0.3 | M45: =I45*L45 -> 0.013636364 | P45: =(IF(K45<=TODAY(),1,0))*I45 -> 0.045454545
B46: 1.1.20 | C46: 88831 | D46: =IFERROR(VLOOKUP(C46,Tabla_APL[[STOCKCODE]:[TYPE]],3,FALSE),"") -> 9 | E46: 1 | F46: =D46-E46 -> 8 | G46: MANGUERA (SOPLADO 2") | H46: 1 | I46: =IF(H46=1,1/SUM(H$31:H$53),0) -> 0.045454545 | J46: 40 | K46: =$G$7-J46 -> 43981 | L46: 0.3 | M46: =I46*L46 -> 0.013636364 | P46: =(IF(K46<=TODAY(),1,0))*I46 -> 0.045454545
B47: 1.1.21 | C47: 746223 | D47: =IFERROR(VLOOKUP(C47,Tabla_APL[[STOCKCODE]:[TYPE]],3,FALSE),"") -> 2 | E47: 1 | F47: =D47-E47 -> 1 | G47: CAÑERIA CON BRIDAS(CODO) | H47: 1 | I47: =IF(H47=1,1/SUM(H$31:H$53),0) -> 0.045454545 | J47: 40 | K47: =$G$7-J47 -> 43981 | L47: 0.3 | M47: =I47*L47 -> 0.013636364 | P47: =(IF(K47<=TODAY(),1,0))*I47 -> 0.045454545
B48: 1.1.22 | C48: 746219 | D48: =IFERROR(VLOOKUP(C48,Tabla_APL[[STOCKCODE]:[TYPE]],3,FALSE),"") -> 4 | E48: 1 | F48: =D48-E48 -> 3 | G48: CAÑERIA CÓNICO. | H48: 1 | I48: =IF(H48=1,1/SUM(H$31:H$53),0) -> 0.045454545 | J48: 40 | K48: =$G$7-J48 -> 43981 | L48: 0.3 | M48: =I48*L48 -> 0.013636364 | P48: =(IF(K48<=TODAY(),1,0))*I48 -> 0.045454545
B49: 1.1.23 | C49: 123216 | D49: =IFERROR(VLOOKUP(C49,Tabla_APL[[STOCKCODE]:[TYPE]],3,FALSE),"") -> 16 | E49: 1 | F49: =D49-E49 -> 15 | G49: VALVULA RETENCION (NO REPARABLE J. T.) | H49: 1 | I49: =IF(H49=1,1/SUM(H$31:H$53),0) -> 0.045454545 | J49: 40 | K49: =$G$7-J49 -> 43981 | L49: 0.3 | M49: =I49*L49 -> 0.013636364 | P49: =(IF(K49<=TODAY(),1,0))*I49 -> 0.045454545
B50: 1.1.24 | C50: 559385 | D50: =IFERROR(VLOOKUP(C50,Tabla_APL[[STOCKCODE]:[TYPE]],3,FALSE),"") -> 3 | E50: 2 | F50: =D50-E50 -> 1 | G50: DUCTO BRIDAS 6" | H50: 1 | I50: =IF(H50=1,1/SUM(H$31:H$53),0) -> 0.045454545 | J50: 40 | K50: =$G$7-J50 -> 43981 | L50: 0.3 | M50: =I50*L50 -> 0.013636364 | P50: =(IF(K50<=TODAY(),1,0))*I50 -> 0.045454545
B51: 1.1.25 | C51: 746220 | D51: =IFERROR(VLOOKUP(C51,Tabla_APL[[STOCKCODE]:[TYPE]],3,FALSE),"") -> 4 | E51: 1 | F51: =D51-E51 -> 3 | G51: CAÑERIA CON BRIDAS (carrete corto) | H51: 1 | I51: =IF(H51=1,1/SUM(H$31:H$53),0) -> 0.045454545 | J51: 40 | K51: =$G$7-J51 -> 43981 | L51: 0.3 | M51: =I51*L51 -> 0.013636364 | P51: =(IF(K51<=TODAY(),1,0))*I51 -> 0.045454545
B52: 1.1.26 | C52: 325316 | D52: =IFERROR(VLOOKUP(C52,Tabla_APL[[STOCKCODE]:[TYPE]],3,FALSE),"") -> 1 | E52: 1 | F52: =D52-E52 -> 0 | G52: FORRO DEGASTE FILTRO 6" | H52: 1 | I52: =IF(H52=1,1/SUM(H$31:H$53),0) -> 0.045454545 | J52: 40 | K52: =$G$7-J52 -> 43981 | L52: 0.3 | M52: =I52*L52 -> 0.013636364 | P52: =(IF(K52<=TODAY(),1,0))*I52 -> 0.045454545
B53: 1.1.27 | C53: 177899 | D53: =IFERROR(VLOOKUP(C53,Tabla_APL[[STOCKCODE]:[TYPE]],3,FALSE),"") -> 2563 | E53: 10 | F53: =D53-E53 -> 2553 | G53: CABLE; CABLE ACERO PLASTIFICADO 3/16" (mts) | H53: 1 | I53: =IF(H53=1,1/SUM(H$31:H$53),0) -> 0.045454545 | J53: 40 | K53: =$G$7-J53 -> 43981 | L53: 0.3 | M53: =I53*L53 -> 0.013636364 | P53: =(IF(K53<=TODAY(),1,0))*I53 -> 0.045454545
B54: 1.2 | C54: CODIGO | D54: Stock Bodega | E54: Cant. Req. | F54: EXISTENCIA | G54: ACCIONAMIENTO COMPUERTA | H54: APLICA | I54: =SUM(I55:I72) -> 1 | J54: FREC | K54: DEAD LINE | L54: =AVERAGE(L55:L72) -> 0.3 | M54: =SUM(M55:M72) -> 0.3 | N54: OBSERVACIONES | O54: RQ: | P54: =SUM(P55:P72) -> 1
B55: 1.2.1 | C55: 271460 | D55: =IFERROR(VLOOKUP(C29,Tabla_APL[[STOCKCODE]:[TYPE]],3,FALSE),"") -> 4 | E55: 2 | F55: =D55-E55 -> 2 | G55: EJE LADO AUXILIAR COMPUERTA FILTRO CORTO | H55: 1 | I55: =IF(H55=1,1/SUM(H$55:H$72),0) -> 0.055555556 | J55: 30 | K55: =$G$7-J55 -> 43991 | L55: 0.3 | M55: =I55*L55 -> 0.016666667 | P55: =(IF(K55<=TODAY(),1,0))*I55 -> 0.055555556
B56: 1.2.2 | C56: 648717 | D56: =IFERROR(VLOOKUP(C56,Tabla_APL[[STOCKCODE]:[TYPE]],3,FALSE),"") -> 9 | E56: 2 | F56: =D56-E56 -> 7 | G56: EJE HEXAGONAL LADO ACCIONAMIENTO | H56: 1 | I56: =IF(H56=1,1/SUM(H$55:H$72),0) -> 0.055555556 | J56: 30 | K56: =$G$7-J56 -> 43991 | L56: 0.3 | M56: =I56*L56 -> 0.016666667 | P56: =(IF(K56<=TODAY(),1,0))*I56 -> 0.055555556
B57: 1.2.3 | C57: 287151 | D57: =IFERROR(VLOOKUP(C57,Tabla_APL[[STOCKCODE]:[TYPE]],3,FALSE),"") -> 20 | E57: 2 | F57: =D57-E57 -> 18 | G57: SOPORTE RODAMIENTO | H57: 1 | I57: =IF(H57=1,1/SUM(H$55:H$72),0) -> 0.055555556 | J57: 30 | K57: =$G$7-J57 -> 43991 | L57: 0.3 | M57: =I57*L57 -> 0.016666667 | P57: =(IF(K57<=TODAY(),1,0))*I57 -> 0.055555556
B58: 1.2.4 | C58: 274605 | D58: =IFERROR(VLOOKUP(C58,Tabla_APL[[STOCKCODE]:[TYPE]],3,FALSE),"") -> 7 | E58: 4 | F58: =D58-E58 -> 3 | G58: RODAMIENTO BOLAS | H58: 1 | I58: =IF(H58=1,1/SUM(H$55:H$72),0) -> 0.055555556 | J58: 30 | K58: =$G$7-J58 -> 43991 | L58: 0.3 | M58: =I58*L58 -> 0.016666667 | P58: =(IF(K58<=TODAY(),1,0))*I58 -> 0.055555556
B59: 1.2.5 | C59: 287169 | D59: =IFERROR(VLOOKUP(C59,Tabla_APL[[STOCKCODE]:[TYPE]],3,FALSE),"") -> 30 | E59: 4 | F59: =D59-E59 -> 26 | G59: MANGUITO FIJACION - CASQUILLO RODAMIENTO COMPUERTA FILTRO | H59: 1 | I59: =IF(H59=1,1/SUM(H$55:H$72),0) -> 0.055555556 | J59: 30 | K59: =$G$7-J59 -> 43991 | L59: 0.3 | M59: =I59*L59 -> 0.016666667 | P59: =(IF(K59<=TODAY(),1,0))*I59 -> 0.055555556
B60: 1.2.6 | C60: 274613 | D60: =IFERROR(VLOOKUP(C60,Tabla_APL[[STOCKCODE]:[TYPE]],3,FALSE),"") -> 24 | E60: 4 | F60: =D60-E60 -> 20 | G60: ANILLO GUIA FRB 125/200 | H60: 1 | I60: =IF(H60=1,1/SUM(H$55:H$72),0) -> 0.055555556 | J60: 30 | K60: =$G$7-J60 -> 43991 | L60: 0.3 | M60: =I60*L60 -> 0.016666667 | P60: =(IF(K60<=TODAY(),1,0))*I60 -> 0.055555556
B61: 1.2.7 | C61: 274621 | D61: =IFERROR(VLOOKUP(C61,Tabla_APL[[STOCKCODE]:[TYPE]],3,FALSE),"") -> 9 | E61: 2 | F61: =D61-E61 -> 7 | G61: CASQUILLO ETP-100/125 - MANGUITO COMPUERTA FILTRO | H61: 1 | I61: =IF(H61=1,1/SUM(H$55:H$72),0) -> 0.055555556 | J61: 30 | K61: =$G$7-J61 -> 43991 | L61: 0.3 | M61: =I61*L61 -> 0.016666667 | P61: =(IF(K61<=TODAY(),1,0))*I61 -> 0.055555556
B62: 1.2.8 | C62: 271478 | D62: =IFERROR(VLOOKUP(C62,Tabla_APL[[STOCKCODE]:[TYPE]],3,FALSE),"") -> 11 | E62: 2 | F62: =D62-E62 -> 9 | G62: PALANCA MOVIMIENTO COMPUERTA FILTRO | H62: 1 | I62: =IF(H62=1,1/SUM(H$55:H$72),0) -> 0.055555556 | J62: 30 | K62: =$G$7-J62 -> 43991 | L62: 0.3 | M62: =I62*L62 -> 0.016666667 | P62: =(IF(K62<=TODAY(),1,0))*I62 -> 0.055555556
B63: 1.2.9 | C63: 395137 | D63: =IFERROR(VLOOKUP(C63,Tabla_APL[[STOCKCODE]:[TYPE]],3,FALSE),"") -> 9 | E63: 2 | F63: =D63-E63 -> 7 | G63: SHAFT PASADOR COMPUERTA ITEM 09 PLANO SA249981 | H63: 1 | I63: =IF(H63=1,1/SUM(H$55:H$72),0) -> 0.055555556 | J63: 30 | K63: =$G$7-J63 -> 43991 | L63: 0.3 | M63: =I63*L63 -> 0.016666667 | P63: =(IF(K63<=TODAY(),1,0))*I63 -> 0.055555556
B64: 1.2.10 | C64: 73684 | D64: =IFERROR(VLOOKUP(C64,Tabla_APL[[STOCKCODE]:[TYPE]],3,FALSE),"") -> 15 | E64: 2 | F64: =D64-E64 -> 13 | G64: CILINDRO HIDRAULICO COMPUERTAS FILTROS | H64: 1 | I64: =IF(H64=1,1/SUM(H$55:H$72),0) -> 0.055555556 | J64: 30 | K64: =$G$7-J64 -> 43991 | L64: 0.3 | M64: =I64*L64 -> 0.016666667 | P64: =(IF(K64<=TODAY(),1,0))*I64 -> 0.055555556
B65: 1.2.11 | C65: 271411 | D65: =IFERROR(VLOOKUP(C65,Tabla_APL[[STOCKCODE]:[TYPE]],3,FALSE),"") -> 7 | E65: 1 | F65: =D65-E65 -> 6 | G65: SOPORTE EJE INFERIOR CILINDRO HIDRAULICO | H65: 1 | I65: =IF(H65=1,1/SUM(H$55:H$72),0) -> 0.055555556 | J65: 30 | K65: =$G$7-J65 -> 43991 | L65: 0.3 | M65: =I65*L65 -> 0.016666667 | P65: =(IF(K65<=TODAY(),1,0))*I65 -> 0.055555556
B66: 1.2.12 | C66: 274597 | D66: =IFERROR(VLOOKUP(C66,Tabla_APL[[STOCKCODE]:[TYPE]],3,FALSE),"") -> 18 | E66: 2 | F66: =D66-E66 -> 16 | G66: SOPORTE RODAMIENTO | H66: 1 | I66: =IF(H66=1,1/SUM(H$55:H$72),0) -> 0.055555556 | J66: 30 | K66: =$G$7-J66 -> 43991 | L66: 0.3 | M66: =I66*L66 -> 0.016666667 | P66: =(IF(K66<=TODAY(),1,0))*I66 -> 0.055555556
B67: 1.2.13 | C67: 306035 | D67: =IFERROR(VLOOKUP(C67,Tabla_APL[[STOCKCODE]:[TYPE]],3,FALSE),"") -> 9 | E67: 4 | F67: =D67-E67 -> 5 | G67: ROTULA ACERO SKF PARA CILINDRO COMPUERTA | H67: 1 | I67: =IF(H67=1,1/SUM(H$55:H$72),0) -> 0.055555556 | J67: 30 | K67: =$G$7-J67 -> 43991 | L67: 0.3 | M67: =I67*L67 -> 0.016666667 | P67: =(IF(K67<=TODAY(),1,0))*I67 -> 0.055555556
... B72: 1.2.18 | C72: 140715 | D72: =IFERROR(VLOOKUP(C72,Tabla_APL[[STOCKCODE]:[TYPE]],3,FALSE),"") -> 16 | E72: 2 | F72: =D72-E72 -> 14 | G72: BURLETE; BURLETE SELLO LATERAL M2 | H72: 1 | I72: =IF(H72=1,1/SUM(H$55:H$72),0) -> 0.055555556 | J72: 30 | K72: =$G$7-J72 -> 43991 | L72: 0.3 | M72: =I72*L72 -> 0.016666667 | P72: =(IF(K72<=TODAY(),1,0))*I72 -> 0.055555556
B73: 1.3 | C73: CODIGO | D73: Stock Bodega | E73: Cant. Req. | F73: EXISTENCIA | G73: ALIMENTACION | H73: APLICA | I73: =SUM(I74:I87) -> 0.85714286 | J73: FREC | K73: DEAD LINE | L73: =AVERAGE(L74:L85) -> 0.225 | M73: =SUM(M74:M85) -> 0.25714286 | N73: OBSERVACIONES | O73: RQ: | P73: =SUM(P74:P86) -> 0.85714286
B74: 1.3.1 | C74: 325316 | D74: =IFERROR(VLOOKUP(C74,Tabla_APL[[STOCKCODE]:[TYPE]],3,FALSE),"") -> 1 | E74: 1 | F74: =D74-E74 -> 0 | G74: FORRO DEGASTE ALIMENTACION FILTRO 6" | H74: 1 | I74: =IF(H74=1,1/SUM(H$74:H$87),0) -> 0.14285714 | J74: 30 | K74: =$G$7-J74 -> 43991 | L74: 0.3 | M74: =I74*L74 -> 0.042857143 | P74: =(IF(K74<=TODAY(),1,0))*I74 -> 0.14285714
B75: 1.3.2 | C75: 176123 | D75: =IFERROR(VLOOKUP(C75,Tabla_APL[[STOCKCODE]:[TYPE]],3,FALSE),"") -> 14 | E75: 3 | F75: =D75-E75 -> 11 | G75: JUNTA EXPANSION ERFLEX 6" (ANCHA) | H75: 1 | I75: =IF(H75=1,1/SUM(H$74:H$87),0) -> 0.14285714 | J75: 30 | K75: =$G$7-J75 -> 43991 | L75: 0.3 | M75: =I75*L75 -> 0.042857143 | P75: =(IF(K75<=TODAY(),1,0))*I75 -> 0.14285714
B76: 1.3.3 | C76: 746217 | D76: =IFERROR(VLOOKUP(C76,Tabla_APL[[STOCKCODE]:[TYPE]],3,FALSE),"") -> 23 | E76: 4 | F76: =D76-E76 -> 19 | G76: CAÑERIA CON BRIDAS (CARRETILLA) | H76: 1 | I76: =IF(H76=1,1/SUM(H$74:H$87),0) -> 0.14285714 | J76: 30 | K76: =$G$7-J76 -> 43991 | L76: 0.3 | M76: =I76*L76 -> 0.042857143 | P76: =(IF(K76<=TODAY(),1,0))*I76 -> 0.14285714
B77: 1.3.4 | C77: 746197 | D77: =IFERROR(VLOOKUP(C77,Tabla_APL[[STOCKCODE]:[TYPE]],3,FALSE),"") -> 0 | E77: 1 | F77: =D77-E77 -> -1 | G77: VALVULA CERAMICA ALIMENTACION FILTROS (V1 - V4) | H77: 1 | I77: =IF(H77=1,1/SUM(H$74:H$87),0) -> 0.14285714 | J77: 30 | K77: =$G$7-J77 -> 43991 | L77: 0.3 | M77: =I77*L77 -> 0.042857143 | P77: =(IF(K77<=TODAY(),1,0))*I77 -> 0.14285714
B78: 1.3.5 | C78: 746510 | D78: =IFERROR(VLOOKUP(C78,Tabla_APL[[STOCKCODE]:[TYPE]],3,FALSE),"") | F78: =D78-E78 -> #VALUE! | G78: VALVULA CERAMICA ALIMENTACION FILTROS (V1 - V4) reparada
B79: 1.3.6 | C79: 746199 | D79: =IFERROR(VLOOKUP(C79,Tabla_APL[[STOCKCODE]:[TYPE]],3,FALSE),"") | F79: =D79-E79 -> #VALUE! | G79: CUERPO VÁLVULA BOLA 6"
B80: 1.3.7 | C80: 527432 | D80: =IFERROR(VLOOKUP(C80,Tabla_APL[[STOCKCODE]:[TYPE]],3,FALSE),"") | F80: =D80-E80 -> #VALUE! | G80: VALVULA PINCH DE 6" REPARADA
B81: 1.3.8 | C81: 88864 | D81: =IFERROR(VLOOKUP(C81,Tabla_APL[[STOCKCODE]:[TYPE]],3,FALSE),"") -> 18 | E81: 2 | F81: =D81-E81 -> 16 | G81: VALVULA PINCH DE 6" NUEVA | H81: 1
B82: 1.3.9 | C82: 337113 | D82: =IFERROR(VLOOKUP(C82,Tabla_APL[[STOCKCODE]:[TYPE]],3,FALSE),"") -> 6 | E82: 1 | F82: =D82-E82 -> 5 | G82: VALVULA CUCHILLO KGD10" (NUEVA) | H82: 1 | I82: =IF(H82=1,1/SUM(H$74:H$87),0) -> 0.14285714 | J82: 30 | K82: =$G$7-J82 -> 43991 | L82: 0.3 | M82: =I82*L82 -> 0.042857143 | P82: =(IF(K82<=TODAY(),1,0))*I82 -> 0.14285714
B83: 1.3.10 | C83: 439661 | D83: =IFERROR(VLOOKUP(C83,Tabla_APL[[STOCKCODE]:[TYPE]],3,FALSE),"") -> 0 | E83: 1 | F83: =D83-E83 -> -1 | G83: VALVULA CUCHILLO 10" (REPARADA) | H83: 0 | I83: =IF(H83=1,1/SUM(H$74:H$87),0) -> 0 | J83: 30 | K83: =$G$7-J83 -> 43991 | L83: 0 | M83: =I83*L83 -> 0 | N83: NO SE UTILIZA | P83: =(IF(K83<=TODAY(),1,0))*I83 -> 0
B84: 1.3.11 | C84: 339911 | D84: =IFERROR(VLOOKUP(C84,Tabla_APL[[STOCKCODE]:[TYPE]],3,FALSE),"") -> 7 | E84: 2 | F84: =D84-E84 -> 5 | G84: MANGA GOMA NATURA Kgd10 (ELASTOMERO) | H84: 0 | I84: =IF(H84=1,1/SUM(H$74:H$87),0) -> 0 | J84: 30 | K84: =$G$7-J84 -> 43991 | L84: 0 | M84: =I84*L84 -> 0 | N84: NO SE UTILIZA | P84: =(IF(K84<=TODAY(),1,0))*I84 -> 0
B85: 1.3.12 | C85: 746226 | D85: =IFERROR(VLOOKUP(C85,Tabla_APL[[STOCKCODE]:[TYPE]],3,FALSE),"") -> 6 | E85: 1 | F85: =D85-E85 -> 5 | G85: DUCTO ALIMENTACION FL1-2-3. | H85: 1 | I85: =IF(H85=1,1/SUM(H$74:H$87),0) -> 0.14285714 | J85: 30 | K85: =$G$7-J85 -> 43991 | L85: 0.3 | M85: =I85*L85 -> 0.042857143 | P85: =(IF(K85<=TODAY(),1,0))*I85 -> 0.14285714
B86: 1.3.13 | C86: 474973 | D86: =IFERROR(VLOOKUP(C86,Tabla_APL[[STOCKCODE]:[TYPE]],3,FALSE),"") -> 3 | E86: 1 | F86: =D86-E86 -> 2 | G86: DUCTO ALIMENTACION FL004 | H86: 0 | I86: =IF(H86=1,1/SUM(H$74:H$87),0) -> 0 | J86: 30 | K86: =$G$7-J86 -> 43991 | L86: 0 | M86: =I86*L86 -> 0 | P86: =(IF(K86<=TODAY(),1,0))*I86 -> 0
B87: 1.3.14 | C87: 474981 | D87: =IFERROR(VLOOKUP(C87,Tabla_APL[[STOCKCODE]:[TYPE]],3,FALSE),"") -> 4 | E87: 1 | F87: =D87-E87 -> 3 | G87: DUCTO ALIMENTACION Fl005 | H87: 0 | I87: =IF(H87=1,1/SUM(H$74:H$87),0) -> 0 | J87: 30 | K87: =$G$7-J87 -> 43991 | L87: 0 | M87: =I87*L87 -> 0 | P87: =(IF(K87<=TODAY(),1,0))*I87 -> 0
B88: 1.4 | C88: CODIGO | D88: Stock Bodega | E88: Cant. Req. | F88: EXISTENCIA | G88: SALIDA AGUA FILTRADA 4" | H88: APLICA | I88: =SUM(I89:I92) -> 1 | J88: FREC | K88: DEAD LINE | L88: =AVERAGE(L89:L92) -> 0.3 | M88: =SUM(M89:M92) -> 0.3 | N88: OBSERVACIONES | O88: RQ: | P88: =SUM(P89:P92) -> 1
B89: 1.4.1 | C89: 746228 | D89: =IFERROR(VLOOKUP(C89,Tabla_APL[[STOCKCODE]:[TYPE]],3,FALSE),"") -> 5 | E89: 1 | F89: =D89-E89 -> 4 | G89: CAÑERIA DE SALIDA DE FILTRADO | H89: 1 | I89: =IF(H89=1,1/SUM(H$89:H$92),0) -> 0.25 | J89: 30 | K89: =$G$7-J89 -> 43991 | L89: 0.3 | M89: =I89*L89 -> 0.075 | P89: =(IF(K89<=TODAY(),1,0))*I89 -> 0.25
B90: 1.4.2 | C90: 746227 | D90: =IFERROR(VLOOKUP(C90,Tabla_APL[[STOCKCODE]:[TYPE]],3,FALSE),"") -> 5 | E90: 1 | F90: =D90-E90 -> 4 | G90: CAÑERIA DE SALIDA DE FILTRADO | H90: 1 | I90: =IF(H90=1,1/SUM(H$89:H$92),0) -> 0.25 | J90: 30 | K90: =$G$7-J90 -> 43991 | L90: 0.3 | M90: =I90*L90 -> 0.075 | P90: =(IF(K90<=TODAY(),1,0))*I90 -> 0.25
B91: 1.4.3 | C91: 746229 | D91: =IFERROR(VLOOKUP(C91,Tabla_APL[[STOCKCODE]:[TYPE]],3,FALSE),"") -> 5 | E91: 1 | F91: =D91-E91 -> 4 | G91: CAÑERIA DE SALIDA DE FILTRADO | H91: 1 | I91: =IF(H91=1,1/SUM(H$89:H$92),0) -> 0.25 | J91: 30 | K91: =$G$7-J91 -> 43991 | L91: 0.3 | M91: =I91*L91 -> 0.075 | P91: =(IF(K91<=TODAY(),1,0))*I91 -> 0.25
B92: 1.4.4 | C92: 746230 | D92: =IFERROR(VLOOKUP(C92,Tabla_APL[[STOCKCODE]:[TYPE]],3,FALSE),"") -> 5 | E92: 1 | F92: =D92-E92 -> 4 | G92: CAÑERIA DE SALIDA DE FILTRADO | H92: 1 | I92: =IF(H92=1,1/SUM(H$89:H$92),0) -> 0.25 | J92: 30 | K92: =$G$7-J92 -> 43991 | L92: 0.3 | M92: =I92*L92 -> 0.075 | P92: =(IF(K92<=TODAY(),1,0))*I92 -> 0.25
B93: 1.5 | C93: CODIGO | D93: Stock Bodega | E93: Cant. Req. | F93: EXISTENCIA | G93: SALIDA AGUA FILTRADA 6" | H93: APLICA | I93: =SUM(I94:I101) -> 1 | J93: FREC | K93: DEAD LINE | L93: =AVERAGE(L94:L101) -> 0.3 | M93: =SUM(M94:M101) -> 0.3 | N93: OBSERVACIONES | O93: RQ: | P93: =SUM(P94:P101) -> 1
B94: 1.5.1 | C94: 746240 | D94: =IFERROR(VLOOKUP(C94,Tabla_APL[[STOCKCODE]:[TYPE]],3,FALSE),"") -> 7 | E94: 1 | F94: =D94-E94 -> 6 | G94: CAÑERIA DE SALIDA DE FILTRADO | H94: 1 | I94: =IF(H94=1,1/SUM(H$94:H$101),0) -> 0.125 | J94: 30 | K94: =$G$7-J94 -> 43991 | L94: 0.3 | M94: =I94*L94 -> 0.0375 | P94: =(IF(K94<=TODAY(),1,0))*I94 -> 0.125
B95: 1.5.2 | C95: 746241 | D95: =IFERROR(VLOOKUP(C95,Tabla_APL[[STOCKCODE]:[TYPE]],3,FALSE),"") -> 3 | E95: 1 | F95: =D95-E95 -> 2 | G95: CAÑERIA DE SALIDA DE FILTRADO | H95: 1 | I95: =IF(H95=1,1/SUM(H$94:H$101),0) -> 0.125 | J95: 30 | K95: =$G$7-J95 -> 43991 | L95: 0.3 | M95: =I95*L95 -> 0.0375 | P95: =(IF(K95<=TODAY(),1,0))*I95 -> 0.125
B96: 1.5.3 | C96: 746242 | D96: =IFERROR(VLOOKUP(C96,Tabla_APL[[STOCKCODE]:[TYPE]],3,FALSE),"") -> 4 | E96: 1 | F96: =D96-E96 -> 3 | G96: CAÑERIA DE SALIDA DE FILTRADO | H96: 1 | I96: =IF(H96=1,1/SUM(H$94:H$101),0) -> 0.125 | J96: 30 | K96: =$G$7-J96 -> 43991 | L96: 0.3 | M96: =I96*L96 -> 0.0375 | P96: =(IF(K96<=TODAY(),1,0))*I96 -> 0.125
B97: 1.5.4 | C97: 155671 | D97: =IFERROR(VLOOKUP(C97,Tabla_APL[[STOCKCODE]:[TYPE]],3,FALSE),"") -> 7 | E97: 1 | F97: =D97-E97 -> 6 | G97: MANGUERA GOMA 1450 mm | H97: 1 | I97: =IF(H97=1,1/SUM(H$94:H$101),0) -> 0.125 | J97: 30 | K97: =$G$7-J97 -> 43991 | L97: 0.3 | M97: =I97*L97 -> 0.0375 | P97: =(IF(K97<=TODAY(),1,0))*I97 -> 0.125
B98: 1.5.5 | C98: 155663 | D98: =IFERROR(VLOOKUP(C98,Tabla_APL[[STOCKCODE]:[TYPE]],3,FALSE),"") -> 12 | E98: 2 | F98: =D98-E98 -> 10 | G98: ACOPLAMIENTO MANGUERA TRELLEX 11190 (VULCOLEX 6") | H98: 1 | I98: =IF(H98=1,1/SUM(H$94:H$101),0) -> 0.125 | J98: 30 | K98: =$G$7-J98 -> 43991 | L98: 0.3 | M98: =I98*L98 -> 0.0375 | P98: =(IF(K98<=TODAY(),1,0))*I98 -> 0.125
B99: 1.5.6 | C99: 49973 | D99: =IFERROR(VLOOKUP(C99,Tabla_APL[[STOCKCODE]:[TYPE]],3,FALSE),"") -> 0 | E99: 2 | F99: =D99-E99 -> -2 | G99: CONO SELLO VULCOLEX (6") | H99: 1 | I99: =IF(H99=1,1/SUM(H$94:H$101),0) -> 0.125 | J99: 30 | K99: =$G$7-J99 -> 43991 | L99: 0.3 | M99: =I99*L99 -> 0.0375 | P99: =(IF(K99<=TODAY(),1,0))*I99 -> 0.125
B100: 1.5.7 | C100: 88799 | D100: =IFERROR(VLOOKUP(C100,Tabla_APL[[STOCKCODE]:[TYPE]],3,FALSE),"") -> 24 | E100: 2 | F100: =D100-E100 -> 22 | G100: JUNTA EXPANSION DN 150 (DELGADA) | H100: 1 | I100: =IF(H100=1,1/SUM(H$94:H$101),0) -> 0.125 | J100: 30 | K100: =$G$7-J100 -> 43991 | L100: 0.3 | M100: =I100*L100 -> 0.0375 | P100: =(IF(K100<=TODAY(),1,0))*I100 -> 0.125
B101: 1.5.8 | C101: 155655 | D101: =IFERROR(VLOOKUP(C101,Tabla_APL[[STOCKCODE]:[TYPE]],3,FALSE),"") -> 17 | E101: 1 | F101: =D101-E101 -> 16 | G101: VÁLVULA DN150/PN16 RS-150/090-100 (6") CON ACTUADOR | H101: 1 | I101: =IF(H101=1,1/SUM(H$94:H$101),0) -> 0.125 | J101: 30 | K101: =$G$7-J101 -> 43991 | L101: 0.3 | M101: =I101*L101 -> 0.0375 | P101: =(IF(K101<=TODAY(),1,0))*I101 -> 0.125
B102: 1.6 | C102: CODIGO | D102: Stock Bodega | E102: Cant. Req. | F102: EXISTENCIA | G102: AIRE DE SECADO 6" | H102: APLICA | I102: =SUM(I103:I109) -> 1 | J102: FREC | K102: DEAD LINE | L102: =AVERAGE(L103:L109) -> 0.21428571 | M102: =SUM(M103:M109) -> 0.3 | N102: OBSERVACIONES | O102: RQ: | P102: =SUM(P103:P109) -> 1
B103: 1.6.1 | C103: 130732 | D103: =IFERROR(VLOOKUP(C103,Tabla_APL[[STOCKCODE]:[TYPE]],3,FALSE),"") | E103: 1 | F103: =D103-E103 -> #VALUE! | G103: VALVULA MARIPOSA MANUAL DN150 | H103: 0 | I103: =IF(H103=1,1/SUM(H$103:H$109),0) -> 0 | J103: 30 | K103: =$G$7-J103 -> 43991 | L103: 0 | M103: =I103*L103 -> 0 | N103: NO SE CAMBIA, PLANTA DETENIDA | P103: =(IF(K103<=TODAY(),1,0))*I103 -> 0
B104: 1.6.2 | C104: 746237 | D104: =IFERROR(VLOOKUP(C104,Tabla_APL[[STOCKCODE]:[TYPE]],3,FALSE),"") -> 4 | E104: 1 | F104: =D104-E104 -> 3 | G104: CAÑERIA CONICO | H104: 0 | I104: =IF(H104=1,1/SUM(H$103:H$109),0) -> 0 | J104: 30 | K104: =$G$7-J104 -> 43991 | L104: 0 | M104: =I104*L104 -> 0 | N104: NO SE OCUPA DEBE DETENER TODA LA PLANTA PARA CAMBIO | P104: =(IF(K104<=TODAY(),1,0))*I104 -> 0
B105: 1.6.3 | C105: 746236 | D105: =IFERROR(VLOOKUP(C105,Tabla_APL[[STOCKCODE]:[TYPE]],3,FALSE),"") -> 5 | E105: 1 | F105: =D105-E105 -> 4 | G105: CAÑERIA ENTRADA AIRE | H105: 1 | I105: =IF(H105=1,1/SUM(H$103:H$109),0) -> 0.2 | J105: 30 | K105: =$G$7-J105 -> 43991 | L105: 0.3 | M105: =I105*L105 -> 0.06 | P105: =(IF(K105<=TODAY(),1,0))*I105 -> 0.2
B106: 1.6.4 | C106: 155655 | D106: =IFERROR(VLOOKUP(C106,Tabla_APL[[STOCKCODE]:[TYPE]],3,FALSE),"") -> 17 | E106: 1 | F106: =D106-E106 -> 16 | G106: VÁLVULA DN150/PN16 RS-150/090-100 (6") CON ACTUADOR | H106: 1 | I106: =IF(H106=1,1/SUM(H$103:H$109),0) -> 0.2 | J106: 30 | K106: =$G$7-J106 -> 43991 | L106: 0.3 | M106: =I106*L106 -> 0.06 | P106: =(IF(K106<=TODAY(),1,0))*I106 -> 0.2
B107: 1.6.5 | C107: 746216 | D107: =IFERROR(VLOOKUP(C107,Tabla_APL[[STOCKCODE]:[TYPE]],3,FALSE),"") -> 6 | E107: 1 | F107: =D107-E107 -> 5 | G107: CAÑERIA DE ENTRADA DE AIRE | H107: 1 | I107: =IF(H107=1,1/SUM(H$103:H$109),0) -> 0.2 | J107: 30 | K107: =$G$7-J107 -> 43991 | L107: 0.3 | M107: =I107*L107 -> 0.06 | P107: =(IF(K107<=TODAY(),1,0))*I107 -> 0.2
B108: 1.6.6 | C108: 88799 | D108: =IFERROR(VLOOKUP(C108,Tabla_APL[[STOCKCODE]:[TYPE]],3,FALSE),"") -> 24 | E108: 2 | F108: =D108-E108 -> 22 | G108: JUNTA EXPANSION DN 150 (DELGADA) | H108: 1 | I108: =IF(H108=1,1/SUM(H$103:H$109),0) -> 0.2 | J108: 30 | K108: =$G$7-J108 -> 43991 | L108: 0.3 | M108: =I108*L108 -> 0.06 | P108: =(IF(K108<=TODAY(),1,0))*I108 -> 0.2
...

Sheet MATRIZ REPUESTOS ELEC. INSTRU.
G1: MATRIZ DE REPUESTOS Y INSUMES HIDRAULICOS Y ELECTRICOS
F4: FAENA : | G4: PUERTO CMDIC GMT1401A
F5: EQUIPO APL : | G5: FILTROS PUERTO
B7: INICIO DEL MANTENIMIENTO | G7: 44819 | N7: Real | O7: Esperado a la fecha
B8: Area: | G8: Filtrado y Embarque | L8: =G17 -> REPUESTOS ELECTRICOS | N8: =M17*0.5 -> 0.24 | O8: =P17*0.5 -> 0.5 | P8: n
B9: Revisado por: | F9: Armando Pizarro/ Pedro Perez | L9: =G40 -> REPUESTOS ELECTRICOS FEEDER FILTROS | N9: =M40*0.5 -> 0 | O9: =P17*0.5 -> 0.5 | P9: n
B10: Jefe de Área | F10: Juan Marisio
B11: Equipo | F11: 310FL003 | G11: ='[3]MATRIZ REPUESTOS MECANICOS'!G11 -> MANTENCION SEMESTRAL FILTRO PRENSA
B12: Fecha de Hoy | F12: =TODAY() -> 46163 | G12: =TODAY() -> 46163
B13: SD | F13: =[4]!HAZOP[Codigo] -> #REF!
L14: Cumplimiento del Area | N14: =SUM(N8:N12) -> 0.24 | O14: =SUM(O8:O12) -> 1 | P14: n
B16: ID | C16: CODIGO | D16: Stock Bodega | E16: Cant. Req. | F16: SALDO STOCK | G16: REPUESTOS | H16: APLICA | I16: Pond | J16: Frec | K16: DeadLine | L16: Avance | M16: Avance Ponderado | N16: Observaciones | O16: Evidencia | P16: Esperado
B17: 1.1 | C17: CODIGO | D17: Stock Bodega | E17: Cant. Req. | F17: EXISTENCIA | G17: REPUESTOS ELECTRICOS | H17: APLICA | I17: =SUM(I18:I39) -> 1 | J17: FREC | K17: DEAD LINE | L17: =AVERAGE(L18:L39) -> 0.10909091 | M17: =SUM(M18:M39) -> 0.48 | N17: OBSERVACIONES | O17: RQ: | P17: =SUM(P18:P39) -> 1
B18: 1.1.1 | C18: 401315 | D18: =IFERROR(VLOOKUP(C18,Tabla_APL[[STOCKCODE]:[TYPE]],3,FALSE),"") -> 7 | E18: 4 | F18: =D18-E18 -> 3 | G18: PULLCORD | H18: 0 | I18: =IF(H18=1,1/SUM(H$18:H$39),0) -> 0 | J18: 40 | K18: =$G$7-J18 -> 44779 | L18: 0 | M18: =I18*L18 -> 0 | P18: =(IF(K18<=TODAY(),1,0))*I18 -> 0
B19: 1.1.2 | C19: 743701 | D19: =IFERROR(VLOOKUP(C19,Tabla_APL[[STOCKCODE]:[TYPE]],3,FALSE),"") -> 10 | E19: 10 | F19: =D19-E19 -> 0 | G19: ELECTROVALVULA SIMPLE EFECTO (TABLERO NEUMATICO PLANTA FILTRADO) | H19: 0 | I19: =IF(H19=1,1/SUM(H$18:H$39),0) -> 0 | J19: 40 | K19: =$G$7-J19 -> 44779 | L19: 0 | M19: =I19*L19 -> 0 | P19: =(IF(K19<=TODAY(),1,0))*I19 -> 0
B20: 1.1.3 | C20: 358283 | D20: =IFERROR(VLOOKUP(C20,Tabla_APL[[STOCKCODE]:[TYPE]],3,FALSE),"") -> 8 | E20: 4 | F20: =D20-E20 -> 4 | G20: CELDA DE CARGA | H20: 0 | I20: =IF(H20=1,1/SUM(H$18:H$39),0) -> 0 | J20: 40 | K20: =$G$7-J20 -> 44779 | L20: 0 | M20: =I20*L20 -> 0 | P20: =(IF(K20<=TODAY(),1,0))*I20 -> 0
B21: 1.1.4 | C21: 127704 | D21: =IFERROR(VLOOKUP(C21,Tabla_APL[[STOCKCODE]:[TYPE]],3,FALSE),"") -> 41 | E21: 9 | F21: =D21-E21 -> 32 | G21: RELE CONTROL SALIDA 24 VDC | H21: 0 | I21: =IF(H21=1,1/SUM(H$18:H$39),0) -> 0 | J21: 40 | K21: =$G$7-J21 -> 44779 | L21: 0 | M21: =I21*L21 -> 0 | P21: =(IF(K21<=TODAY(),1,0))*I21 -> 0
B22: 1.1.5 | C22: 453944 | D22: =IFERROR(VLOOKUP(C22,Tabla_APL[[STOCKCODE]:[TYPE]],3,FALSE),"") -> 2 | E22: 1 | F22: =D22-E22 -> 1 | G22: UNIDAD FILTRO REGULADOR LUBRICADOR C/ MANOMETRO 3/8" | H22: 0 | I22: =IF(H22=1,1/SUM(H$18:H$39),0) -> 0 | J22: 40 | K22: =$G$7-J22 -> 44779 | L22: 0 | M22: =I22*L22 -> 0 | P22: =(IF(K22<=TODAY(),1,0))*I22 -> 0
B23: 1.1.6 | C23: 453951 | D23: =IFERROR(VLOOKUP(C23,Tabla_APL[[STOCKCODE]:[TYPE]],3,FALSE),"") -> 9 | E23: 1 | F23: =D23-E23 -> 8 | G23: UNIDAD FILTRO REGULADOR LUBRICADOR C/ MANOMETRO 1/2" | H23: 0 | I23: =IF(H23=1,1/SUM(H$18:H$39),0) -> 0 | J23: 40 | K23: =$G$7-J23 -> 44779 | L23: 0 | M23: =I23*L23 -> 0 | P23: =(IF(K23<=TODAY(),1,0))*I23 -> 0
B24: 1.1.7 | C24: 449686 | D24: =IFERROR(VLOOKUP(C24,Tabla_APL[[STOCKCODE]:[TYPE]],3,FALSE),"") -> 0 | E24: 4 | F24: =D24-E24 -> -4 | G24: VALVULA DE CORTE 1/2" | H24: 0 | I24: =IF(H24=1,1/SUM(H$18:H$39),0) -> 0 | J24: 40 | K24: =$G$7-J24 -> 44779 | L24: 0 | M24: =I24*L24 -> 0 | P24: =(IF(K24<=TODAY(),1,0))*I24 -> 0
B25: 1.1.8 | C25: 741009 | D25: =IFERROR(VLOOKUP(C25,Tabla_APL[[STOCKCODE]:[TYPE]],3,FALSE),"") -> 1 | E25: 4 | F25: =D25-E25 -> -3 | G25: CONTACTOR LC1-D50F7 BOBINA 110VAC 22KW | H25: 1 | I25: =IF(H25=1,1/SUM(H$18:H$39),0) -> 0.2 | J25: 40 | K25: =$G$7-J25 -> 44779 | L25: 0.8 | M25: =I25*L25 -> 0.16 | P25: =(IF(K25<=TODAY(),1,0))*I25 -> 0.2
B26: 1.1.9 | C26: 426965 | D26: =IFERROR(VLOOKUP(C26,Tabla_APL[[STOCKCODE]:[TYPE]],3,FALSE),"") -> 38 | E26: 4 | F26: =D26-E26 -> 34 | G26: SENSOR DESALINEAMIENTO FILTRO | H26: 0 | I26: =IF(H26=1,1/SUM(H$18:H$39),0) -> 0 | J26: 40 | K26: =$G$7-J26 -> 44779 | L26: 0 | M26: =I26*L26 -> 0 | P26: =(IF(K26<=TODAY(),1,0))*I26 -> 0
B27: 1.1.10 | C27: 409243 | D27: =IFERROR(VLOOKUP(C27,Tabla_APL[[STOCKCODE]:[TYPE]],3,FALSE),"") -> 6 | E27: =[5]Repuestos!F18 -> 3 | F27: =D27-E27 -> 3 | G27: SWITCH DE PRESION UNIDAD HIDRAULICA (Filtro 4 y 5) | H27: 0 | I27: =IF(H27=1,1/SUM(H$18:H$39),0) -> 0 | J27: 40 | K27: =$G$7-J27 -> 44779 | L27: 0 | M27: =I27*L27 -> 0 | P27: =(IF(K27<=TODAY(),1,0))*I27 -> 0
B28: 1.1.11 | C28: 504423 | D28: =IFERROR(VLOOKUP(C28,Tabla_APL[[STOCKCODE]:[TYPE]],3,FALSE),"") -> 152 | E28: =[5]Repuestos!F19 -> 4 | F28: =D28-E28 -> 148 | G28: CONECTOR ;CONECTOR RECTO 3/8 X 1/4" NPT | H28: 0 | I28: =IF(H28=1,1/SUM(H$18:H$39),0) -> 0 | J28: 40 | K28: =$G$7-J28 -> 44779 | L28: 0 | M28: =I28*L28 -> 0 | P28: =(IF(K28<=TODAY(),1,0))*I28 -> 0
B29: 1.1.12 | C29: 127639 | D29: =IFERROR(VLOOKUP(C29,Tabla_APL[[STOCKCODE]:[TYPE]],3,FALSE),"") -> 4 | E29: =[5]Repuestos!F20 -> 1 | F29: =D29-E29 -> 3 | G29: SAFETY SWITCH MOTOVIBRADOR | H29: 0 | I29: =IF(H29=1,1/SUM(H$18:H$39),0) -> 0 | J29: 40 | K29: =$G$7-J29 -> 44779 | L29: 0 | M29: =I29*L29 -> 0 | P29: =(IF(K29<=TODAY(),1,0))*I29 -> 0
B30: 1.1.13 | C30: 407569 | D30: =IFERROR(VLOOKUP(C30,Tabla_APL[[STOCKCODE]:[TYPE]],3,FALSE),"") -> 2 | E30: =[5]Repuestos!F21 -> 1 | F30: =D30-E30 -> 1 | G30: INTERRUPTOR DE SEGURIDAD BBA ALTA | H30: 1 | I30: =IF(H30=1,1/SUM(H$18:H$39),0) -> 0.2 | J30: 40 | K30: =$G$7-J30 -> 44779 | L30: 0.8 | M30: =I30*L30 -> 0.16 | P30: =(IF(K30<=TODAY(),1,0))*I30 -> 0.2
B31: 1.1.14 | C31: 159368 | D31: =IFERROR(VLOOKUP(C31,Tabla_APL[[STOCKCODE]:[TYPE]],3,FALSE),"") -> 4 | E31: =[5]Repuestos!F22 -> 4 | F31: =D31-E31 -> 0 | G31: CONTACTOR MOTOVIBRADOR | H31: 1 | I31: =IF(H31=1,1/SUM(H$18:H$39),0) -> 0.2 | J31: 40 | K31: =$G$7-J31 -> 44779 | L31: 0.8 | M31: =I31*L31 -> 0.16 | P31: =(IF(K31<=TODAY(),1,0))*I31 -> 0.2
B32: 1.1.15 | C32: 6833 | D32: =IFERROR(VLOOKUP(C32,Tabla_APL[[STOCKCODE]:[TYPE]],3,FALSE),"") -> 16 | E32: =[5]Repuestos!F23 -> 1 | F32: =D32-E32 -> 15 | G32: MANOMETRO 2" DIAL 0-160 PSI 1 | H32: 0 | I32: =IF(H32=1,1/SUM(H$18:H$39),0) -> 0 | J32: 40 | K32: =$G$7-J32 -> 44779 | L32: 0 | M32: =I32*L32 -> 0 | P32: =(IF(K32<=TODAY(),1,0))*I32 -> 0
B33: 1.1.16 | C33: 177899 | D33: =IFERROR(VLOOKUP(C33,Tabla_APL[[STOCKCODE]:[TYPE]],3,FALSE),"") -> 2563 | E33: =[5]Repuestos!F24 -> 1 | F33: =D33-E33 -> 2562 | G33: PIOLA DE PULL CORD | H33: 1 | I33: =IF(H33=1,1/SUM(H$18:H$39),0) -> 0.2 | J33: 40 | K33: =$G$7-J33 -> 44779 | L33: 0 | M33: =I33*L33 -> 0 | P33: =(IF(K33<=TODAY(),1,0))*I33 -> 0.2
B34: 1.1.17 | C34: 145839 | D34: =IFERROR(VLOOKUP(C34,Tabla_APL[[STOCKCODE]:[TYPE]],3,FALSE),"") -> 4 | E34: =[5]Repuestos!F25 -> 4 | F34: =D34-E34 -> 0 | G34: JUEGO CONTACTO CONTACTOR SIZE 4 | H34: 1 | I34: =IF(H34=1,1/SUM(H$18:H$39),0) -> 0.2 | J34: 40 | K34: =$G$7-J34 -> 44779 | L34: 0 | M34: =I34*L34 -> 0 | P34: =(IF(K34<=TODAY(),1,0))*I34 -> 0.2
B35: 1.1.18 | C35: 127605 | D35: =IFERROR(VLOOKUP(C35,Tabla_APL[[STOCKCODE]:[TYPE]],3,FALSE),"") -> 5 | E35: =[5]Repuestos!F26 -> 4 | F35: =D35-E35 -> 1 | G35: GUARDA MOTOR 0.63-1 AMP | H35: 0 | I35: =IF(H35=1,1/SUM(H$18:H$39),0) -> 0 | J35: 40 | K35: =$G$7-J35 -> 44779 | L35: 0 | M35: =I35*L35 -> 0 | P35: =(IF(K35<=TODAY(),1,0))*I35 -> 0
B36: 1.1.19 | C36: 402685 | D36: =IFERROR(VLOOKUP(C36,Tabla_APL[[STOCKCODE]:[TYPE]],3,FALSE),"") -> 2 | E36: 1 | F36: =D36-E36 -> 1 | G36: INTERRUPTOR DE SEGURIDAD OTP90T3M BBA BAJA | H36: 0 | I36: =IF(H36=1,1/SUM(H$18:H$39),0) -> 0 | J36: 40 | K36: =$G$7-J36 -> 44779 | L36: 0 | M36: =I36*L36 -> 0 | P36: =(IF(K36<=TODAY(),1,0))*I36 -> 0
B37: 1.1.20 | C37: 744220 | D37: =IFERROR(VLOOKUP(C37,Tabla_APL[[STOCKCODE]:[TYPE]],3,FALSE),"") -> 0 | E37: 6 | F37: =D37-E37 -> -6 | G37: BASE PLACA SENSORES APERTURA / CIERRE | H37: 0 | I37: =IF(H37=1,1/SUM(H$18:H$39),0) -> 0 | J37: 40 | K37: =$G$7-J37 -> 44779 | L37: 0 | M37: =I37*L37 -> 0 | P37: =(IF(K37<=TODAY(),1,0))*I37 -> 0
B38: 1.1.21 | C38: 744863 | D38: =IFERROR(VLOOKUP(C38,Tabla_APL[[STOCKCODE]:[TYPE]],3,FALSE),"") -> 119 | E38: 4 | F38: =D38-E38 -> 115 | G38: BASE SOPORTE SENSOR COMPUERTA | H38: 0 | I38: =IF(H38=1,1/SUM(H$18:H$39),0) -> 0 | J38: 40 | K38: =$G$7-J38 -> 44779 | L38: 0 | M38: =I38*L38 -> 0 | P38: =(IF(K38<=TODAY(),1,0))*I38 -> 0
B39: 1.1.22 | C39: 361139 | D39: =IFERROR(VLOOKUP(C39,Tabla_APL[[STOCKCODE]:[TYPE]],3,FALSE),"") -> 0 | E39: 1 | F39: =D39-E39 -> -1 | G39: CAJA SUMADORA | H39: 0 | I39: =IF(H39=1,1/SUM(H$18:H$39),0) -> 0 | J39: 40 | K39: =$G$7-J39 -> 44779 | L39: 0 | M39: =I39*L39 -> 0 | P39: =(IF(K39<=TODAY(),1,0))*I39 -> 0
B40: 1.1 | C40: CODIGO | D40: Stock Bodega | E40: Cant. Req. | F40: EXISTENCIA | G40: REPUESTOS ELECTRICOS FEEDER FILTROS | H40: APLICA | I40: =SUM(I41:I62) -> 0 | J40: FREC | K40: DEAD LINE | L40: =AVERAGE(L41:L62) -> 13 | M40: =SUM(M41:M62) -> 0 | N40: OBSERVACIONES | O40: RQ: | P40: =SUM(P41:P62) -> 0
B41: 1.1.43 | C41: 144261 | D41: =IFERROR(VLOOKUP(C41,Tabla_APL[[STOCKCODE]:[TYPE]],3,FALSE),"") -> 84 | E41: 2 | F41: =D41-E41 -> 82 | G41: BASTON INTERRUPTOR DESALINEAMIENTO | H41: 5 | I41: =IF(H41=1,1/SUM(H$18:H$39),0) -> 0 | J41: 45 | K41: =$G$7-J41 -> 44774 | L41: 5 | M41: =I41*L41 -> 0 | P41: =(IF(K41<=TODAY(),1,0))*I41 -> 0
B42: 1.1.44 | C42: 127308 | D42: =IFERROR(VLOOKUP(C42,Tabla_APL[[STOCKCODE]:[TYPE]],3,FALSE),"") -> 0 | E42: 2 | F42: =D42-E42 -> -2 | G42: INTERRUPTOR DESALINEAMIENTO | H42: 6 | I42: =IF(H42=1,1/SUM(H$18:H$39),0) -> 0 | J42: 46 | K42: =$G$7-J42 -> 44773 | L42: 6 | M42: =I42*L42 -> 0 | P42: =(IF(K42<=TODAY(),1,0))*I42 -> 0
B43: 1.1.45 | C43: 368035 | D43: =IFERROR(VLOOKUP(C43,Tabla_APL[[STOCKCODE]:[TYPE]],3,FALSE),"") -> 0 | E43: 1 | F43: =D43-E43 -> -1 | G43: INTERRUPTOR VELOCIDAD CERO | H43: 7 | I43: =IF(H43=1,1/SUM(H$18:H$39),0) -> 0 | J43: 47 | K43: =$G$7-J43 -> 44772 | L43: 7 | M43: =I43*L43 -> 0 | P43: =(IF(K43<=TODAY(),1,0))*I43 -> 0
B44: 1.1.46 | C44: 80705 | D44: =IFERROR(VLOOKUP(C44,Tabla_APL[[STOCKCODE]:[TYPE]],3,FALSE),"") -> 3 | E44: 1 | F44: =D44-E44 -> 2 | G44: MOTOR ELECTRICO 7.5 HP 1480 RPM 380 V | H44: 8 | I44: =IF(H44=1,1/SUM(H$18:H$39),0) -> 0 | J44: 48 | K44: =$G$7-J44 -> 44771 | L44: 8 | M44: =I44*L44 -> 0 | P44: =(IF(K44<=TODAY(),1,0))*I44 -> 0
B45: 1.1.47 | C45: 177899 | D45: =IFERROR(VLOOKUP(C45,Tabla_APL[[STOCKCODE]:[TYPE]],3,FALSE),"") -> 2563 | E45: 100 | F45: =D45-E45 -> 2463 | G45: CABLE ACERO PLASTIFICADO 3/16" | H45: 9 | I45: =IF(H45=1,1/SUM(H$18:H$39),0) -> 0 | J45: 49 | K45: =$G$7-J45 -> 44770 | L45: 9 | M45: =I45*L45 -> 0 | P45: =(IF(K45<=TODAY(),1,0))*I45 -> 0
B46: 1.1.48 | C46: 742654 | D46: =IFERROR(VLOOKUP(C46,Tabla_APL[[STOCKCODE]:[TYPE]],3,FALSE),"") -> 25 | E46: 50 | F46: =D46-E46 -> -25 | G46: PRENSA TIPO CROSBY SS450 | H46: 10 | I46: =IF(H46=1,1/SUM(H$18:H$39),0) -> 0 | J46: 50 | K46: =$G$7-J46 -> 44769 | L46: 10 | M46: =I46*L46 -> 0 | P46: =(IF(K46<=TODAY(),1,0))*I46 -> 0
B47: 1.1.49 | C47: 68403 | D47: =IFERROR(VLOOKUP(C47,Tabla_APL[[STOCKCODE]:[TYPE]],3,FALSE),"") -> 1 | E47: 4 | F47: =D47-E47 -> -3 | G47: INTERRUPTOR CABLE 600 VAC 7,5 AMPS | H47: 11 | I47: =IF(H47=1,1/SUM(H$18:H$39),0) -> 0 | J47: 51 | K47: =$G$7-J47 -> 44768 | L47: 11 | M47: =I47*L47 -> 0 | P47: =(IF(K47<=TODAY(),1,0))*I47 -> 0
B48: 1.1.50 | C48: 127225 | D48: =IFERROR(VLOOKUP(C48,Tabla_APL[[STOCKCODE]:[TYPE]],3,FALSE),"") -> 3 | E48: 1 | F48: =D48-E48 -> 2 | G48: SENSOR ATOLLO 1,77V RMS 250 VP 44.2 M A | H48: 12 | I48: =IF(H48=1,1/SUM(H$18:H$39),0) -> 0 | J48: 52 | K48: =$G$7-J48 -> 44767 | L48: 12 | M48: =I48*L48 -> 0 | P48: =(IF(K48<=TODAY(),1,0))*I48 -> 0
B49: 1.1.51 | C49: 127209 | D49: =IFERROR(VLOOKUP(C49,Tabla_APL[[STOCKCODE]:[TYPE]],3,FALSE),"") -> 0 | E49: 1 | F49: =D49-E49 -> -1 | G49: SENSOR VELOCIDAD CERO 24 VDC 50 M A | H49: 13 | I49: =IF(H49=1,1/SUM(H$18:H$39),0) -> 0 | J49: 53 | K49: =$G$7-J49 -> 44766 | L49: 13 | M49: =I49*L49 -> 0 | P49: =(IF(K49<=TODAY(),1,0))*I49 -> 0
B50: 1.1.52 | C50: 402727 | D50: =IFERROR(VLOOKUP(C50,Tabla_APL[[STOCKCODE]:[TYPE]],3,FALSE),"") -> 0 | E50: 1 | F50: =D50-E50 -> -1 | G50: TRASMISOR NIVEL MULTIRANGE 100, 1 RELAY | H50: 14 | I50: =IF(H50=1,1/SUM(H$18:H$39),0) -> 0 | J50: 54 | K50: =$G$7-J50 -> 44765 | L50: 14 | M50: =I50*L50 -> 0 | P50: =(IF(K50<=TODAY(),1,0))*I50 -> 0
B51: 1.1.53 | C51: 127233 | D51: =IFERROR(VLOOKUP(C51,Tabla_APL[[STOCKCODE]:[TYPE]],3,FALSE),"") -> 0 | E51: 0 | F51: =D51-E51 -> 0 | G51: TRANSMISOR SENSOR ATOLLO BLOQUEADO PROCESO OBSOLETOS 2010 | H51: 15 | I51: =IF(H51=1,1/SUM(H$18:H$39),0) -> 0 | J51: 55 | K51: =$G$7-J51 -> 44764 | L51: 15 | M51: =I51*L51 -> 0 | P51: =(IF(K51<=TODAY(),1,0))*I51 -> 0
B52: 1.1.54 | C52: 551473 | D52: =IFERROR(VLOOKUP(C52,Tabla_APL[[STOCKCODE]:[TYPE]],3,FALSE),"") | E52: 1 | F52: =D52-E52 -> #VALUE! | G52: BALIZA ESTROBOSCOPICA ROJO 110V | H52: 16 | I52: =IF(H52=1,1/SUM(H$18:H$39),0) -> 0 | J52: 56 | K52: =$G$7-J52 -> 44763 | L52: 16 | M52: =I52*L52 -> 0 | P52: =(IF(K52<=TODAY(),1,0))*I52 -> 0
... B57: 1.1.59 | C57: 127308 | D57: =IFERROR(VLOOKUP(C57,Tabla_APL[[STOCKCODE]:[TYPE]],3,FALSE),"") -> 0 | E57: 2 | F57: =D57-E57 -> -2 | G57: BALIZA ALARMA | H57: 21 | I57: =IF(H57=1,1/SUM(H$18:H$39),0) -> 0 | J57: 61 | K57: =$G$7-J57 -> 44758 | L57: 21 | M57: =I57*L57 -> 0 | P57: =(IF(K57<=TODAY(),1,0))*I57 -> 0

Sheet FODA
D1: Fortaleza
D2: Oportunidad
D3: Debilidad
D4: Amenaza
A5: ITEM | B5: FILTRO | C5: FECHA | D5: CLASIFICACIÓN | E5: GENERADO POR | F5: DESCRIPCIÓN | G5: ESPECIALIDAD | H5: PLANES DE ACCIÓN | I5: PRIORIDAD | J5: RESPONSABLE | K5: AVANCE | L5: FECHA IMPLEMENTACIÓN | M5: OBSERVACIONES
A6: 1 | B6: Filtrado | C6: 42644 | D6: Oportunidad | E6: R. Contrera | F6: Falla en accionamiento de compuerta inferior ( no evaluada, fl002) | G6: Mecanico | H6: Considerar en Hazop "Revision de accionamiento de compuerta con anticipacion para poder evaluar y proyectar tiempos de reparacion y planificacion". | I6: Alta | J6: R. Contera | K6: 1 | L6: 42675 | M6: Programado semana 26-01 al 01-02 en mantencion semanal FL003
A7: 2 | B7: Filtro 5 | C7: 42644 | D7: Debilidad | E7: A.Tolosa | F7: Realizar buena inspección antes de emitir diagnostico (actividad ducto cabezal fijo) | G7: Mecanico | H7: Considerar en Hazop la Coordinación con personal de GSO CMDIC medición a de espesores en ducto aire y agua drenaje cabezal fijo. | I7: Alta | J7: P.Perez | K7: 1 | L7: 42675 | M7: Gestionado a traves de JC.Mella
A8: 3 | B8: Filtro 5 | C8: 42644 | D8: Amenaza | E8: A. Contreras | F8: Falla de Puente Grúa durante mantenimiento Semestral impacta el cumplimiento de carta gantt. | G8: Mecanico | H8: Considerar en Hazop la Coordinación de revisión previa de puente grúa principal y auxiliar, asegurando (Certificar color del mes). | I8: Alta | J8: P.Perez | K8: 1 | L8: 42675 | M8: Gestionado a traves de JC.Mella
A9: 4 | B9: Filtro 5 | C9: 42644 | D9: Debilidad | E9: R. Segovia. | F9: Repuestos no quedan en punto de trabajo. | G9: Mecanico | H9: Incorporar el Hazop Revisión y definición de layout de repuestos en plataformas y asegurar su cumplimiento. | I9: Alta | J9: R. Segovia | K9: 1 | L9: 42736
A10: 5 | B10: Filtro 5 | C10: 42644 | D10: Debilidad | E10: R. Segovia. | F10: Herramientas no quedan en punto. | G10: Mecanico | H10: Incorporar en el Hazop la ubicación exacta donde quedan las herramientas en el área de trabajo. | I10: Alta | J10: R. Segovia | K10: 1 | L10: 42736
A11: 6 | B11: Filtro 5 | C11: 42644 | D11: Oportunidad | E11: R. Segovia. | F11: Enviar a fabricar brazos pescante o pata de cabra para cambiar VV clarkson o elastometro y liberar puente grúa. | G11: Mecanico | H11: Incorporar en Hazop el armado de pata de cabra para cambio de válvulas clarkson. | I11: Media | J11: J. Area Mec | K11: 1 | L11: 42736 | M11: Se debe diseñar y enviar a fabricar.
A12: 7 | B12: Filtro 5 | C12: 42644 | D12: Amenaza | E12: A. Contreras | F12: Placas reparadas vienen separadas en filtrante y membrana. Se requiere que esten de pares | G12: Mecanico | I12: Alta | J12: R. Segovia | K12: 1 | L12: 42675 | M12: Programado semana 26-01 al 01-02
A13: 8 | B13: Filtro 5 | C13: 42644 | D13: Oportunidad | E13: R. Segovia. | F13: Dejar todo al alcance de puente grúa auxiliar para no depender de puente principal. | G13: Mecanico | H13: Incorporar en Hazop definición de layout de distribucion de repuestos en plataforma de filtros y su seguimiento al cumplimiento. | I13: cada vez | J13: R. Segovia | K13: 1 | L13: 42736
A14: 9 | B14: Filtro 5 | C14: 42644 | D14: Oportunidad | E14: R. Segovia. | F14: Perdida de tiempo y dependencia de puente grúa para subir repuestos desde primer piso a plataforma filtros. | G14: Mecanico | H14: Incorporar el Hazop Revisión y definición de layout de repuestos en plataformas y asegurar su cumplimiento. | I14: Alta | J14: R. Segovia | K14: 1 | L14: 42736 | M14: Programado semana 02-02
A15: 10 | B15: Filtro 5 | C15: 42644 | D15: Oportunidad | E15: R. Segovia. | F15: Disponer cajones para perneria. | G15: Mecanico | H15: Implementar cajones para pernería. | I15: Media | J15: R. Harvey | K15: 0 | M15: Los cajones para pernería deben quedar en las estanterías del área filtros.
A16: 11 | B16: Filtro 5 | C16: 42644 | D16: Oportunidad | E16: C. Roa | F16: Baja Disponibilidad de maquinas de soldar. | G16: Mecanico | I16: Alta | J16: R. Villablanca | K16: 0
A17: 12 | B17: Filtro 5 | C17: 42644 | D17: Oportunidad | E17: P. Tolosa | F17: Mejorar sistema de lubricación a rodamiento compuertas lado fijo (instalando líneas, con puntos cerca del pasillo) | G17: Mecanico | H17: Incorporar en Hazop la revisión de flexibles de lubricación centralizado de lubricación de rodamientos compuertas. | I17: Alta | J17: P.Perez | K17: 1 | M17: Se debe implementar previamente. Pendiente levantamiento para compra de materiales e implementacion
A18: 13 | B18: Filtro 1 | C18: 42686 | D18: Oportunidad | E18: R.Contreras | F18: Fabricación de placas target para sensores de apertura y cierre de prensa de filtros | G18: Mecanico | K18: 1 | M18: Programado semana 02-02
A19: 14 | B19: Filtro 1 | C19: 42686 | D19: Oportunidad | E19: R.Contreras | F19: Plastificar planos del filtro y mantenerlos en terreno para las M. Semestrales. | G19: Mecanico | H19: Incorporar en Hazop la preparación dentro de la carpeta de la intervención. | I19: Media | J19: R. Segovia | K19: 1 | L19: 42736
A20: 15 | B20: Filtro 1 | C20: 42686 | D20: Debilidad | E20: R. Segovia. | F20: Tardía activación del FODA y falta de incorporación de interesados hace perder oportunidades de mejora. | G20: Mecanico | H20: Definir responsable de activación y personal que debe incorporarse. | I20: Alta | J20: R. Segovia | K20: 1 | L20: 43070 | M20: Los programadores del turno en que cae la intervención son los responsables de activar del FODA e incorporación de los interesados.
A21: 16 | B21: Filtro 1 | C21: 42686 | D21: Debilidad | E21: R. Segovia. | F21: Soportes de sensores deben estar considerados dentro de los preparativos. | G21: E&I | H21: Incorporar en el APL de Repuestos los soportes de los sensores. | I21: Media | J21: R. Segovia | K21: 1 | L21: 42736 | M21: Solicitar catalogación
A22: 17 | B22: Filtro 1 | C22: 42686 | D22: Debilidad | E22: R. Segovia. | F22: Siempre debe considerarse personal periférico para atender contingencias | G22: Mecanico | K22: 1 | M22: SE DEJO PERSONAL EXTRA PARA EL MANTENIMIENTO
A23: 18 | B23: Filtro 1 | C23: 42686 | D23: Oportunidad | E23: R. Contreras | F23: Preparar previamente líneas de lubricación para rodamientos de compuerta | G23: Mecanico | K23: 0 | M23: REPUESTO TODAVIA NO LLEGA
A24: 19 | B24: Filtro 1 | C24: 42686 | D24: Oportunidad | E24: M. Poblete | F24: Preparar jaula para cilindros de gas y acetileno en terreno | G24: Mecanico | K24: 0 | M24: SE SOLICITA COMPRA , LA CUAL SIEMENS AUN NO COMPRA.
A25: 20 | B25: Filtro 1 | C25: 42686 | D25: Debilidad | E25: M.Poblere | F25: No se considera en los preparativos el empaque cónico para vulcolet COD. 49973 | G25: Mecanico | H25: Estaba incorporado pero no se preparó. Medidas administrativas. | I25: Alta | J25: R. Segovia | K25: 1
A26: 21 | B26: Filtro 1 | C26: 42686 | D26: Oportunidad | E26: R. Contreras | F26: Considerar dentro de los preparativos la fabricación de la soportación de la línea de aire membranas. | G26: Mecanico | H26: Incorporar en el APL de Repuestos los soportes de los sensores. | I26: Media | J26: R. Segovia | K26: 1 | L26: 42736 | M26: Programado semana 02-02
A27: 22 | B27: Filtro 1 | C27: 42686 | D27: Oportunidad | E27: R. Contreras | F27: Considerar dentro de los preparativos la fabricación de la soportación de la líneas de aire soplado. | G27: Mecanico | H27: Incorporar en el APL de Repuestos los soportes de los sensores. | I27: Media | J27: R. Segovia | K27: 1 | L27: 42736 | M27: Solicitar catalogación
A28: 23 | B28: Filtro 1 | C28: 42686 | D28: Oportunidad | E28: R. Segovia. | F28: Comprar spray fluorescente para marcar pernos torqueados tanto estructurales como de ductería | G28: Mecanico | H28: Incorporar en APL de Insumos | I28: Alta | J28: R. Segovia | K28: 1 | L28: 42736
A29: 24 | B29: Filtro 1 | C29: 42686 | D29: Debilidad | E29: R. Segovia. | F29: Existe utilización de pernería de distinto largo para misma utilización, utilizando paquetes de golillas. | G29: Mecanico | H29: Incorporar en APL de Repuestos una columna de identificación de uso de la pernería. Incorporar en Hazop la clasificación y separación pernos en cajas rotuladas por utilización. | I29: Alta | J29: R. Segovia | K29: 1 | L29: 42736
A30: 25 | B30: Filtro 1 | C30: 42686 | D30: Debilidad | E30: R. Segovia. | F30: Dentro de los preparativos se deben exigir golillas adecuadas para la solicitación. Las golillas instaladas son muy delgadas y se deforman. | G30: Mecanico | H30: Catalogar golillas para filtros y agregar código a APL de repustos. | I30: Media | J30: R. Segovia | K30: 1 | M30: Se encuentran en APL.
A31: 26 | B31: Filtro 2 | C31: 42738 | D31: Debilidad | E31: J. Vergara | F31: Todos los cilindros de gases se encuentran vacíos en terreno. | G31: Mecanico | H31: Considerado en APL de Insumos y se reporta en preparativos como 100%. Investigar y Generar medidas administrativas. | I31: Alta | J31: P.Perez/ R. Harvey. | K31: 1
A32: 27 | B32: Filtro 2 | C32: 42738 | D32: Debilidad | E32: R. Segovia. | F32: No se preparan empaquetaduras para cambio de ductos como preparativos | G32: Mecanico | H32: Considerar en APL de Repuestos. | I32: Media | J32: R. Segovia | K32: 1 | L32: 42736 | M32: Programado semana 02-02. Pendiente compra material sin stock
A33: 28 | B33: Filtro 2 | C33: 42738 | D33: Debilidad | E33: R. Segovia. | F33: Ductos no se suben a la plataforma de los filtros los repuestos de los ductos a cambio, creando dependencia de puente grúa. | G33: Mecanico | H33: Asegurar el entendimiento dentro de la organización respecto a que el cumplimiento de los preparativos debe ser la herramienta para definir si una intervención se realiza o no. | I33: Alta | J33: J. Area | K33: 1
A34: 29 | B34: Filtro 2 | C34: 42738 | D34: Oportunidad | E34: R. Segovia. | F34: Revisar como impacta el retiro de piezas usadas durante el mantenimiento a modo de validar o redefinir estrategia. | G34: Mecanico | H34: Incorporar en Hazopo preparar palett repisa para repuestos nuevos y usados, estos últimos a retirar post mantenimiento. | I34: Alta | J34: R. Segovia | K34: 1
A35: 30 | B35: Filtro 2 | C35: 42738 | D35: Amenaza | E35: R. Segovia. | F35: Falta de definición de personal que apoya en el mantenimiento genera desconcierto y entropía. | G35: Mecanico | K35: 1 | M35: se definio el personal y los grupo de trabajo de los supervisores
A36: 31 | B36: Filtro 2 | C36: 42738 | D36: Debilidad | E36: R. Segovia. | F36: Desplazamiento de mantenimiento no evalúa el impacto de cambio de turno sin personal de apoyo cordillera ni lixiviación. | G36: Mecanico | H36: Investigar y definir planes de acción | K36: 1 | M36: Confirmada fecha mantencion 04-02-17
A37: 32 | B37: Filtro 2 | C37: 42738 | D37: Debilidad | E37: A. Collao | F37: No contar con ducto pantalón, válvula larox, eje compuerta, placas, buje. Todo lo anterior comprados el dia 30… | G37: Mecanico | K37: 1 | M37: Asegurar compra minimo 15 días de anticipación.
A38: 33 | B38: Filtro 2 | C38: 42738 | D38: Amenaza | E38: A. Collao | F38: Al inicio de turno no se contaba con instalación de buje en soporte horquilla ¿soldar bujes en soportes? | G38: Mecanico | K38: 1 | M38: Programado en Preparativos Sem 5.
A39: 34 | B39: Filtro 2 | C39: 42738 | D39: Debilidad | E39: R. Segovia. | F39: Maniobras inadecuadas de izaje por falta de anclajes (orejas) | G39: Mecanico | H39: Incorporar en el Hazop el levantamiento de los requerimientos de puntos de anclaje y generar los WR para que se programe preparativo. | I39: Alta | J39: R. Segovia | K39: 1 | L39: 42736 | M39: Programado semana 26-01 al 01-02. Pendiente confirmacion repuesto 25-02 (se cuenta con repuesto)
A40: 35 | B40: Filtro 2 | C40: 42738 | D40: Debilidad | E40: R. Segovia. | F40: Maniobras de izaje sin protecciones de cantos vivos | G40: Mecanico | H40: Incorporar dentro del APL Insumos el tener preparadas protecciones para cantos vivos | I40: Alta | J40: R. Segovia | K40: 1 | L40: 42736 | M40: Programado semana 02-02
A41: 36 | B41: Filtro 2 | C41: 42738 | D41: Amenaza | E41: R. Segovia. | F41: Contingencias en los demás filtros se atienden con personal de la semestral. | G41: Mecanico
A42: 37 | B42: Filtro 2 | C42: 42738 | D42: Oportunidad | E42: E.loyola | F42: Fabricación de otro atril para colgar telas adicionales para contingencia de otros filtros. | G42: Mecanico | H42: Extender el atril existente. | I42: Alta | J42: R. Harvey | K42: 1 | L42: 42765 | M42: Programado semana 26-01 al 01-02.
A43: 38 | B43: Filtro 3 | C43: 42777 | D43: Fortaleza | E43: R. Segovia. | F43: Se adelnatan trabajos turno noche, hasta retiro total de placas. | G43: Mecánica | H43: Simepre que se pueda realizar estara esta fortaleza. | K43: 1
A44: 39 | B44: Filtro 3 | C44: 42777 | D44: Amenaza | E44: R. Segovia. | F44: Por rotura de ductos corto en FL002 se reciben lozas instransitables. Se define sacar gente para dar paso a limpieza. | G44: Mecánica | H44: Se comienza en planes semanales la normalización de ductos | I44: Alta | K44: 1
A45: 40 | B45: Filtro 3 | C45: 42777 | D45: Debilidad | E45: R. Segovia. | F45: Linea de lavado y soplado ductos 2" no considerados en Semestral y no se reparan. | G45: Mecánica | H45: Se comienza en planes semanales con ductos. | I45: Alta | K45: 1 | M45: Se encuentran en carta gantt futuras.
A46: 41 | B46: Filtro 3 | C46: 42777 | D46: Oportunidad | E46: R. Segovia. | F46: Centrador de flanges reduce tiempos. | G46: Mecánico | H46: Se encuentra en evalucion. | I46: Media | K46: 0
A47: 42 | B47: Filtro 3 | C47: 42777 | D47: Amenaza | E47: R. Segovia. | F47: Falta de ductos ya con parches pasan la cuenta en plena semestral FL003 | G47: Mecánico | H47: Se tiene ingresar a APL repuesto | K47: 0
A48: 43 | B48: Filtro 3 | C48: 42781 | D48: Debilidad | E48: A. Collao | F48: Consolidar cantidad de cuerpos de andamios a utilizar en filtro. Se tienen que realizar levantamiento de cuerpos de contrato Siemens. | G48: Mecánico | H48: Se tiene que definir en preparativos según actividades a tomar | K48: 1 | M48: Se realiza levantamiento para compra de nuevos andamios.
A49: 44 | B49: Filtro 3 | C49: 42781 | D49: Amenaza | E49: A. Collao | F49: Habilitación de enchufes 220v en 4 nivel de filtro. Tanto los existente como los que son necesario para mantenciones. | G49: Eléctrico | K49: 1 | M49: Se instalan nuevos enchufes, de igual manera no dana abasto para consumo en semestral, tener plan B (contar con generador)
A50: 45 | B50: Filtro 3 | C50: 42781 | D50: Debilidad | E50: R. Segovia. | F50: No estan todos los ductos de 2" como repuestos tanto lado cabezal movil como fijo. | G50: Mecánico | H50: Incluir en APL repuestos | K50: 1 | M50: Todos los ductos se encuentran en APL.
A51: 46 | B51: Filtro 3 | C51: 42781 | D51: Amenaza | E51: R. Segovia. | F51: Repuesto de V9 sin existencia en bodega. | G51: Bodega CMDIC | H51: Realizar aviso aportuno a J.C Mella | I51: Alta | K51: 1 | M51: Se realiza compra
A52: 47 | B52: Filtro 3 | C52: 42781 | D52: Debilidad | E52: R. Segovia. | F52: Sin WD40 durante intervención. | G52: Abasteciemiento | K52: 1 | M52: Se tiene que enviar LVAC a abastecimeinto 15 días anticipado para su respuesta con inusmo.
A53: 48 | B53: Filtro 3 | C53: 42781 | D53: Amenaza | E53: R. Segovia. | F53: Humedad de aire de instrumentación impacta en operación de válvulas. | G53: Instrumentación | K53: 0
A54: 49 | B54: Filtro 3 | C54: 42781 | D54: Amenaza | E54: R. Segovia. | F54: Plataforma ESED sin agua 2 días. | G54: Operaciones | K54: N/A | M54: PERSONAL DE APOYO EN CASA DE CAMBIO
A55: 50 | B55: Filtro 3 | C55: 42781 | D55: Amenaza | E55: R. Segovia. | F55: Operaciones sin hidrolavadora para lavado de placas. | G55: Operaciones | H55: Solicitar hidrolavadora en punto de trabajo (comprar nueva hidrolavadora) | K55: 1 | M55: Operaciones compra nueva hidrolavadora para lavado de placas.
A56: 51 | B56: Filtro 3 | C56: 42781 | D56: Fortaleza | E56: R. Segovia. | F56: Preparativos repuestos en niveles reduciendo tiempo | G56: Mecánico | K56: 1 | M56: Se realiza layauot para repuestos en diferentes pisos de planta.
A57: 52 | B57: Filtro 3 | C57: 42781 | D57: Fortaleza | E57: R. Segovia. | F57: Nueva estrategia de entrega de EPP reduce tiempos muertos | G57: Mecánico | K57: 1 | M57: Se preparan EPP para cada personal día antes de intervecnción.
A58: 53 | B58: Filtro 3 | C58: 42781 | D58: Oportunidad | E58: R. Segovia. | F58: Levantamiento de todas las soportaciones de ductos en filtro de prensa que sean necesarios | G58: Mecánico/instrumentacion | K58: 1 | M58: Se realiza planilla de seguimiento de ductos de planta.
A59: 54 | B59: Filtro 4 | C59: 42861 | D59: Amenaza | E59: M. Contreras | F59: No se realiza limpieza por parte de operaciones a filtro. | G59: Operaciones | K59: 1 | M59: En reunión de las 18:30 hrs de día anterior se tiene reforzar a operaciones limpieza de filtros.
A60: 55 | B60: Filtro 4 | C60: 42861 | D60: Amenaza | E60: A. Collao | F60: No se cuenta con empaquetaduras. | G60: Mecánico | H60: Se realiza solicitud de cambio de extatus dereposición usuario a repocicion automatica (J.Mella) | I60: Alta | J60: P. Perez | K60: 1 | L60: 42871
A61: 56 | B61: Filtro 4 | C61: 42861 | D61: Amenaza | E61: M. Espejo | F61: No se realiza bloqueo de acuerdo a lo difinido en reunion. | G61: Operaciones | I61: Media | J61: J. Operaciones CMDIC | K61: 0
A62: 57 | B62: Filtro 4 | C62: 42861 | D62: Debilidad | E62: A. Collao | F62: No llegan radios solicitadas. | G62: Abasteciemiento | H62: Seguimiento a compra de radios solicitadas. | I62: Alta | J62: R. Segovia | K62: 1 | L62: 42885 | M62: Llegan 5 radios nuevas, se cuentan con 8 radios grupo Mecánicos y 3 el grupo eléctricos.
A63: 58 | B63: Filtro 4 | C63: 42863 | D63: Oportunidad | E63: D. Ibañez | F63: Comprar herramienta adecuada para corte y fabricación de empaquetadura. | G63: Abasteciemiento | H63: Solicitar solcom de compra de herramientas | I63: Alta | J63: P. Perez | K63: 0
A64: 59 | B64: Filtro 4 | C64: 42863 | D64: Oportunidad | E64: D. Ibañez | F64: Incorporar dentro de carta gantt HH para armado de telas. | G64: Programación | H64: Incorporar HH a Carta Gantt semestral de filtro | K64: 1 | L64: 42872 | M64: Se dejan destinadas HH dentro de carta gantt de mantencion semestral de filtro para armado de telas.
A65: 60 | B65: Filtro 5 | C65: 42894 | D65: Oportunidad | E65: R. Ruiz | F65: Programar cambio de valvula de bloqueo de linea de aire en las mantenciones semestrales | G65: Planificación | H65: programar el cambio de valvulas, incluir en plan matriz | I65: Media | J65: Planificación CMDIC
A66: 61 | B66: Filtro 5 | C66: 42894 | D66: Oportunidad | E66: R. Vilca | F66: Fabricación de empaquetadura previa a la mantención | G66: Operaciones | H66: Incluir en Lvac en actividades previas | I66: Media | J66: Planificación Siemens | K66: 1 | M66: Esta dentro de preparativos en taller en LVAC a la tarea.
A67: 62 | B67: Filtro 3 | C67: 42984 | D67: Amenaza | E67: L. Vidal | F67: No se limpia losa de tercer nivel y personal de aseo no esta en el punto | G67: Operaciones | H67: Incluir en preparativos e enviar correo a Andres Gonzales asegurando limpieza. | I67: Alta | J67: Programación | K67: 100 | L67: 43005 | M67: el 27-09 se incoopora en preparativos
A68: 63 | B68: Filtro 3 | C68: 42984 | D68: Amenaza | E68: C. Roa | F68: Operaciones no entrega equipo en hora establecida para iniciar la mantención | G68: Operaciones
A69: 64 | B69: Filtro 3 | C69: 42984 | D69: Oportunidad | E69: C. Roa | F69: Fabricación de plataformas para dejar repuestos frente al FL005 | G69: Operaciones | H69: Realizar levantameinto y diseño de estanteria para repuestos. | I69: Media | J69: P. Elisondo/H. Galvez | K69: 0.1 | M69: 27-09 se envia correo a responsable.
A70: 65 | B70: Filtro 3 | C70: 42984 | D70: Oportunidad | E70: C. Marin | F70: Tener dispensadores de basura en el area | G70: Programación | H70: Incorporar en preparativos que se cuente con ellos en área de trabajo. Solictar a CMDC | I70: Media | J70: Programación | K70: 1 | L70: 43005 | M70: se incorpora en lista de preparativos con fecha 27-09-2017
A71: 66 | B71: Filtro 3 | C71: 42984 | D71: Amenaza | E71: R. Vilca | F71: No se realiza la actividad de limpieza de filtro y placas | G71: Programación | H71: Asegurar cumplimiento de carta Gantt, y solicitud de protocolo de entrega de equipos | I71: Alta | J71: supervisores | K71: 100 | L71: Cada vez | M71: De no cumplirce escalar el tema
A72: 67 | B72: Filtro 3 | C72: 42985 | D72: Debilidad | E72: M. Contreras | F72: Cambio de mangas de valvula larox a prueba durante la mantención. | G72: Operaciones | H72: Asegurar el cumplimiento de los preparativos considerados en los programas semanales previos | I72: Alta | J72: supervisores | K72: 100 | L72: Cada vez | M72: Linea de supervisión debe priorizar lo importante por sobre lo urgente y levantar a nivel superior el cambio de prioridades de los preparativos
A73: 68 | B73: Filtro 3 | C73: 42985 | D73: Amenaza | E73: M. Contreras | F73: No se sueldan bujes de horquillas como preparativo | G73: Programación | H73: Solicitar que buje sea incorporada a horquilla por proveedor | I73: Media | J73: M. Meriño | K73: 50 | L73: unica vez | M73: 27-09 se envia correo a responsable
A74: 69 | B74: Filtro 3 | C74: 42985 | D74: Debilidad | E74: P. Perez | F74: No se cuenta con extensión cuadrante de 1" para torqueo de soporte horquilla. | G74: Operaciones | H74: Realizar solcom para su compra. | I74: Media | J74: Abastecimeinto | K74: 50 | L74: unica vez | M74: 03-09-2017 se genera solcom x cinco unidades ( Luis Cortes)
A75: 70 | B75: Filtro 3 | C75: 42985 | D75: Debilidad | E75: P. Perez | F75: No se encuentran pernos en area para soporte horquilla. | G75: Operaciones | H75: Asegurar cumplimeinto de preparativos en programa semanal. | I75: Alta | J75: supervisores | K75: 100 | L75: Cada vez | M75: Linea de supervisión debe priorizar lo importante por sobre lo urgente y levantar a nivel superior el cambio de prioridades de los preparativos
A76: 71 | B76: Filtro 3 | C76: 42986 | D76: Amenaza | E76: M. Contreras | F76: No se preparan las empaquetadura. | G76: Operaciones | H76: Asegurar cumplimeinto de preparativos en programa semanal. | I76: Media | J76: supervisores | K76: 100 | L76: Cada vez
A77: 72 | B77: Filtro 3 | C77: 42986 | D77: Oportunidad | E77: R. Segovia. | F77: Verificar espesor ductos salientes lado cabezal fijo. | G77: Programación | H77: Incoporar en preparativos la medición de espesor de ductos para definir cambio. | I77: Media | J77: supervisores | K77: 100 | L77: 43005 | M77: se incorpora en lista de preparativos con fecha 27-09-2017
A78: 73 | B78: Filtro 3 | C78: 42986 | D78: Amenaza | E78: M. Contreras | F78: No se fabrican ductos inferiores de drenaje en preparativos (insertos lado fijo) | G78: Programación | H78: Incoporar en preparativos fabricación de ducto meintras se asegure su catalogación (con revestimiento poliupretano) | I78: Media | J78: Programación | K78: 1 | L78: 43005
A79: 74 | B79: Filtro 3 | C79: 42986 | D79: Oportunidad | E79: R. Segovia. | F79: Considerar lijadora de banda para pulido de rieles y bastidor para cambio de pernos. | G79: Operaciones | H79: Realizar solcom para su compra. | I79: Media | J79: Abastecimeinto | K79: 50 | L79: unica vez | M79: 03-09-2017 se genera solcom x cinco unidades ( Luis Cortes)
A80: 75 | B80: Filtro 3 | C80: 42986 | D80: Oportunidad | E80: R. Segovia. | F80: Considerar pre armado de ducteria como preparativo | G80: Programación | H80: Considerar en preparativos y dentro de programa semanal. | I80: Media | J80: Planificacion | K80: 1 | L80: 43005 | M80: se incorpora en lista de preparativos con fecha 27-09-2017
A81: 76 | B81: Filtro 3 | C81: 42986 | D81: Debilidad | E81: M. Contreras | F81: No se cuenta con oxigenos en punto de trabajo (para cambio de botellas) | G81: Operaciones | H81: Asegurar cumplimeinto de preparativos en programa semanal. | I81: Alta | J81: supervisores | K81: 100 | L81: Cada vez | M81: Linea de supervisión debe priorizar lo importante por sobre lo urgente y levantar a nivel superior el cambio de prioridades de los preparativos
A82: 77 | B82: Filtro 3 | C82: 42986 | D82: Amenaza | E82: C. Marin | F82: Habilitar jaula para depositos de oxigeno y acetileno. | G82: Operaciones | H82: seguimiento a compra de jaulas para traslado de cilindros | I82: Alta | J82: Pedro Perez | K82: 0 | L82: 43042
A83: 78 | B83: Filtro 3 | C83: 42986 | D83: Debilidad | E83: M. Espejo | F83: Brida de 4" cabezal movil, no coincide.
A84: 79 | B84: Filtro 3 | C84: 42986 | D84: Debilidad | E84: R. Segovia. | F84: La instalacion de puntos de anclaje deben ser con terminación con pintura para evitar corrosión. | G84: Operaciones | H84: Incorporar en instructivo de instalación de ptos de anclaje la pintura en la terminación | I84: Media | J84: supervisores | K84: 50 | L84: Cada vez | M84: 03-10-2017 se envia correo a linea de supervisión por la incooporación en instructivo de trabajo y por la entrega de especificaciones tecnicas a bodega para la compra de pintura
A85: 80 | B85: Filtro 3 | C85: 42987 | D85: Debilidad | E85: M. Espejo | F85: Pernos separadores de portatelas en lado contrario. | G85: Operaciones | H85: 1.-General lista de chequeo para los porta telas con plano del fabricante 2.-Incorporar en preparativos siemens la cumplimiento de la verificación de porta Telas | I85: 1.-Media 2.-Media | J85: 1.-supervisores 2.-Planificación | K85: 1.-50 2.-100 | L85: unica vez | M85: 1.-03-10-2017 Se envia correo a linea de supervición para la generación de lista chequeo 2.-03-09-2017 Se incorpora en lista de preparativos
A86: 81 | B86: Filtro 3 | C86: 42988 | D86: Oportunidad | E86: P. Perez | F86: considerar bandeja para clasificación de perneria
A87: 82 | B87: Filtro 3 | C87: 42989 | D87: Debilidad | E87: R. Segovia. | F87: Chavetas instaladas sentido inverso. | G87: Operaciones | H87: Incorporar en instructivo la forma correcta de instalar las chavetas | I87: Alta | J87: supervisores | K87: 50 | L87: Cada vez | M87: 03-10-2017 se envia correo a linea de supervisión por la incooporación en instructivo de trabajo
A88: 83 | B88: Filtro 3 | C88: 42989 | D88: Amenaza | E88: R. Segovia. | F88: Fugas en filtros contiguos mientras se realiza mantención | G88: Operaciones | H88: implementación de cortinas para evitar la proyecion de pulpa | I88: Alta | J88: supervisores | K88: 0 | L88: Cada vez | M88: generar solicitud de insumos para la instalación de cortinas
A89: 84 | B89: Filtro 3 | C89: 42989 | D89: Debilidad | E89: R. Segovia. | F89: Fuga en flange de ducto. | G89: Operaciones | H89: Incorporar en instructivo la forma corresta de apretar flanje | I89: Alta | J89: supervisores | K89: 50 | L89: Cada vez | M89: 03-10-2017 se envia correo a linea de supervisión por la incorporación en instructivo de trabajo
A90: 85 | B90: Filtro 5 | C90: 43152 | D90: DEBILIDAD | E90: R. VILCA | F90: Instalación de tres placa madre en filtro | G90: Operaciones
A91: 86 | B91: Filtro 5 | C91: 43152 | D91: DEBILIDAD | E91: R. VILCA | F91: Mal calado en valvula v9 | G91: Operaciones
A92: 87 | B92: Filtro 5 | C92: 43152 | D92: DEBILIDAD | E92: R. VILCA | F92: Valvula de aguja al reves | G92: Operaciones
A93: 88 | B93: Filtro 5 | C93: 43152 | D93: DEBILIDAD | E93: R. VILCA | F93: Mal conexionado de valvulas v8 | G93: Operaciones
A94: 89 | B94: Filtro 5 | C94: 43152 | D94: Fortaleza | E94: R. VILCA | F94: Metodología de instalacion de rieles | G94: Operaciones
A95: 90 | B95: Filtro 5 | C95: 43152 | D95: Fortaleza | E95: R. VILCA | F95: Limpieza del area en cada cambio de turno | G95: Operaciones
A96: 91 | B96: Filtro 5 | C96: 43152 | D96: Fortaleza | E96: R. VILCA | F96: Ordenamiento de pernos el cajas | G96: Programación
A97: 92 | B97: Filtro 5 | C97: 43152 | D97: DEBILIDAD | E97: R. VILCA | F97: Logistica de personal de apoyo ( Ropa, Casa de cambio) | G97: Programación
A98: 93 | B98: Filtro 5 | C98: 43152 | D98: OPORTUNIDAD | E98: R. VILCA | F98: Mejora en plan de mantenimiento HU | G98: Programación
A99: 94 | B99: Filtro 5 | C99: 43152 | D99: OPORTUNIDAD | E99: R. VILCA | F99: Generar tareas por dias para en mantenimiento | G99: Programación
A100: 95 | B100: Filtro 5 | C100: 43152 | D100: Fortaleza | E100: R. VILCA | F100: Generación del plan de segregacion de cierre | G100: Operaciones
...

Sheet STOCK CODE
C1: SEGUIMIENTO STOCKCODE | N1: 45367.333
C4: FAENA : | D4: CORDILLERA CMDIC GMT1401A
C5: EQUIPO APL :
B7: =COUNTA(Tabla_APL[STOCKCODE]) -> 239 | C7: AVIABLE | E7: EN TRANSITO | G7: POR ENTREGA | H7: UBICACION | K7: CLASIFICACION | M7: ITEM
A8: ITEM | B8: STOCKCODE | C8: QTY | D8: SOH | E8: IN TRANSIT | F8: DUES IN | G8: DUES OUT | H8: BODEGA | I8: ROP | J8: ROQ | K8: CLASS | L8: TYPE | M8: NOMBRE | N8: DESCRIPCION | O8: EXTENDIDA | P8: Column1 | Q8: Column2
A9: 1 | B9: 580449 | C9: 62 CU | D9: 62 | E9: 0 | F9: 0 | G9: 0 | H9: BPTO | I9: 50 | J9: 0 | K9: N | L9: 7 | M9: POLIN | N9: POLIN METALICO DE CARGA 6" | O9: POLIN METALICO DE CARGA 6", , , | P9: 160334091 | Q9: 127201
A10: 2 | B10: 96206 | C10: 82 CU | D10: 82 | E10: 0 | F10: 0 | G10: 0 | H10: BPTO | I10: 70 | J10: 0 | K10: N | L10: B | M10: POLIN | N10: POLIN RETORNO 6"X 44-1/2" 17 | O10: POLIN RETORNO 6"X 44-1/2" 17, , , | P10: 403097473 | Q10: 339174,05
A11: 3 | B11: 439844 | C11: 24 CU | D11: 24 | E11: 0 | F11: 0 | G11: 0 | H11: BPTO | I11: 3 | J11: 0 | K11: N | L11: 7 | M11: POLIN | N11: POLIN CARGA POLIETILENO UHMW | O11: POLIN CARGA POLIETILENO UHMW, , , | P11: 53219024 | Q11: 40794
A12: 4 | B12: 727602 | C12: 26 CU | D12: 26 | E12: 0 | F12: 0 | G12: 0 | H12: BPTO | I12: 0 | J12: 0 | K12: 5 | L12: 7 | M12: POLIN | N12: POLIN | O12: POLIN, , , | P12: 151006538 | Q12: 108225
A13: 5 | B13: 91330 | C13: 3 CU | D13: 3 | E13: 0 | F13: 0 | G13: 0 | H13: BPTO | I13: 0 | J13: 0 | K13: N | L13: 7 | M13: ESTACION | N13: ESTAC POLIN RETORNO 6X36" CEMA C6 | O13: ESTAC POLIN RETORNO 6X36" CEMA C6, , , | P13: 199521875 | Q13: 138740
A14: 6 | B14: 570275 | C14: 4 CU | D14: 4 | E14: 0 | F14: 0 | G14: 0 | H14: INES | I14: 3 | J14: 0 | K14: N | L14: 7 | M14: POLIN | N14: POLIN AUTOCENTRANTE DE CARGA (TRU-TRAINE | O14: POLIN AUTOCENTRANTE DE CARGA (TRU-TRAINE, , , | P14: 7299,46 | Q14: 68278134375
A15: 7 | B15: 743669 | C15: 6 CU | D15: 6 | E15: 0 | F15: 11 | G15: 0 | H15: INES | I15: 26 | J15: 0 | K15: N | L15: 7 | M15: RODILLO | N15: RODILLO LATERAL CONICO DE CARGA CORREA36" | O15: RODILLO LATERAL CONICO DE CARGA;CORREA36, ", , | P15: 187615186 | Q15: 1583459
A16: 8 | B16: 743668 | C16: 22 CU | D16: 22 | E16: 0 | F16: 0 | G16: 0 | H16: INES | I16: 20 | J16: 0 | K16: N | L16: 7 | M16: RODILLO | N16: RODILLO CENTRAL METALICO DE CARGA CORREA36" | O16: RODILLO CENTRAL METALICO DE CARGA;CORREA, 36", , | P16: 565812273 | Q16: 484545079091
A17: 9 | B17: 748010 | C17: 5 CU | D17: 5 | E17: 0 | F17: 0 | G17: 0 | H17: BPTO | I17: 4 | J17: 0 | K17: N | L17: 7 | M17: ESTACION | N17: ESTACION | O17: ESTACION, , , | P17: 13125989167 | Q17: 11612392
A18: 10 | B18: 748002 | C18: 20 CU | D18: 20 | E18: 0 | F18: 0 | G18: 0 | H18: INES | I18: 20 | J18: 0 | K18: N | L18: 7 | M18: RODILLO | N18: RODILLO | O18: RODILLO, , , | P18: 4515459167 | Q18: 4103563,4
A19: 11 | B19: 743670 | C19: 6 CU | D19: 6 | E19: 0 | F19: 0 | G19: 0 | H19: INES | I19: 5 | J19: 0 | K19: N | L19: 7 | M19: ESTACION | N19: ESTACION AUTO-CENTRANTE DE RETORNO PLANOCORREA 36" | O19: ESTACION AUTO-CENTRANTE DE RETORNO PLANO, CORREA 36", , | P19: 8244896667 | Q19: 7677870691667
A20: 12 | B20: 96180 | C20: 0 CU | D20: 0 | E20: 0 | F20: 0 | G20: 0 | H20: BPTO | I20: 0 | J20: 0 | K20: 5 | L20: 7 | M20: ESTACION | N20: ESTAC POLIN GUIA CARGA 36X6" 35GRD C6 | O20: ESTAC POLIN GUIA CARGA 36X6" 35GRD C6, , , | P20: 584,66 | Q20: 363218666667
A21: 13 | B21: 444042 | C21: 5 CU | D21: 5 | E21: 0 | F21: 8 | G21: 0 | H21: BPTO | I21: 8 | J21: 0 | K21: N | L21: 7 | M21: BASTON | N21: BASTON CENTRADOR POLIMERO | O21: BASTON CENTRADOR POLIMERO, , , | P21: 74359375 | Q21: 57055
A22: 14 | B22: 96198 | C22: 0 CU | D22: 0 | E22: 0 | F22: 0 | G22: 0 | H22: BPTO | I22: 0 | J22: 0 | K22: 5 | L22: 7 | M22: ESTACION | N22: ESTAC POLIN GUIA RETORNO 36X6" CEMA C6 REEMPLAZADO x 748010 y 743670 | O22: ESTAC POLIN GUIA RETORNO 36X6" CEMA C6;R, EEMPLAZADO x 748010 y 743670, , | P22: 595142 | Q22: 365170,2
A23: 15 | B23: 146340 | C23: 3 CU | D23: 3 | E23: 0 | F23: 0 | G23: 0 | H23: BPTO | I23: 2 | J23: 0 | K23: N | L23: B | M23: PLANCHA | N23: PLANCHA TIVAR88 13MMX800MMX2000XMM | O23: PLANCHA TIVAR88 13MMX800MMX2000XMM, , , | P23: 7355025 | Q23: 597625
A24: 16 | B24: 151126 | C24: 0 RL | D24: 12 | E24: 12 | F24: 0 | G24: 0 | H24: INES | I24: 9 | J24: 0 | K24: N | L24: B | M24: GUARDERA | N24: GUARDERA GOMA 15MMX150MMX10MTS 50 SHOREA | O24: GUARDERA GOMA 15MMX150MMX10MTS 50 SHOREA, , , | P24: 7144525 | Q24: 677930
A25: 17 | B25: 475806 | C25: 0 CU | D25: 0 | E25: 0 | F25: 0 | G25: 0 | H25: BPTO | I25: 5 | J25: 8 | K25: N | L25: 6 | M25: PARRILLA | N25: PARRILLA FRP | O25: PARRILLA FRP, , , | P25: 796902 | Q25: 685977
A26: 18 | B26: 146340 | C26: 3 CU | D26: 3 | E26: 0 | F26: 0 | G26: 0 | H26: BPTO | I26: 2 | J26: 0 | K26: N | L26: B | M26: PLANCHA | N26: PLANCHA TIVAR88 13MMX800MMX2000XMM | O26: PLANCHA TIVAR88 13MMX800MMX2000XMM, , , | P26: 7355025 | Q26: 597625
A27: 19 | B27: 580449 | C27: 62 CU | D27: 62 | E27: 0 | F27: 0 | G27: 0 | H27: BPTO | I27: 50 | J27: 0 | K27: N | L27: 7 | M27: POLIN | N27: POLIN METALICO DE CARGA 6" | O27: POLIN METALICO DE CARGA 6", , , | P27: 160334091 | Q27: 127201
A28: 20 | B28: 96206 | C28: 82 CU | D28: 82 | E28: 0 | F28: 0 | G28: 0 | H28: BPTO | I28: 70 | J28: 0 | K28: N | L28: B | M28: POLIN | N28: POLIN RETORNO 6"X 44-1/2" 17 | O28: POLIN RETORNO 6"X 44-1/2" 17, , , | P28: 403097473 | Q28: 339174,05
A29: 21 | B29: 439844 | C29: 24 CU | D29: 24 | E29: 0 | F29: 0 | G29: 0 | H29: BPTO | I29: 3 | J29: 0 | K29: N | L29: 7 | M29: POLIN | N29: POLIN CARGA POLIETILENO UHMW | O29: POLIN CARGA POLIETILENO UHMW, , , | P29: 53219024 | Q29: 40794
A30: 22 | B30: 727602 | C30: 26 CU | D30: 26 | E30: 0 | F30: 0 | G30: 0 | H30: BPTO | I30: 0 | J30: 0 | K30: 5 | L30: 7 | M30: POLIN | N30: POLIN | O30: POLIN, , , | P30: 151006538 | Q30: 108225
A31: 23 | B31: 91330 | C31: 3 CU | D31: 3 | E31: 0 | F31: 0 | G31: 0 | H31: BPTO | I31: 0 | J31: 0 | K31: N | L31: 7 | M31: ESTACION | N31: ESTAC POLIN RETORNO 6X36" CEMA C6 | O31: ESTAC POLIN RETORNO 6X36" CEMA C6, , , | P31: 199521875 | Q31: 138740
A32: 24 | B32: 570275 | C32: 4 CU | D32: 4 | E32: 0 | F32: 0 | G32: 0 | H32: INES | I32: 3 | J32: 0 | K32: N | L32: 7 | M32: POLIN | N32: POLIN AUTOCENTRANTE DE CARGA (TRU-TRAINE | O32: POLIN AUTOCENTRANTE DE CARGA (TRU-TRAINE, , , | P32: 7299,46 | Q32: 68278134375
A33: 25 | B33: 743669 | C33: 6 CU | D33: 6 | E33: 0 | F33: 11 | G33: 0 | H33: INES | I33: 26 | J33: 0 | K33: N | L33: 7 | M33: RODILLO | N33: RODILLO LATERAL CONICO DE CARGA CORREA36" | O33: RODILLO LATERAL CONICO DE CARGA;CORREA36, ", , | P33: 187615186 | Q33: 1583459
A34: 26 | B34: 743668 | C34: 22 CU | D34: 22 | E34: 0 | F34: 0 | G34: 0 | H34: INES | I34: 20 | J34: 0 | K34: N | L34: 7 | M34: RODILLO | N34: RODILLO CENTRAL METALICO DE CARGA CORREA36" | O34: RODILLO CENTRAL METALICO DE CARGA;CORREA, 36", , | P34: 565812273 | Q34: 484545079091
A35: 27 | B35: 748010 | C35: 5 CU | D35: 5 | E35: 0 | F35: 0 | G35: 0 | H35: BPTO | I35: 4 | J35: 0 | K35: N | L35: 7 | M35: ESTACION | N35: ESTACION | O35: ESTACION, , , | P35: 13125989167 | Q35: 11612392
A36: 28 | B36: 748002 | C36: 20 CU | D36: 20 | E36: 0 | F36: 0 | G36: 0 | H36: INES | I36: 20 | J36: 0 | K36: N | L36: 7 | M36: RODILLO | N36: RODILLO | O36: RODILLO, , , | P36: 4515459167 | Q36: 4103563,4
A37: 29 | B37: 743670 | C37: 6 CU | D37: 6 | E37: 0 | F37: 0 | G37: 0 | H37: INES | I37: 5 | J37: 0 | K37: N | L37: 7 | M37: ESTACION | N37: ESTACION AUTO-CENTRANTE DE RETORNO PLANOCORREA 36" | O37: ESTACION AUTO-CENTRANTE DE RETORNO PLANO, CORREA 36", , | P37: 8244896667 | Q37: 7677870691667
A38: 30 | B38: 96180 | C38: 0 CU | D38: 0 | E38: 0 | F38: 0 | G38: 0 | H38: BPTO | I38: 0 | J38: 0 | K38: 5 | L38: 7 | M38: ESTACION | N38: ESTAC POLIN GUIA CARGA 36X6" 35GRD C6 | O38: ESTAC POLIN GUIA CARGA 36X6" 35GRD C6, , , | P38: 584,66 | Q38: 363218666667
A39: 31 | B39: 444042 | C39: 5 CU | D39: 5 | E39: 0 | F39: 8 | G39: 0 | H39: BPTO | I39: 8 | J39: 0 | K39: N | L39: 7 | M39: BASTON | N39: BASTON CENTRADOR POLIMERO | O39: BASTON CENTRADOR POLIMERO, , , | P39: 74359375 | Q39: 57055
A40: 32 | B40: 96198 | C40: 0 CU | D40: 0 | E40: 0 | F40: 0 | G40: 0 | H40: BPTO | I40: 0 | J40: 0 | K40: 5 | L40: 7 | M40: ESTACION | N40: ESTAC POLIN GUIA RETORNO 36X6" CEMA C6 REEMPLAZADO x 748010 y 743670 | O40: ESTAC POLIN GUIA RETORNO 36X6" CEMA C6;R, EEMPLAZADO x 748010 y 743670, , | P40: 595142 | Q40: 365170,2
A41: 33 | B41: 146340 | C41: 3 CU | D41: 3 | E41: 0 | F41: 0 | G41: 0 | H41: BPTO | I41: 2 | J41: 0 | K41: N | L41: B | M41: PLANCHA | N41: PLANCHA TIVAR88 13MMX800MMX2000XMM | O41: PLANCHA TIVAR88 13MMX800MMX2000XMM, , , | P41: 7355025 | Q41: 597625
A42: 34 | B42: 151126 | C42: 0 RL | D42: 12 | E42: 12 | F42: 0 | G42: 0 | H42: INES | I42: 9 | J42: 0 | K42: N | L42: B | M42: GUARDERA | N42: GUARDERA GOMA 15MMX150MMX10MTS 50 SHOREA | O42: GUARDERA GOMA 15MMX150MMX10MTS 50 SHOREA, , , | P42: 7144525 | Q42: 677930
A43: 35 | B43: 751697 | C43: 223 CU | D43: 223 | E43: 0 | F43: 0 | G43: 0 | H43: BPTO | I43: 87 | J43: 0 | K43: N | L43: 7 | M43: RODILLO | N43: RODILLO DE IMPACTO | O43: RODILLO DE IMPACTO, , , | P43: 168885078 | Q43: 1345350625
A44: 36 | B44: 746231 | C44: 4 CU | D44: 4 | E44: 0 | F44: 2 | G44: 2 | H44: BPTO | I44: 3 | J44: 0 | K44: N | L44: 7 | M44: TUBO | N44: TUBO AIRE MEMBRANA | O44: TUBO AIRE MEMBRANA, , , | P44: 1444,07 | Q44: 1285073736
A45: 37 | B45: 746218 | C45: 2 CU | D45: 4 | E45: 2 | F45: 0 | G45: 1 | H45: BPTO | I45: 2 | J45: 0 | K45: N | L45: 7 | M45: TUBO | N45: TUBO CON FLANGE | O45: TUBO CON FLANGE, , , | P45: 8523975 | Q45: 7711718375
A46: 38 | B46: 746232 | C46: 7 CU | D46: 8 | E46: 1 | F46: 0 | G46: 4 | H46: BPTO | I46: 4 | J46: 1 | K46: N | L46: 7 | M46: TUBO | N46: TUBO AIRE MEMBRANA | O46: TUBO AIRE MEMBRANA, , , | P46: 329290125 | Q46: 2916392235
A47: 39 | B47: 123216 | C47: 16 CU | D47: 16 | E47: 0 | F47: 0 | G47: 4 | H47: BPTO | I47: 10 | J47: 0 | K47: N | L47: 7 | M47: VALVULA | N47: VALVULA RETENCION (NO REPARABLE J. T.) | O47: VALVULA RETENCION (NO REPARABLE J. T.), , , | P47: 696088889 | Q47: 608371,88
A48: 40 | B48: 88948 | C48: 39 CU | D48: 47 | E48: 8 | F48: 0 | G48: 4 | H48: BPTO | I48: 38 | J48: 0 | K48: N | L48: 7 | M48: VALVULA | N48: VALVULA CHECK | O48: VALVULA CHECK, , , | P48: 1458638936 | Q48: 1290030254043
A49: 41 | B49: 123224 | C49: 28 CU | D49: 28 | E49: 0 | F49: 8 | G49: 24 | H49: BPTO | I49: 15 | J49: 0 | K49: N | L49: 7 | M49: JUNTA | N49: JUNTA EXPANSION 2" ANSI 150 LBS | O49: JUNTA EXPANSION 2" ANSI 150 LBS, , , | P49: 846730625 | Q49: 744548263125
A50: 42 | B50: 114330 | C50: 20 CU | D50: 20 | E50: 0 | F50: 0 | G50: 6 | H50: BPTO | I50: 15 | J50: 6 | K50: N | L50: 7 | M50: VALVULA | N50: VALVULA 10/070-120 DN50/PN V10 | O50: VALVULA 10/070-120 DN50/PN V10, , , | P50: 1618501786 | Q50: 1371093654286
A51: 43 | B51: 746233 | C51: 6 CU | D51: 10 | E51: 4 | F51: 2 | G51: 4 | H51: BPTO | I51: 6 | J51: 0 | K51: N | L51: 7 | M51: TUBO | N51: TUBO TOP BLOW | O51: TUBO TOP BLOW, , , | P51: 750251 | Q51: 691341271
A52: 44 | B52: 448068 | C52: 9 CU | D52: 11 | E52: 2 | F52: 0 | G52: 6 | H52: BPTO | I52: 4 | J52: 0 | K52: N | L52: 7 | M52: VALVULA | N52: VALVULA REDUCTORA AJU235-50 | O52: VALVULA REDUCTORA AJU235-50, , , | P52: 1379477273 | Q52: 1221666836364
A53: 45 | B53: 746234 | C53: 5 CU | D53: 5 | E53: 0 | F53: 0 | G53: 1 | H53: BPTO | I53: 3 | J53: 0 | K53: N | L53: 7 | M53: TUBO | N53: TUBO DN50 PN16 ANSI 2" 150lbs L=480 | O53: TUBO DN50 PN16 ANSI 2" 150lbs L=480, , , | P53: 1304526667 | Q53: 1144480136667
A54: 46 | B54: 155762 | C54: 9 CU | D54: 21 | E54: 12 | F54: 0 | G54: 4 | H54: BPTO | I54: 9 | J54: 0 | K54: N | L54: 7 | M54: VALVULA | N54: VALVULA DN 50/PN10 | O54: VALVULA DN 50/PN10, , , | P54: 82939524 | Q54: 75997265714
A55: 47 | B55: 746235 | C55: 4 CU | D55: 4 | E55: 0 | F55: 0 | G55: 1 | H55: BPTO | I55: 3 | J55: 1 | K55: N | L55: 7 | M55: TUBO | N55: TUBO DN50 PN16 ANSI 2" 150lbs L=963 | O55: TUBO DN50 PN16 ANSI 2" 150lbs L=963, , , | P55: 1569986 | Q55: 1375807276
A56: 48 | B56: 746221 | C56: 10 CU | D56: 10 | E56: 0 | F56: 2 | G56: 6 | H56: BPTO | I56: 6 | J56: 2 | K56: N | L56: 7 | M56: TUBO | N56: TUBO CON FLANGE L365 | O56: TUBO CON FLANGE L365, , , | P56: 1314376667 | Q56: 1142763768333
A57: 49 | B57: 746222 | C57: 6 CU | D57: 6 | E57: 0 | F57: 2 | G57: 2 | H57: BPTO | I57: 4 | J57: 0 | K57: N | L57: 7 | M57: TUBO | N57: TUBO CON FLANGE L440 | O57: TUBO CON FLANGE L440, , , | P57: 1095847143 | Q57: 948904164286
A58: 50 | B58: 746225 | C58: 8 CU | D58: 10 | E58: 2 | F58: 2 | G58: 4 | H58: BPTO | I58: 6 | J58: 0 | K58: N | L58: 7 | M58: TUBO | N58: TUBO CON FLANGE L175 | O58: TUBO CON FLANGE L175, , , | P58: 966914 | Q58: 880721968
A59: 51 | B59: 155903 | C59: 8 CU | D59: 8 | E59: 0 | F59: 4 | G59: 4 | H59: BPTO | I59: 7 | J59: 0 | K59: N | L59: 7 | M59: VALVULA | N59: VALVULA DN50/PN16 | O59: VALVULA DN50/PN16, , , | P59: 204150455 | Q59: 183558242727
... A64: 56 | B64: 155861 | C64: 14 CU | D64: 24 | E64: 10 | F64: 0 | G64: 10 | H64: BPTO | I64: 9 | J64: 0 | K64: N | L64: 7 | M64: ACOPLAMIENTO | N64: ACOPLAMIENTO TUBO RACOR DN50 | O64: ACOPLAMIENTO TUBO RACOR DN50, , , | P64: 49332917 | Q64: 43810333333
A65: 57 | B65: 158147 | C65: 114 CU | D65: 114 | E65: 0 | F65: 0 | G65: 51 | H65: BPTO | I65: 60 | J65: 0 | K65: N | L65: B | M65: ABRAZADERA | N65: ABRAZADERA ACERO 3" SIN FIN AISI 304 | O65: ABRAZADERA ACERO 3" SIN FIN AISI 304, , , | P65: 2170773 | Q65: 19279923617
A66: 58 | B66: 158154 | C66: 34 CU | D66: 34 | E66: 0 | F66: 0 | G66: 12 | H66: BPTO | I66: 20 | J66: 0 | K66: N | L66: 7 | M66: ABRAZADERA | N66: ABRAZADERA | O66: ABRAZADERA, , , | P66: 74966552 | Q66: 66282,5
A67: 59 | B67: 88831 | C67: 9 CU | D67: 9 | E67: 0 | F67: 4 | G67: 3 | H67: BPTO | I67: 6 | J67: 0 | K67: N | L67: B | M67: MANGUERA | N67: MANGUERA | O67: MANGUERA, , , | P67: 704635 | Q67: 629869965714
A68: 60 | B68: 746223 | C68: 2 CU | D68: 2 | E68: 0 | F68: 4 | G68: 2 | H68: BPTO | I68: 3 | J68: 0 | K68: N | L68: 7 | M68: CODO | N68: CODO CON FLANGE | O68: CODO CON FLANGE, , , | P68: 1068466667 | Q68: 1016998,4
A69: 61 | B69: 746219 | C69: 4 CU | D69: 4 | E69: 0 | F69: 2 | G69: 2 | H69: BPTO | I69: 3 | J69: 0 | K69: N | L69: 7 | M69: REDUCCION | N69: REDUCCION TOP BLOW | O69: REDUCCION TOP BLOW, , , | P69: 3053872 | Q69: 2698337766
A70: 62 | B70: 559385 | C70: 3 CU | D70: 3 | E70: 0 | F70: 8 | G70: 6 | H70: BPTO | I70: 5 | J70: 0 | K70: N | L70: 7 | M70: DUCTO | N70: DUCTO 6" | O70: DUCTO 6", , , | P70: 694657 | Q70: 575327
A71: 63 | B71: 746220 | C71: 4 CU | D71: 4 | E71: 0 | F71: 2 | G71: 4 | H71: BPTO | I71: 2 | J71: 1 | K71: N | L71: 7 | M71: TUBO | N71: TUBO CON FLANGE L150 | O71: TUBO CON FLANGE L150, , , | P71: 1181438 | Q71: 1069175748
A72: 64 | B72: 325316 | C72: 1 CU | D72: 1 | E72: 0 | F72: 9 | G72: 4 | H72: BPTO | I72: 3 | J72: 0 | K72: N | L72: 7 | M72: FORRO | N72: FORRO DEGASTE ALIMENTACION FILTRO | O72: FORRO DEGASTE ALIMENTACION FILTRO, , , | P72: 90550833 | Q72: 78928,9
A73: 65 | B73: 177899 | C73: 2563 MT | D73: 2563 | E73: 0 | F73: 0 | G73: 1020 | H73: BPTO | I73: 212 | J73: 0 | K73: N | L73: B | M73: CABLE | N73: CABLE ACERO PLASTIFICADO 3/16" | O73: CABLE ACERO PLASTIFICADO 3/16", , , | P73: 1516853 | Q73: 1373347158
A74: 66 | B74: 271460 | C74: 2 CU | D74: 2 | E74: 0 | F74: 3 | G74: 0 | H74: BPTO | I74: 4 | J74: 0 | K74: N | L74: 7 | M74: EJE | N74: EJE LADO PRINCIPAL COMPUERTA FILTRO | O74: EJE LADO PRINCIPAL COMPUERTA FILTRO, , , | P74: 1387193333 | Q74: 1288860883333
A75: 67 | B75: 648717 | C75: 9 JG | D75: 9 | E75: 0 | F75: 0 | G75: 2 | H75: BPTO | I75: 4 | J75: 0 | K75: N | L75: 7 | M75: EJE | N75: EJE DE COMPUERTA FILTRO PRENSA | O75: EJE DE COMPUERTA FILTRO PRENSA, , , | P75: 1463,49 | Q75: 1372133107273
A76: 68 | B76: 287151 | C76: 20 CU | D76: 20 | E76: 0 | F76: 4 | G76: 12 | H76: BPTO | I76: 10 | J76: 0 | K76: N | L76: 7 | M76: SOPORTE | N76: SOPORTE RODAMIENTO | O76: SOPORTE RODAMIENTO, , , | P76: 1877104545 | Q76: 1726459576818
A77: 69 | B77: 274605 | C77: 7 CU | D77: 7 | E77: 0 | F77: 30 | G77: 28 | H77: BPTO | I77: 6 | J77: 0 | K77: N | L77: 7 | M77: RODAMIENTO | N77: RODAMIENTO BOLAS | O77: RODAMIENTO BOLAS, , , | P77: 77388619 | Q77: 692946323333
A78: 70 | B78: 287169 | C78: 30 CU | D78: 30 | E78: 0 | F78: 4 | G78: 24 | H78: BPTO | I78: 6 | J78: 0 | K78: N | L78: 7 | M78: MANGUITO | N78: MANGUITO FIJACION | O78: MANGUITO FIJACION, , , | P78: 201426765 | Q78: 185816229412
A79: 71 | B79: 274613 | C79: 24 CU | D79: 24 | E79: 0 | F79: 8 | G79: 20 | H79: BPTO | I79: 8 | J79: 0 | K79: N | L79: B | M79: ANILLO | N79: ANILLO GUIA FRB 125/200 | O79: ANILLO GUIA FRB 125/200, , , | P79: 75614688 | Q79: 68240,9
A80: 72 | B80: 274621 | C80: 9 CU | D80: 9 | E80: 0 | F80: 5 | G80: 4 | H80: BPTO | I80: 8 | J80: 0 | K80: N | L80: 7 | M80: CASQUILLO | N80: CASQUILLO ETP-100/125 | O80: CASQUILLO ETP-100/125, , , | P80: 2929415625 | Q80: 25847983125
A81: 73 | B81: 271478 | C81: 11 CU | D81: 11 | E81: 0 | F81: 3 | G81: 6 | H81: BPTO | I81: 4 | J81: 0 | K81: N | L81: 7 | M81: PALANCA | N81: PALANCA MOVIMIENTO COMPUERTA FILTRO | O81: PALANCA MOVIMIENTO COMPUERTA FILTRO, , , | P81: 1985002308 | Q81: 1734883274615
A82: 74 | B82: 395137 | C82: 9 CU | D82: 9 | E82: 0 | F82: 5 | G82: 6 | H82: BPTO | I82: 4 | J82: 0 | K82: N | L82: 7 | M82: EJE | N82: SHAFT | O82: SHAFT, , , | P82: 77820769 | Q82: 69389268462
A83: 75 | B83: 73684 | C83: 15 CU | D83: 15 | E83: 0 | F83: 0 | G83: 6 | H83: BPTO | I83: 4 | J83: 0 | K83: N | L83: 7 | M83: CILINDRO | N83: CILINDRO HIDRAULICO | O83: CILINDRO HIDRAULICO, , , | P83: 846861765 | Q83: 760381029412
A84: 76 | B84: 271411 | C84: 7 CU | D84: 7 | E84: 0 | F84: 0 | G84: 5 | H84: BPTO | I84: 1 | J84: 0 | K84: N | L84: 7 | M84: SOPORTE | N84: SOPORTE EJE INFERIOR CILINDRO HIDRAULICO | O84: SOPORTE EJE INFERIOR CILINDRO HIDRAULICO, , , | P84: 1393644286 | Q84: 1222533825714
A85: 77 | B85: 274597 | C85: 18 CU | D85: 18 | E85: 0 | F85: 0 | G85: 14 | H85: BPTO | I85: 4 | J85: 2 | K85: N | L85: 7 | M85: SOPORTE | N85: SOPORTE RODAMIENTO | O85: SOPORTE RODAMIENTO, , , | P85: 16172975 | Q85: 1501610,24
A86: 78 | B86: 306035 | C86: 9 CU | D86: 9 | E86: 0 | F86: 26 | G86: 4 | H86: BPTO | I86: 5 | J86: 0 | K86: N | L86: 7 | M86: ROTULA | N86: ROTULA ACERO | O86: ROTULA ACERO, , , | P86: 11024516 | Q86: 8961156129
A87: 79 | B87: 271452 | C87: 8 CU | D87: 10 | E87: 2 | F87: 2 | G87: 6 | H87: BPTO | I87: 4 | J87: 0 | K87: N | L87: 7 | M87: TAPA | N87: TAPA COMPUERTA FILTROS | O87: TAPA COMPUERTA FILTROS, , , | P87: 673905 | Q87: 583021331
A88: 80 | B88: 395129 | C88: 12 CU | D88: 12 | E88: 0 | F88: 0 | G88: 4 | H88: BPTO | I88: 4 | J88: 0 | K88: N | L88: 7 | M88: EJE | N88: EJE INFERIOR SOPORTE CILINDRO | O88: EJE INFERIOR SOPORTE CILINDRO, , , | P88: 72529286 | Q88: 65781741429
A89: 81 | B89: 274639 | C89: 12 CU | D89: 16 | E89: 4 | F89: 4 | G89: 8 | H89: BPTO | I89: 8 | J89: 0 | K89: N | L89: B | M89: ANILLO | N89: ANILLO V 100S | O89: ANILLO V 100S, , , | P89: 59295625 | Q89: 524447975
A90: 82 | B90: 140707 | C90: 8 CU | D90: 10 | E90: 2 | F90: 0 | G90: 4 | H90: BPTO | I90: 4 | J90: 0 | K90: N | L90: 7 | M90: BURLETE | N90: BURLETE SELLO LATERAL M1 | O90: BURLETE SELLO LATERAL M1, , , | P90: 199968 | Q90: 180233,69
A91: 83 | B91: 140715 | C91: 10 CU | D91: 16 | E91: 6 | F91: 0 | G91: 4 | H91: BPTO | I91: 6 | J91: 0 | K91: N | L91: 7 | M91: BURLETE | N91: BURLETE SELLO LATERAL M2 | O91: BURLETE SELLO LATERAL M2, , , | P91: 1506125 | Q91: 134687550625
A92: 84 | B92: 176123 | C92: 14 CU | D92: 14 | E92: 0 | F92: 15 | G92: 6 | H92: BPTO | I92: 9 | J92: 0 | K92: N | L92: 7 | M92: JUNTA | N92: JUNTA EXPANSION ERFLEX 6" | O92: JUNTA EXPANSION ERFLEX 6", , , | P92: 1503939444 | Q92: 1468112
A93: 85 | B93: 746217 | C93: 13 CU | D93: 23 | E93: 10 | F93: 0 | G93: 8 | H93: BPTO | I93: 9 | J93: 0 | K93: N | L93: 7 | M93: TUBO | N93: TUBO DN150/PN16 | O93: TUBO DN150/PN16, , , | P93: 3793409565 | Q93: 3508858823043
A94: 86 | B94: 746197 | C94: 0 CU | D94: 0 | E94: 0 | F94: 17 | G94: 8 | H94: BPTO | I94: 8 | J94: 0 | K94: N | L94: 7 | M94: VALVULA | N94: VALVULA BOLA CERAMICA 6" | O94: VALVULA BOLA CERAMICA 6", , , | P94: 55383855 | Q94: 494905505375
A95: 87 | B95: 337113 | C95: 6 CU | D95: 6 | E95: 0 | F95: 3 | G95: 0 | H95: BPTO | I95: 6 | J95: 0 | K95: N | L95: 7 | M95: VALVULA | N95: VALVULA CUCHILLO 10" | O95: VALVULA CUCHILLO 10", , , | P95: 9319577273 | Q95: 7944759297273
A96: 88 | B96: 439661 | C96: 0 CU | D96: 0 | E96: 0 | F96: 0 | G96: 1 | H96: BPTO | I96: 0 | J96: 0 | K96: R | L96: 7 | M96: REPARADO | N96: VALVULA CUCHILLO 10" | O96: VALVULA CUCHILLO 10", , , | P96: 1 | Q96: 550
A97: 89 | B97: 339911 | C97: 7 CU | D97: 7 | E97: 0 | F97: 0 | G97: 0 | H97: BPTO | I97: 4 | J97: 0 | K97: N | L97: 7 | M97: MANGA | N97: MANGA GOMA NATURAL KGD10 | O97: MANGA GOMA NATURAL KGD10, , , | P97: 1493291429 | Q97: 1339969551429
A98: 90 | B98: 746226 | C98: 0 CU | D98: 6 | E98: 6 | F98: 6 | G98: 3 | H98: BPTO | I98: 6 | J98: 3 | K98: N | L98: 7 | M98: TUBO | N98: TUBO ENTRADA | O98: TUBO ENTRADA, , , | P98: 14153,74 | Q98: 13660907013333
A99: 91 | B99: 474981 | C99: 4 CU | D99: 4 | E99: 0 | F99: 1 | G99: 2 | H99: BPTO | I99: 1 | J99: 0 | K99: N | L99: 7 | M99: DUCTO | N99: DUCTO ALIMENTACION FL005 | O99: DUCTO ALIMENTACION FL005, , , | P99: 38943825 | Q99: 3411009125
A100: 92 | B100: 474973 | C100: 3 CU | D100: 3 | E100: 0 | F100: 3 | G100: 3 | H100: BPTO | I100: 2 | J100: 0 | K100: N | L100: 7 | M100: DUCTO | N100: DUCTO ALIMENTACION FL004 | O100: DUCTO ALIMENTACION FL004, , , | P100: 3267525 | Q100: 2671477125
A101: 93 | B101: 746228 | C101: 2 CU | D101: 5 | E101: 3 | F101: 0 | G101: 1 | H101: BPTO | I101: 3 | J101: 0 | K101: N | L101: 7 | M101: TUBO | N101: TUBO FILTRATE OUTLET -RPH | O101: TUBO FILTRATE OUTLET -RPH, , , | P101: 5802686 | Q101: 5465651984
A102: 94 | B102: 746227 | C102: 5 CU | D102: 5 | E102: 0 | F102: 1 | G102: 3 | H102: BPTO | I102: 3 | J102: 1 | K102: N | L102: 7 | M102: TUBO | N102: TUBO FILTRATE OUTLET -RPH | O102: TUBO FILTRATE OUTLET -RPH, , , | P102: 2253745 | Q102: 1985264041667
A103: 95 | B103: 746229 | C103: 5 CU | D103: 5 | E103: 0 | F103: 1 | G103: 3 | H103: BPTO | I103: 3 | J103: 1 | K103: N | L103: 7 | M103: TUBO | N103: TUBO SALIDA FILTRADO | O103: TUBO SALIDA FILTRADO, , , | P103: 2514138333 | Q103: 2214945868333
A104: 96 | B104: 746230 | C104: 5 CU | D104: 5 | E104: 0 | F104: 1 | G104: 3 | H104: BPTO | I104: 3 | J104: 1 | K104: N | L104: 7 | M104: TUBO | N104: TUBO SALIDA FILTRADO | O104: TUBO SALIDA FILTRADO, , , | P104: 2655158333 | Q104: 2296073656667
A105: 97 | B105: 746240 | C105: 7 CU | D105: 7 | E105: 0 | F105: 1 | G105: 2 | H105: BPTO | I105: 4 | J105: 0 | K105: N | L105: 7 | M105: TUBO | N105: TUBO SALIDA FILTRADO | O105: TUBO SALIDA FILTRADO, , , | P105: 81283925 | Q105: 7230488,29
A106: 98 | B106: 746241 | C106: 3 CU | D106: 3 | E106: 0 | F106: 0 | G106: 1 | H106: BPTO | I106: 2 | J106: 1 | K106: N | L106: 7 | M106: TUBO | N106: TUBO SALIDA FILTRADO | O106: TUBO SALIDA FILTRADO, , , | P106: 11236595 | Q106: 98752991425
A107: 99 | B107: 746242 | C107: 4 CU | D107: 4 | E107: 0 | F107: 1 | G107: 3 | H107: BPTO | I107: 3 | J107: 2 | K107: N | L107: 7 | M107: TUBO | N107: TUBO SALIDA FILTRADO | O107: TUBO SALIDA FILTRADO, , , | P107: 2354256667 | Q107: 2070332255
...

Sheet Data
B1: Opción
B2: 1
B3: 0

Sheet Activo
A1: Length
A2: Sí
A3: No
